Workbook

Sheet 2006
A1: TT | B1: TÊN SÁCH | C1: TÁC GIẢ | D1: PHƯƠNG THỨC | E1: Lần XB | F1: SỐ LƯỢNG IN | G1: TRANG | H1: KHỔ SÁCH | I1: GIÁ BÌA | J1: Ruột | K1: Bìa | L1: Đủ Ruột + bìa | M1: Ghi chú
A2: 1 | B2: Lịch sử Chính phủ Việt Nam- T1 (1945-1955) | C2: Ban chỉ đạo biên soạn lịch sử Chính phủ Việt Nam | D2: TW ĐẶT HÀNG | F2: 1040 | G2: 454 | H2: 16x24 | I2: Không giá | J2: ko có | K2: ko có
A3: 2 | B3: Văn kiện Đảng toàn tập- Tập43 (1982) | C3: ĐCSVN | D3: TW ĐẶT HÀNG | F3: 6000 | G3: 812 | H3: 15x22 | I3: Không giá | J3: ko có | K3: ko có
A4: 3 | B4: Tệ quan liêu, lãng phí và một số giải pháp phòng, chống | C4: Ban chỉ đạo TW6(2) | D4: TW ĐẶT HÀNG | F4: 3500 | G4: 666 | H4: 15x22 | I4: 30000 | J4: ko có | K4: ko có
A5: 4 | B5: Đổi mới công tác kiểm tra, kỷ luật nhằm nâng cao sức chiến đấu của Đảng trong giai đoạn cách mạng mới | C5: GS,TS.Nguyễn Thị Doan | D5: TW ĐẶT HÀNG | F5: 1200 | G5: 316 | H5: 14,5x20,5 | I5: 30000 | J5: ko có | K5: ko có
A6: 5 | B6: Đổi mới sâu rộng, phát triển đát nước nhanh và bền vững, tiến cùng thời đại - T1 | C6: Phan Văn Khải | D6: TW ĐẶT HÀNG | F6: 2000 | G6: 536 | H6: 15x22 | I6: 45000 | J6: ko có | K6: ko có
A7: 6 | B7: Hồ Chí Minh- Biên niên tiểu sử Tập 1(1890-1929) | C7: Học viện CTQGHCM | D7: TW ĐẶT HÀNG | F7: 2000 | G7: 456 | H7: 14,5x20,5 | I7: 50000 | J7: ko có | K7: ko có
A8: 7 | B8: Văn kiện Đảng toàn tập- Tập46 (1985) | C8: ĐCSVN | D8: TW ĐẶT HÀNG | F8: 6000 | G8: 422 | H8: 15x22 | I8: Không giá | J8: ko có | K8: ko có
A9: 8 | B9: Đổi mới sâu rộng, phát triển đát nước nhanh và bền vững, tiến cùng thời đại - T2 | C9: Phan Văn Khải | D9: TW ĐẶT HÀNG | F9: 2000 | G9: 528 | H9: 15x22 | I9: 45000 | J9: ko có | K9: ko có
A10: 9 | B10: Văn kiện Đảng toàn tập- Tập45 (1984) | C10: ĐCSVN | D10: TW ĐẶT HÀNG | F10: 6000 | G10: 510 | H10: 15x22 | I10: Không giá | J10: ko có | K10: ko có
A11: 10 | B11: Kết quả Đại hội đại biểu toàn quốc lần thứ X Đảng Cộng sản Việt Nam | C11: Văn phòng TWĐCSVN | D11: TW ĐẶT HÀNG | F11: 5000 | G11: 118 | H11: 13x19 | I11: 5000 | J11: ko có | K11: ko có
A12: 11 | B12: Văn kiện Đảng toàn tập- Tập44 (1983) | C12: ĐCSVN | D12: TW ĐẶT HÀNG | F12: 6000 | G12: 480 | H12: 15x22 | I12: Không giá | J12: ko có | K12: ko có
A13: 12 | B13: Hồ Chí Minh- Biên niên tiểu sử Tập 2(1930-1945) | C13: Học viện CTQGHCM | D13: TW ĐẶT HÀNG | F13: 2000 | G13: 348 | H13: 14,5x20,5 | I13: 40000 | J13: ko có | K13: ko có
A14: 13 | B14: Đổi mới và phát triển ở Việt Nam- một số vấn đề lý luận và thực tiễn | C14: GS,TS.Nguyễn Phú Trọng | D14: TW ĐẶT HÀNG | F14: 1000 | G14: 484 | H14: 15x22 | I14: 60000 | J14: ko có | K14: ko có
A15: 14 | B15: C.Mác và Ph.ĂngGhen tuyển tập Tập 5 | D15: TW ĐẶT HÀNG | F15: 1040 | G15: 830 | H15: 15x22 | I15: 93000 | J15: ko có | K15: ko có
A16: 15 | B16: C.Mác và Ph.ĂngGhen tuyển tập Tập 6 | D16: TW ĐẶT HÀNG | F16: 1040 | G16: 846 | H16: 15x22 | I16: 95000 | J16: ko có | K16: ko có
A17: 16 | B17: Văn kiện Đại hội đại biểu toàn quốc lần thứ X | C17: ĐCSVN | D17: TW ĐẶT HÀNG | F17: 130000 | G17: 376 | H17: 13x19 | I17: Không giá | J17: ko có | K17: ko có
A18: 17 | B18: Văn kiện Đảng toàn tập- Tập47 (1986) | C18: ĐCSVN | D18: TW ĐẶT HÀNG | F18: 6000 | G18: 656 | H18: 15x22 | I18: Không giá | J18: ko có | K18: ko có
A19: 18 | B19: Việt Nam bước khởi động 5 năm đầu thế kỷ thắng lợi | C19: Trần Đức Lương | D19: TW ĐẶT HÀNG | F19: 1000 | G19: 758 | H19: 16x24 | I19: 115000 | J19: ko có | K19: ko có
A20: 19 | B20: Tham luận tại Đại hội đại biểu toàn quốc lần thứ X | C20: ĐCSVN | D20: TW ĐẶT HÀNG | F20: 5000 | G20: 444 | H20: 16x24 | I20: Không giá | J20: ko có | K20: ko có
A21: 20 | B21: Chính quyền địa phương trong nhà nước pháp quyền XHCN của dân, do dân, vì dân | C21: PGS,TS.Lê Minh Thông | D21: TW ĐẶT HÀNG | F21: 1040 | G21: 414 | H21: 19x27 | I21: 145000 | J21: ko có | K21: ko có
A22: 21 | B22: Sở hữu tư nhân và kinh tế tư nhân trong nền kinh tế thị trường định hướng XHCN ở Việt Nam | C22: GS,TS.Nguyễn Thanh Tuyền | D22: TW ĐẶT HÀNG | F22: 500 | G22: 362 | H22: 14,5x20,5 | I22: 35000 | J22: ko có | K22: ko có
A23: 22 | B23: Đồng chí Phạm Văn Xô- Người cán bộ lão thành nhân hậu, giản dị | D23: TW ĐẶT HÀNG | F23: 1000 | G23: 416 | H23: 15x22 | I23: 42000 | J23: ko có | K23: ko có
A24: 23 | B24: Văn kiện Đại hội đại biểu toàn quốc lần thứ X | C24: ĐCSVN | D24: TW ĐẶT HÀNG | F24: 10000 | G24: 376 | H24: 13x19 | I24: 20000 | J24: ko có | K24: ko có
A25: 24 | B25: Hà Huy Tập- Ngưòi cộng sản kiên trung,nhà lý luận xuất sắc | D25: TW ĐẶT HÀNG | F25: 1000 | G25: 760 | H25: 16x24 | I25: Không giá | J25: ko có | K25: ko có
A26: 25 | B26: Lịch sử Chính phủ Việt Nam- T2 (1955-1976) | C26: Ban chỉ đạo biên soạn lịch sử Chính phủ Việt Nam | D26: TW ĐẶT HÀNG | F26: 1000 | G26: 506 | H26: 16x24 | I26: Không giá | J26: ko có | K26: ko có
A27: 26 | B27: Lịch sử Chính phủ Việt Nam- T3 (1976-2005) | C27: Ban chỉ đạo biên soạn lịch sử Chính phủ Việt Nam | D27: TW ĐẶT HÀNG | F27: 1000 | G27: 592 | H27: 16x24 | I27: Không giá | J27: ko có | K27: ko có
A28: 27 | B28: Hồ Chí Minh- biên niên tiểu sử tập4 (1946-1950) | C28: Viện HCM | D28: TW ĐẶT HÀNG | F28: 2000 | G28: 562 | H28: 14,5x20,5 | I28: 60000 | J28: ko có | K28: ko có
A29: 28 | B29: Văn kiện Đảng Toàn tập Tập 48(1987) | C29: ĐCSVN | D29: TW ĐẶT HÀNG | F29: 6000 | G29: 650 | H29: 15x22 | I29: Không giá | J29: ko có | K29: ko có
A30: 29 | B30: Thể chế kinh tế thị trường định hướng XHCN ở Việt Nam | C30: PGS,TS.Hà Huy Bảo | D30: TW ĐẶT HÀNG | F30: 500 | G30: 380 | H30: 14,5x20,5 | I30: 36000 | J30: ko có | K30: ko có
A31: 30 | B31: Nông nghiệp nông thôn Việt Nam 20 năm đổi mới và phát triển | C31: Đặng Kim Sơn | D31: TW ĐẶT HÀNG | F31: 500 | G31: 244 | H31: 16x24 | I31: 32000 | J31: ko có | K31: ko có
A32: 31 | B32: Ngoại giao Việt Nam - phương sách và nghệ thuật đàm phán | C32: Nguyễn Khắc Huỳnh | D32: TW ĐẶT HÀNG | F32: 500 | G32: 396 | H32: 14,5x20,5 | I32: 37000 | J32: ko có | K32: ko có
A33: 32 | B33: Hồ Chí Minh- Biên niên tiểu sử tập 3 (1945-1946) | C33: Học viện CTQGHCM | D33: TW ĐẶT HÀNG | F33: 2000 | G33: 468 | H33: 14,5x20,5 | I33: 50000 | J33: ko có | K33: ko có
A34: 33 | B34: Đề cương bài giảng xử lý tình huống chính trị (cao cấp LLCT) | C34: Học viện CTQGHCM | D34: QUẢN LÝ PHÍ | F34: 1000 | G34: 116 | H34: 13x19 | I34: 13000 | J34: ko có | K34: ko có
A35: 34 | B35: Lịch sử Đảng bộ tỉnh Sơn La Tập III (1976-2000) | C35: BCHĐB Sơn La | D35: QUẢN LÝ PHÍ | F35: 3500 | G35: 252 | H35: 13x19 | I35: Không giá | J35: ko có | K35: ko có
A36: 35 | B36: Tìm hiểu luật bảo vệ, chăm sóc và giáo dục trẻ em năm 2004 | C36: Lg. Nguyễn Ngọc Dũng | D36: QUẢN LÝ PHÍ | F36: 1000 | G36: 48 | H36: 14,5x20,5 | I36: 6000 | J36: ko có | K36: ko có
A37: 36 | B37: Tìm hiểu luật thi đua, khen thưởng ( đã được sửa đổi ,bổ sung năm 2005) | C37: Lg. Nguyễn Ngọc Dũng | D37: QUẢN LÝ PHÍ | F37: 1000 | G37: 64 | H37: 14,5x20,5 | I37: 8000 | J37: ko có | K37: ko có
A38: 37 | B38: Tìm hiểu luật đường sắt | C38: Lg. Nguyễn Ngọc Dũng | D38: QUẢN LÝ PHÍ | F38: 1000 | G38: 96 | H38: 14,5x20,5 | I38: 12000 | J38: ko có | K38: ko có
A39: 38 | B39: Tìm hiểu luật các tổ chức tín dụng | C39: Lg. Nguyễn Ngọc Dũng | D39: QUẢN LÝ PHÍ | F39: 1000 | G39: 72 | H39: 14,5x20,5 | I39: 9000 | J39: ko có | K39: ko có
A40: 39 | B40: Tìm hiểu luật điện lực | C40: Lg. Nguyễn Văn Thung | D40: QUẢN LÝ PHÍ | F40: 1000 | G40: 72 | H40: 14,5x20,5 | I40: 9000 | J40: ko có | K40: ko có
A41: 40 | B41: Sức hấp dẫn-một giá trị văn hóa doanh nghiệp | C41: Trần Quốc Dân | D41: QUẢN LÝ PHÍ | F41: 1000 | G41: 208 | H41: 14,5x20,5 | I41: 22000 | J41: ko có | K41: ko có
A42: 41 | B42: Chính trị học-Hỏi và đáp | C42: Học viện CTQGHCM | D42: QUẢN LÝ PHÍ | F42: 1000 | G42: 254 | H42: 14,5x20,5 | I42: 25000 | J42: ko có | K42: ko có
A43: 42 | B43: Tập bài giảng kinh tế học phát triển | C43: nt | D43: QUẢN LÝ PHÍ | F43: 1000 | G43: 288 | H43: 14,5x20,5 | I43: 28000 | J43: ko có | K43: ko có
A44: 43 | B44: Biến động kinh tế Đông Á và con đường công nghiệp hóa Việt Nam | C44: GS.Trần Văn Thọ | D44: QUẢN LÝ PHÍ | F44: 1500 | G44: 310 | H44: 15,5x23,5 | I44: 65000 | J44: ko có | K44: ko có
A45: 44 | B45: Thực thi luật thương mại lành mạnh ở Đài Loan- T1 | D45: QUẢN LÝ PHÍ | F45: 530 | G45: 496 | H45: 14,5x20,5 | I45: Không giá | J45: ko có | K45: ko có
A46: 45 | B46: Thực thi luật thương mại lành mạnh ở Đài Loan- T2 | D46: QUẢN LÝ PHÍ | F46: 530 | G46: 322 | H46: 14,5x20,5 | I46: Không giá | J46: ko có | K46: ko có
A47: 46 | B47: Điều tiết thị trường- lý thuyết kinh tế và vai trò của chính phủ trong công nghiệp hóa ở Đông Á | C47: Robert Wade | D47: QUẢN LÝ PHÍ | F47: 840 | G47: 576 | H47: 15,5x23,5 | I47: Không giá | J47: ko có | K47: ko có
A48: 47 | B48: Thái Nguyên- Thế và lực mới trong thế kỷ XXI | C48: CTY Cổ phần thông tin kinh tế đối ngoại | D48: QUẢN LÝ PHÍ | F48: 1000 | G48: 680 | H48: 19x27 | I48: 75000 | J48: ko có | K48: ko có
A49: 48 | B49: Hòa Bình -Thế và lực mới trong thế kỷ XXI | C49: CTY Cổ phần thông tin kinh tế đối ngoại | D49: QUẢN LÝ PHÍ | F49: 1000 | G49: 622 | H49: 19x27 | I49: 75000 | J49: ko có | K49: ko có
A50: 49 | B50: Hà Nam- Thế và lực mới trong thế kỷ XXI | C50: CTY Cổ phần thông tin kinh tế đối ngoại | D50: QUẢN LÝ PHÍ | F50: 1000 | G50: 566 | H50: 19x27 | I50: 75000 | J50: ko có | K50: ko có
A51: 50 | B51: Tác động của Hiệp định thương mại song phương Việt Nam-Hoa Kỳ | C51: Bộ KHĐT | D51: QUẢN LÝ PHÍ | F51: 2040 | G51: 136 | H51: 21x29,5 | I51: Không giá | J51: ko có | K51: ko có
A52: 51 | B52: Địa chí Hòa Bình | C52: Tỉnh Hòa Bình | D52: QUẢN LÝ PHÍ | F52: 1330 | G52: 920 | H52: 21x29 | I52: Không giá | J52: ko có | K52: ko có
A53: 52 | B53: Sổ tay công tác ngoại giao, phục vụ phát triển kinh tế | C53: Bộ Ngoại giao | D53: QUẢN LÝ PHÍ | F53: 1310 | G53: 292 | H53: 14,5x20,5 | I53: Không giá | J53: ko có | K53: ko có
A54: 53 | B54: Đổi mới chính sách về chuyển đổi mục đích sử dụng đất đai trong quá trình công nghiệp hóa,đô thị hóa ở Việt Nam | C54: Nguyễn Quốc Hùng | D54: QUẢN LÝ PHÍ | F54: 500 | G54: 170 | H54: 13x19 | I54: 19600 | J54: ko có | K54: ko có
A55: 54 | B55: Luật giao thông đường bộ-Biển báo,Hỏi và đáp dùng cho thi….. | C55: QH | D55: QUẢN LÝ PHÍ | F55: 1040 | G55: 324 | H55: 13x19 | I55: 37000 | M55: Hết hiệu lực
A56: 55 | B56: Nghiệp vụ bao thanh toán | C56: ThS.Nguyễn Quỳnh Lan | D56: QUẢN LÝ PHÍ | F56: 500 | G56: 204 | H56: 14,5x20,5 | I56: 21000 | J56: ko có | K56: ko có
A57: 56 | B57: Người Việt Nam ở nước ngoài không chỉ có Việt kiều | C57: Trần Trọng Đăng Đoàn | D57: QUẢN LÝ PHÍ | F57: 1000 | G57: 230 | H57: 14,5x20,5 | I57: 35000 | J57: ko có | K57: ko có
A58: 57 | B58: Người Quảng Trị | C58: Hồ Sĩ Vịnh | D58: QUẢN LÝ PHÍ | F58: 600 | G58: 586 | H58: 14,5x20,5 | I58: 135000 | J58: ko có | K58: ko có
A59: 58 | B59: Lịch sử Mặt trận tổ quốc Việt Nam tỉnh Gia Lai(1930-2005) | C59: MTTQVN Tỉnh Gia Lai | D59: QUẢN LÝ PHÍ | F59: 1000 | G59: 570 | H59: 15x22 | I59: 70000 | J59: ko có | K59: ko có
A60: 59 | B60: Bí ẩn của vốn | C60: Hernando De Soto | D60: QUẢN LÝ PHÍ | F60: 1000 | G60: 308 | H60: 15,5x23,5 | I60: Không giá | J60: ko có | K60: ko có
A61: 60 | B61: Tài liệu học tập luật giao thông đường bộ….. | C61: Bộ GTVT | D61: QUẢN LÝ PHÍ | F61: 2000 | G61: 296 | H61: 13x19 | I61: 27000 | M61: Hết hiệu lực
A62: 61 | B62: Tìm hiểu luật thực hành tiết kiệm, chống lãng phí | C62: Lg.Nguyễn Ngọc Dũng | D62: QUẢN LÝ PHÍ | F62: 1000 | G62: 72 | H62: 14,5x20,5 | I62: 9500 | M62: Hết hiệu lực
A63: 62 | B63: Tìm hiểu luật sở hữu trí tuệ | C63: Lg.Nguyễn Ngọc Dũng | D63: QUẢN LÝ PHÍ | F63: 1000 | G63: 168 | H63: 14,5x20,5 | I63: 21500 | M63: Hết hiệu lực
A64: 63 | B64: Tìm hiểu luật khiếu nại, tố cáo | C64: Lg.Nguyễn Ngọc Dũng | D64: QUẢN LÝ PHÍ | F64: 1000 | G64: 72 | H64: 14,5x20,5 | I64: 8500 | M64: Hết hiệu lực
A65: 64 | B65: Hỏi và đáp luật đầu tư | C65: Lg.Nguyễn Ngọc Dũng | D65: QUẢN LÝ PHÍ | F65: 1000 | G65: 120 | H65: 14,5x20,5 | I65: 16500 | M65: Hết hiệu lực
A66: 65 | B66: Tìm hiểu luật đàu tư | C66: Lg.Nguyễn Ngọc Dũng | D66: QUẢN LÝ PHÍ | F66: 1000 | G66: 72 | H66: 14,5x20,5 | I66: 9500 | M66: Hết hiệu lực
A67: 66 | B67: Tìm hiểu pháp lệnh thú y | C67: Lg.Nguyễn Ngọc Dũng | D67: QUẢN LÝ PHÍ | F67: 1000 | G67: 80 | H67: 14,5x20,5 | I67: 10000 | M67: Hết hiệu lực
A68: 67 | B68: Tìm hiểu luật đấu thầu | C68: Lg.Nguyễn Ngọc Dũng | D68: QUẢN LÝ PHÍ | F68: 1000 | G68: 80 | H68: 14,5x20,5 | I68: 10500 | M68: Hết hiệu lực
A69: 68 | B69: Tìm hiểu luật doanh nghiệp | C69: Lg.Nguyễn Văn Thung | D69: QUẢN LÝ PHÍ | F69: 1000 | G69: 176 | H69: 14,5x20,5 | I69: 22000 | M69: Hết hiệu lực
A70: 69 | B70: Tìm hiểu luật giao dịch điện tử | C70: Lg.Nguyễn Văn Thung | D70: QUẢN LÝ PHÍ | F70: 1000 | G70: 48 | H70: 14,5x20,5 | I70: 7000 | M70: Hết hiệu lực
A71: 70 | B71: Hỏi và đáp luật đấu thầu | C71: Lg.Nguyễn Văn Thung | D71: QUẢN LÝ PHÍ | F71: 1000 | G71: 136 | H71: 14,5x20,5 | I71: 16500 | M71: Hết hiệu lực
A72: 71 | B72: Lịch sử giáo dục Hải Dương (1945-2005) | C72: Sở GDĐT Hải Dương | D72: QUẢN LÝ PHÍ | F72: 1500 | G72: 282 | H72: 14,5x20,5 | I72: Không giá | J72: ko có | K72: ko có
A73: 72 | B73: Đổi mới quản lý và hoạt động các tổ chức khoa học và công nghệ theo cơ chế doanh nghiệp | C73: TSKH.Phạm Xuân Dũng TS.Hồ Thị Mỹ Duệ | D73: QUẢN LÝ PHÍ | F73: 1000 | G73: 246 | H73: 14,5x20,5 | I73: 46000 | J73: ko có | K73: ko có
A74: 73 | B74: Lịch sử Đoàn Thanh niên Cộng sản Hồ Chí Minh và phong trào thanh niên quận Hoàn Kiếm (1930-2002) | C74: Đoàn TNCSHCM quận Hoàn Kiếm | D74: QUẢN LÝ PHÍ | F74: 500 | G74: 248 | H74: 14,5x20,5 | I74: Không giá | J74: ko có | K74: ko có
A75: 74 | B75: Du lịch Khánh Hòa từ cuối thế kỷ XIX đến nay | C75: Nguyễn Thị Kim Hoa | D75: QUẢN LÝ PHÍ | F75: 540 | G75: 164 | H75: 14,5x20,5 | I75: 37000 | J75: ko có | K75: ko có
A76: 75 | B76: Nhận biết và phòng chống dịch cúm gia cầm H5N1 | D76: QUẢN LÝ PHÍ | F76: 1000 | G76: 328 | H76: 19x27 | I76: 75000 | J76: ko có | K76: ko có
A77: 76 | B77: Thương hiệu Việt- Tập IV | D77: QUẢN LÝ PHÍ | F77: 1250 | G77: 80 | H77: 20,5x28,5 | I77: 15000 | J77: ko có | K77: ko có
A78: 77 | B78: Hỏi và đáp về luật nhà ở | C78: Lg.Nguyễn Văn Thung | D78: QUẢN LÝ PHÍ | F78: 750 | G78: 176 | H78: 14,5x20,5 | I78: 24000 | M78: Hết hiệu lực
A79: 78 | B79: Luật giao thông đường bộ và xử phạt vi phạm hành chính trong lĩnh vực giao thông đường bộ | C79: Lg.Nguyễn Văn Thung | D79: QUẢN LÝ PHÍ | F79: 1000 | G79: 144 | H79: 14,5x20,5 | I79: 18000 | M79: Hết hiệu lực
A80: 79 | B80: Tìm hiểu luật bảo vệ môi trường | C80: Lg.Vương Thị Lan Phương | D80: QUẢN LÝ PHÍ | F80: 1000 | G80: 160 | H80: 14,5x20,5 | I80: 19000 | M80: Hết hiệu lực
A81: 80 | B81: Tìm hiểu luật các công cụ chuyển nhượng | C81: Lg.Vương Thị Lan Phương | D81: QUẢN LÝ PHÍ | F81: 1000 | G81: 72 | H81: 14,5x20,5 | I81: 10000 | J81: ko có | K81: ko có
A82: 81 | B82: Tìm hiểu luật kế toán | C82: Lg.Nguyễn Ngọc Dũng | D82: QUẢN LÝ PHÍ | F82: 1000 | G82: 64 | H82: 14,5x20,5 | I82: 8000 | M82: Hết hiệu lực
A83: 82 | B83: Tìm hiểu luật phòng chống tham nhũng | C83: Lg.Nguyễn Ngọc Dũng | D83: QUẢN LÝ PHÍ | F83: 1000 | G83: 72 | H83: 14,5x20,5 | I83: 10000 | M83: Hết hiệu lực
A84: 83 | B84: Hệ thống văn bản pháp luật về thuế xuất khẩu, thuế nhập khẩu | C84: QH | D84: QUẢN LÝ PHÍ | F84: 1000 | G84: 184 | H84: 14,5x20,5 | I84: 25000 | M84: Hết hiệu lực
A85: 84 | B85: Lich sử nước ta | C85: Hồ Chí Minh | D85: QUẢN LÝ PHÍ | F85: 3000 | G85: 30 | H85: 9x13 | I85: 3500 | J85: ko có | K85: ko có
A86: 85 | B86: Bác Hồ ở Tân Trào | D86: QUẢN LÝ PHÍ | F86: 1000 | G86: 154 | H86: 13x19 | I86: 14500 | J86: ko có | K86: ko có
A87: 86 | B87: Tăng cường pháp chế XHCN trong hoạt động lập pháp, lập quy ở Việt Nam hiện nay | C87: TS.Đỗ Ngọc Hải | D87: QUẢN LÝ PHÍ | F87: 700 | G87: 278 | H87: 13x19 | I87: 25000
A88: 87 | B88: Giáo trình Mỹ học Mác- Lênin | C88: Học viện CTQGHCM | D88: QUẢN LÝ PHÍ | F88: 550 | G88: 486 | H88: 14,5x20,5 | I88: 45000
A89: 88 | B89: Ninh Thuận- Thế và lực mới trong thế kỷ XXI | C89: CTY Cổ phần thông tin kinh tế đối ngoại | D89: QUẢN LÝ PHÍ | F89: 1000 | G89: 610 | H89: 19x26,5 | I89: 75000
A90: 89 | B90: Phú Yên-Thế và lực mới trong thế kỷ XXI | C90: CTY Cổ phần thông tin kinh tế đối ngoại | D90: QUẢN LÝ PHÍ | F90: 1000 | G90: 670 | H90: 19x26,5 | I90: 75000
A91: 90 | B91: Kon Tum trên đường phát triển | C91: CTY Cổ phần thông tin kinh tế đối ngoại | D91: QUẢN LÝ PHÍ | F91: 1000 | G91: 516 | H91: 19x26,5 | I91: 75000
A92: 91 | B92: Thương hiệu Việt - III | D92: QUẢN LÝ PHÍ | F92: 1250 | G92: 96 | H92: 20,5x28,5 | I92: 20000
A93: 92 | B93: Những điểm mới của luật thương mại năm 2005 | C93: ThS.Trần Thị Bạch Dương | D93: QUẢN LÝ PHÍ | F93: 800 | G93: 160 | H93: 13x19 | I93: 15800
A94: 93 | B94: Không thể làm ngơ | C94: TS.Ngọc Đản | D94: QUẢN LÝ PHÍ | F94: 1200 | G94: 500 | H94: 14,5x20,5 | I94: 44500
A95: 94 | B95: Theo dòng thời sự | C95: Vũ Duy Thông | D95: QUẢN LÝ PHÍ | F95: 540 | G95: 400 | H95: 14,5x20,5 | I95: 45000
A96: 95 | B96: Mỹ học Mác- Lênin (tái bản có sửa chữa, bổ sung) | C96: Nguyễn Văn Đại | D96: QUẢN LÝ PHÍ | F96: 700 | G96: 248 | H96: 14,5x20,5 | I96: 27000
A97: 96 | B97: Đảng Cộng sản Việt Nam- chặng đường qua hai thế kỷ | C97: Tập thể TG | D97: QUẢN LÝ PHÍ | F97: 2000 | G97: 806 | H97: 20x28 | I97: 295000
A98: 97 | B98: Policies on attrating investment in the real estate maket in VietNam | C98: CEG Facility | D98: QUẢN LÝ PHÍ | F98: 500 | G98: 400 | H98: 14,5x20,5 | I98: Không giá
A99: 98 | B99: Tài liệu giáo dục công dân dành cho người chưa thành niên phạm tội trong các trại giam | C99: Bộ Công an Cục V26 | D99: QUẢN LÝ PHÍ | F99: 2500 | G99: 340 | H99: 14,5x20,5 | I99: Không giá
A100: 99 | B100: Giáo trình các ngành luật cơ bản trong hệ thống pháp luật Việt Nam | C100: Học viện BCTT | D100: QUẢN LÝ PHÍ | F100: 740 | G100: 354 | H100: 15,5x23,5 | I100: 34000
...

Sheet 2007
A1: TT | B1: Tên sách | C1: Tác giả | D1: Phương thức | E1: Lần xuất bản | F1: Số lượng in | G1: Trang | H1: Khổ | I1: Giá bìa | J1: Ban BT | K1: QĐXB | L1: Nơi in | M1: Ruột | N1: Bìa
A2: 1 | B2: Quy định mới về xử lý trách nhiệm vật chất đối với cán bộ công chức | C2: QH | D2: CQ | E2: 1 | F2: 1000 | G2: 72 | H2: 13x19 | I2: 8000 | J2: Pháp luật | K2: 39085 | L2: CTQG | M2: Có | N2: Ko có | O2: file word
A3: 2 | B3: Chuyện nhà- Chuyện nước | C3: Hữu Thọ | D3: CQ | E3: 1 | F3: 1000 | G3: 260 | H3: 13x19 | I3: 22000 | J3: Đảng | K3: 39085 | L3: CTQG | M3: Ko có | N3: Ko có
A4: 3 | B4: Các quy định pháp luật về tăng cường quản lý thu chi ngân sách nhà nước | C4: QH | D4: CQ | E4: 1 | F4: 700 | G4: 320 | H4: 13x19 | I4: 27000 | J4: Pháp luật | K4: 39085 | L4: CTQG | M4: Ko có | N4: Ko có
A5: 4 | B5: Văn bản hướng dẫn thi hành Bộ luật hàng hải Việt Nam năm 2005 | C5: QH | D5: CQ | E5: 1 | F5: 500 | G5: 376 | H5: 13x19 | I5: 31000 | J5: Pháp luật | K5: 39085 | L5: CTQG | M5: Ko có | N5: Ko có
A6: 5 | B6: Giáo trình lịch sử kinh tế quốc dân | C6: PGS,TS.Vũ Văn Phúc | D6: CQ | E6: 1 | F6: 700 | G6: 468 | H6: 14,5x20,5 | I6: 43000 | J6: Kinh tế | K6: 39085 | L6: Nhà in Hà Nội | M6: Có | N6: không | O6: file word
A7: 6 | B7: Bộ luật dân sự năm 2005 và văn bản hướng dẫn thi hành | C7: QH | D7: CQ | E7: 1 | F7: 1000 | G7: 504 | H7: 19x27 | I7: 87000 | J7: Pháp luật | K7: 39085 | L7: CTQG | M7: Ko có | N7: Ko có
A8: 7 | B8: Lịch sử Đảng bộ và nhân dân thị trấn Hưng Hà (1930-2005 ) | C8: BCHĐB Hưng Hà | D8: LKTG | E8: 1 | F8: 700 | G8: 296 | H8: 13x19 | I8: Không giá | J8: Đảng | K8: 39085 | L8: Công ty in Giao thông | M8: Ko có | N8: Ko có
A9: 8 | B9: Phạm Văn Đồng và ngoại giao Việt Nam | C9: Bộ Ngoại giao | D9: LKTG | E9: 1 | F9: 1200 | G9: 768 | H9: 16x24 | I9: Không giá | J9: Quốc tế | K9: 39085 | L9: Công ty in Nam Thanh | M9: Ko có | N9: Ko có
A10: 9 | B10: Lôgích chính trị Mỹ | C10: Samuel Kernell Gary C. Jacob | D10: LKTG | E10: 1 | F10: 1000 | G10: 718 | H10: 19x27 | I10: Không giá | J10: Quốc tế | K10: 39085 | L10: Nhà in Hà Nội | M10: Ko có | N10: Ko có
A11: 10 | B11: Phát triển con người ở Việt Nam 1999-2004. Những thay đổi và xu hướng chủ yếu | C11: Viện KHXH Việt Nam | D11: LKTG | E11: 1 | F11: 2040 | G11: 106 | H11: 21x28 | I11: Không giá | J11: TT In | K11: 39085 | L11: Văn hóa phẩm | M11: Ko có | N11: Ko có
A12: 11 | B12: Bác Hồ ở Tân Trào | D12: QLP | E12: TB | F12: 2000 | G12: 156 | H12: 13x19 | I12: 15000 | J12: Đảng | K12: 39085 | L12: Tiến bộ | M12: Ko có | N12: Ko có
A13: 12 | B13: Quản lý đầu tư và thương mại toàn cầu. Các kỹ năng thiết yếu để thành công trong nền kinh tế toàn cầu WTO | C13: MiGuel Pardo De Zela | D13: QLP | E13: 1 | F13: 3040 | G13: 218 | H13: 19x27 | I13: 152000 | J13: Lý luận | K13: 39085 | L13: Tiến bộ | M13: Ko có | N13: Ko có
A14: 13 | B14: Thấm nhuần tư tưởng đạo đức Hồ Chí Minh | C14: TS.Phạm Văn Khánh | D14: CQ | E14: 1 | F14: 500 | G14: 176 | H14: 13x19 | I14: 19000 | J14: Đảng | K14: 39093 | L14: CTQG | M14: Ko có | N14: Ko có
A15: 14 | B15: Văn bản pháp luật về thanh tra, kiểm tra và xử lý vi phạm hành chính trong lĩnh vực kế hoạch đầu tư | C15: QH | D15: CQ | E15: 1 | F15: 700 | G15: 324 | H15: 13x19 | I15: 32000 | J15: Pháp luật | K15: 39093 | L15: CTQG | M15: Ko có | N15: Ko có
A16: 15 | B16: Luật người Việt Nam đi làm việc ở nước ngài theo hợp đồng năm 2006 và văn bản hướng dẫn thi hành | C16: QH | D16: CQ | E16: 1 | F16: 550 | G16: 228 | H16: 13x19 | I16: 24000 | J16: Pháp luật | K16: 39093 | L16: CTQG | M16: Ko có | N16: Ko có
A17: 16 | B17: Quy điịnh mới về bảo vệ, chăm sóc và giáo dục trẻ em | C17: QH | D17: CQ | E17: 1 | F17: 600 | G17: 172 | H17: 13x19 | I17: 18000 | J17: Pháp luật | K17: 39093 | L17: CTQG | M17: Ko có | N17: Ko có
A18: 17 | B18: Quy định về công tác quy hoạch kế hoạch phát triển kinh tế-xã hội | C18: QH | D18: CQ | E18: 1 | F18: 500 | G18: 288 | H18: 13x19 | I18: 29000 | J18: Pháp luật | K18: 39093 | L18: CTQG | M18: Ko có | N18: Ko có
A19: 18 | B19: Pháp lệnh dân quân tự vệ năm 2004 và văn bản hướng dẫn thi hành | C19: QH | D19: CQ | E19: 1 | F19: 1000 | G19: 184 | H19: 13x19 | I19: 20000 | J19: Pháp luật | K19: 39093 | L19: CTQG | M19: Ko có | N19: Ko có
A20: 19 | B20: Kiểm soát tập trung kinh tế Kinh nghiệm quốc tế và thực tiễn tại Việt Nam | C20: Bộ Công thương | D20: LKTG | E20: 1 | F20: 700 | G20: 312 | H20: 14,5x20,5 | I20: Không giá | J20: Ban Nghiên cứu KHXB | K20: 39093 | L20: CTQG | M20: Có | N20: file word
A21: 20 | B21: Quy định mới về phòng chống thiên tai | C21: QH | D21: CQ | E21: 1 | F21: 700 | G21: 236 | H21: 13x19 | I21: 20000 | J21: Pháp luật | K21: 19/1/2007 | L21: CTQG | M21: Ko có | N21: Ko có
A22: 21 | B22: Quy định mới về quản lý công sở và tiêu chuẩn, định mức trụ sở-trang thiết bị, phương tiện làm việc của cơ quan-cán bộ công chức viên chức nhà nước | C22: QH | D22: CQ | E22: 1 | F22: 1000 | G22: 120 | H22: 13x19 | I22: 11000 | J22: Pháp luật | K22: 19/1/2007 | L22: CTQG | M22: Ko có | N22: Ko có
A23: 22 | B23: Quy định mới hướng dẫn quy chế vay, trả nợ nước ngoài và quản lý, sử dụng nguồn hỗ trợ phát triển chính thức (ODA) | C23: QH | D23: CQ | E23: 1 | F23: 600 | G23: 192 | H23: 13x19 | I23: 17000 | J23: Pháp luật | K23: 19/1/2007 | L23: CTQG | M23: Ko có | N23: Ko có
A24: 23 | B24: Các quy định hướng dẫn thi hành việc chuyển hợp đồng thuê đất, cấp giấy chứng nhận quyền sử dụng đất khi chuyển công ty nhà nước thành công ty cổ phần | C24: QH | D24: CQ | E24: 1 | F24: 700 | G24: 292 | H24: 13x19 | I24: 25000 | J24: Pháp luật | K24: 19/1/2007 | L24: CTQG | M24: Ko có | N24: Ko có
A25: 24 | B25: Quy định mới về tổ chức và hoạt động của lực lượng kiểm lâm | C25: QH | D25: CQ | E25: 1 | F25: 1000 | G25: 124 | H25: 13x19 | I25: 11000 | J25: Pháp luật | K25: 19/1/2007 | L25: CTQG | M25: Ko có | N25: Ko có
A26: 25 | B26: Luật bảo hiểm xã hội và các văn bản có liên quan | C26: QH | D26: CQ | E26: 1 | F26: 2000 | G26: 116 | H26: 14,5x20,5 | I26: 13000 | J26: Quốc tế | K26: 19/1/2007 | L26: XN In và Văn hóa phẩm Bến Thành | M26: Ko có | N26: Ko có
A27: 26 | B27: Những vấn đề toàn cầu hóa trong hai thập niên đầu thế kỷ XXI | C27: GS,TS.Nguyễn Trọng Chuẩn | D27: LK 1phần | E27: 1 | F27: 580 | G27: 440 | H27: 14,5x20,5 | I27: 44000 | J27: Kinh điển | K27: 19/1/2007 | L27: CTQG | M27: Ko có | N27: Ko có
A28: 27 | B28: Lịch sử chính quyền Nhà nước Việt Nam | C28: TS.Nguyễn Vũ Tiến | D28: LKTG | E28: 1 | F28: 740 | G28: 236 | H28: 13x19 | I28: 23000 | J28: Giáo khoa | K28: 19/1/2007 | L28: CTQG | M28: Ko có | N28: Ko có
A29: 28 | B29: Phát triển công nghiệp chế biến nông sản ở Việt Nam | C29: TS.Mai Thị Thanh Xuân ThS.Ngô Đăng Thành | D29: QLP | E29: 1 | F29: 530 | G29: 236 | H29: 13x19 | I29: 30000 | J29: Đảng | K29: 19/1/2007 | L29: Tiến bộ | M29: Ko có | N29: Ko có
A30: 29 | B30: Quy định về xử phạt vi phạm hành chính trong hoạt động văn hóa-thông tin và văn bản có liên quan | C30: QH | D30: QLP | E30: 1 | F30: 1000 | G30: 256 | H30: 14,5x20,5 | I30: 25000 | J30: Quốc tế | K30: 19/1/2007 | L30: XN In và Văn hóa phẩm Bến Thành | M30: Ko có | N30: Ko có
A31: 30 | B31: Luật hàng không dân dụng Việt Nam và công ước về việc thống nhất một số quy tắc liên quan tới vận chuyển hàng không quốc tế | C31: QH | D31: QLP | E31: 1 | F31: 1000 | G31: 140 | H31: 14,5x20,5 | I31: 15000 | J31: Quốc tế | K31: 19/1/2007 | L31: XN In và Văn hóa phẩm Bến Thành | M31: Ko có | N31: Ko có
A32: 31 | B32: Luật luật sư, luật trợ giúp pháp lý và các văn bản có liên quan | C32: QH | D32: QLP | E32: 1 | F32: 1000 | G32: 120 | H32: 14,5x20,5 | I32: 13000 | J32: Quốc tế | K32: 19/1/2007 | L32: XN In và Văn hóa phẩm Bến Thành | M32: Ko có | N32: Ko có
... A39: 38 | B39: Quy định mới về thương mại điện tử | C39: QH | D39: CQ | E39: 1 | F39: 600 | G39: 104 | H39: 13x19 | I39: 10000 | J39: Pháp luật | K39: 26/1/2007 | L39: CTQG | M39: Ko có | N39: Ko có
A40: 39 | B40: Luật kiểm toán nhà nước và văn bản hướng dẫn thi hành | C40: QH | D40: CQ | E40: TB | F40: 1000 | G40: 100 | H40: 13x19 | I40: 10000 | J40: Pháp luật | K40: 26/1/2007 | L40: CTQG | M40: Ko có | N40: Ko có
A41: 40 | B41: Trường Chinh- Một tư duy sáng tạo, một tài năng kiệt xuất | C41: GS.Trần Nhâm | D41: CQ | E41: 1 | F41: 1000 | G41: 812 | H41: 14,5x20,5 | I41: 73000 | J41: Lý luận | K41: 26/1/2007 | L41: CTQG | M41: Ko có | N41: Ko có
A42: 41 | B42: Mối quan hệ Đảng-Nhà nước-Dân trong cuộc sống | C42: Nguyễn Khánh | D42: CQ | E42: 1 | F42: 600 | G42: 388 | H42: 15,5x23,5 | I42: 50000 | J42: Kinh điển | K42: 26/1/2007 | L42: CTQG | M42: Ko có | N42: Ko có
A43: 42 | B43: Những nghiên cứu tâm lý học | C43: Đỗ Long | D43: CQ | E43: 1 | F43: 500 | G43: 476 | H43: 16x24 | I43: 55000 | J43: Giáo khoa | K43: 26/1/2007 | L43: Văn hóa phẩm | M43: Ko có | N43: Ko có
A44: 43 | B44: Đánh giá tiến trình APEC và tác động đối với Việt Nam | C44: TS.Hoàng Anh Tuấn | D44: LK 1phần | E44: 1 | F44: 700 | G44: 260 | H44: 14,5x20,5 | I44: 34000 | J44: Lý luận | K44: 26/1/2007 | L44: CTQG | M44: Ko có | N44: Ko có
A45: 44 | B45: Một số lời dạy và mẩu chuyện về tấm gương đạo đức của Chủ tịch Hồ Chí Minh | C45: Ban TT-VHTW | D45: LKTG | E45: 1 | F45: 5000 | G45: 232 | H45: 13x19 | I45: 10000 | J45: Giáo khoa | K45: 26/1/2007 | L45: CTQG | M45: Có | N45: Ko có | O45: file word
A46: 45 | B46: Đẩy mạnh học tập và làm theo tấm gương đạo đức Hồ Chí Minh | C46: Ban TT-VHTW | D46: LKTG | E46: 1 | F46: 10000 | G46: 112 | H46: 13x19 | I46: 5000 | J46: Giáo khoa | K46: 26/1/2007 | L46: CTQG | M46: Ko có | N46: Ko có
A47: 46 | B47: Tôn giáo và chính sách tôn giáo ở Việt Nam | C47: Ban TGCP | D47: LKTG | E47: 1 | F47: 1000 | G47: 88 | H47: 14,5x20,5 | I47: Không giá | J47: Kinh điển | K47: 26/1/2007 | L47: Văn hóa phẩm | M47: Có | N47: Ko có | O47: file word. Ko có trang chịu TN
A48: 47 | B48: nt - Tiếng Anh (Religion and Policies Regarding Religion in VietNam) | C48: Ban TGCP | D48: LKTG | E48: 1 | F48: 2000 | G48: 94 | H48: 14,5x20,5 | I48: Không giá | J48: Kinh điển | K48: 26/1/2007 | L48: Văn hóa phẩm | M48: Có | N48: Ko có | O48: file word. Ko có trang chịu TN
A49: 48 | B49: Lịch sử Đảng bộ huyện Lục Nam (1975 - 2005 ) | C49: BCHĐB huyện Lục Nam | D49: LKTG | E49: 1 | F49: 700 | G49: 304 | H49: 14,5x20,5 | I49: Không giá | J49: Đảng | K49: 26/1/2007 | L49: Tiến bộ | M49: Ko có | N49: Ko có
A50: 49 | B50: Lịch sử Đảng bộ huyện Vũ Thư (1975 - 2005 ) | C50: BCHĐB huyện Vũ Thư | D50: LKTG | E50: 1 | F50: 800 | G50: 304 | H50: 14,5x20,5 | I50: Không giá | J50: Giáo khoa | K50: 26/1/2007 | L50: CTQG | M50: Ko có | N50: Ko có
A51: 50 | B51: Lịch sử Đảng bộ và nhân dân phường Tiền Phong thành phố Thái Bình (1945 - 2005 ) | C51: BCHĐB Tiền Phong | D51: LKTG | E51: 1 | F51: 500 | G51: 308 | H51: 14,5x20,5 | I51: Không giá | J51: Lý luận | K51: 26/1/2007 | L51: Văn hóa phẩm | M51: Ko có | N51: Ko có
A52: 51 | B52: Lịch sử trường chính trị tỉnh Thái Bình (1957 - 2006 ) | C52: TU - UBND Thái Bình | D52: LKTG | E52: 1 | F52: 540 | G52: 352 | H52: 14,5x20,5 | I52: Không giá | J52: Giáo khoa | K52: 26/1/2007 | L52: CTQG | M52: Ko có | N52: Ko có
A53: 52 | B53: Sổ tay tổ chức lấy ý kiến cử tri về dự thảo luật | C53: Văn phòng QH | D53: QLP | E53: 1 | F53: 800 | G53: 56 | H53: 12x20 | I53: Không giá | J53: Ban NCKH | K53: 26/1/2007 | L53: CT In Giao thông | M53: Ko có | N53: Ko có
A54: 53 | B54: Giáo trình đạo đức học Mác-Lênin | C54: PGS;TS.Vũ Trọng Dung | D54: QLP | E54: TB | F54: 1500 | G54: 320 | H54: 14,5x20,5 | I54: 40000 | J54: Lý luận | K54: 26/1/2007 | L54: CT In Trung Sơn | M54: Ko có | N54: Ko có
A55: 54 | B55: Nhà nước cách mạng kiểu mới ở Việt Nam (1945 - 2005 ) | C55: PGS;TS.Nguyễn Trọng Phúc | D55: TWĐH | E55: 1 | F55: 500 | G55: 544 | H55: 14,5x20,5 | I55: 50000 | J55: Giáo khoa | K55: 26/1/2007 | L55: CTQG | M55: Ko có | N55: Ko có
A56: 55 | B56: Pháp lệnh người cao tuổi và văn bản hướng dẫn thi hành | C56: QH | D56: CQ | E56: 1 | F56: 500 | G56: 168 | H56: 13x19 | I56: 18000 | J56: Pháp luật | K56: 39121 | L56: CTQG | M56: Ko có | N56: Ko có
A57: 56 | B57: Các quy định mới hướng dẫn thi hành luật giáo dục năm 2005 | C57: QH | D57: CQ | E57: 1 | F57: 600 | G57: 352 | H57: 13x19 | I57: 35000 | J57: Pháp luật | K57: 39121 | L57: CTQG | M57: Ko có | N57: Ko có
A58: 57 | B58: Luật nhà ở năm 2005 và văn bản hướng dẫn thi hành | C58: QH | D58: CQ | E58: 1 | F58: 540 | G58: 416 | H58: 13x19 | I58: 40000 | J58: Pháp luật | K58: 39121 | L58: CTQG | M58: Ko có | N58: Ko có
A59: 58 | B59: Quy định mới hướng dẫn thi hành luật đầu tư năm 2005 | C59: QH | D59: CQ | E59: 1 | F59: 500 | G59: 468 | H59: 13x19 | I59: 45000 | J59: Pháp luật | K59: 39121 | L59: CTQG | M59: Ko có | N59: Ko có
A60: 59 | B60: Một số chuyên đề lịch sử Đảng Cộng sản Việt Nam - Tập II | C60: Bộ GD - ĐT | D60: CQ | E60: 1 | F60: 1000 | G60: 384 | H60: 14,5x20,5 | I60: 42000 | J60: Đảng | K60: 39121 | L60: CTQG | M60: Ko có | N60: Ko có
A61: 60 | B61: Vấn đề tôn giáo trong cách mạng Việt Nam - lý luận và thực tiễn | C61: GS,TS.Đỗ Quang Hưng | D61: CQ | E61: TB | F61: 500 | G61: 564 | H61: 14,5x20,5 | I61: 60000 | J61: Quốc tế | K61: 39121 | L61: CTQG | M61: Ko có | N61: Ko có
A62: 61 | B62: Phương thức lãnh đạo và đổi mới phương thức lãnh đạo của Đảng | C62: Nguyễn Sỹ Nồng | D62: QLP | E62: 1 | F62: 1000 | G62: 120 | H62: 14,5x20,5 | I62: 20000 | J62: CNTPHCM | K62: 39121 | L62: CTTNHH 1 thành viên Người lao động | M62: Ko có | N62: Ko có
A63: 62 | B63: Hồ Chí Minh - Biên niên sự kiện lịch sử - Tập 5 (1951-1955) | C63: Học viện CT-HCQG Hồ Chí Minh | D63: TWĐH | E63: TB | F63: 2000 | G63: 626 | H63: 14,5x20,5 | I63: 70000 | J63: Đảng | K63: 39121 | L63: Văn hoá phẩm | M63: Ko có | N63: Ko có
A64: 63 | B64: Bộ luật Lao động của nước CHXHCN Việt Nam ( Sửa đổi, bổ sung năm 2002,2006 ) | C64: QH | D64: CQ | E64: 1 | F64: 5000 | G64: 140 | H64: 13x19 | I64: 13000 | J64: Pháp luật | K64: 15/3/2007 | L64: CTQG | M64: Ko có | N64: Ko có
A65: 64 | B65: Quy định mới về áp dụng hệ thống quản lý chất lượng TCVN ISO 9001-2000 vào hoạt động của cơ quan hành chính nhà nước | C65: QH | D65: CQ | E65: 1 | F65: 500 | G65: 56 | H65: 13x19 | I65: 7000 | J65: Pháp luật | K65: 15/3/2007 | L65: CTQG | M65: Ko có | N65: Ko có
A66: 65 | B66: Pháp lệnh cựu chiến binh năm 2005 và văn bản hướng dẫn thi hành | C66: QH | D66: CQ | E66: 1 | F66: 1000 | G66: 44 | H66: 13x19 | I66: 6000 | J66: Pháp luật | K66: 15/3/2007 | L66: CTQG | M66: Ko có | N66: Ko có
A67: 66 | B67: Pháp lệnh về tổ chức và họat động, hòa giải ở cơ sở và văn bản hướng dẫn thi hành | C67: QH | D67: CQ | E67: 1 | F67: 1040 | G67: 80 | H67: 13x19 | I67: 9000 | J67: Pháp luật | K67: 15/3/2007 | L67: CTQG | M67: Ko có | N67: Ko có
A68: 67 | B68: Các văn bản hướng dẫn thi hành Bộ luật tố tụng hình sự năm 2003 | C68: QH | D68: CQ | E68: 1 | F68: 700 | G68: 648 | H68: 14,5x20,5 | I68: 50000 | J68: Pháp luật | K68: 15/3/2007 | L68: CTQG | M68: Ko có | N68: Ko có
A69: 68 | B69: Kỷ yếu hoạt động của Đoàn Đại biểu Quốc hội khóa XI tỉnh Thái Bình (2002 - 2007 ) | C69: QH | D69: LKTG | E69: 1 | F69: 420 | G69: 352 | H69: 16x24 | I69: Không giá | J69: Giáo khoa | K69: 15/3/2007 | L69: Văn hóa phẩm | M69: Ko có | N69: Ko có
A70: 69 | B70: Kỷ yếu Đoàn Đại biểu Quốc hội tỉnh Vĩnh Phúc từ khóa I đến khóa XI (1946 - 2007 ) | C70: QH | D70: LKTG | E70: 1 | F70: 500 | G70: 596 | H70: 16x24 | I70: Không giá | J70: Đảng | K70: 15/3/2007 | L70: Công ty in Tiến bộ | M70: Ko có | N70: Ko có
A71: 70 | B71: Cuộc đấu tranh chống diễn biến hòa bình trong lĩnh vực văn hóa hiện nay | C71: TS.Cù Huy Chử | D71: CQ | E71: 1 | F71: 500 | G71: 128 | H71: 13x19 | I71: 12000 | J71: Giáo khoa | K71: 22/3/2007 | L71: CTQG | M71: Ko có | N71: Ko có
A72: 71 | B72: Giáo trình lịch sử Đảng Cộng sản Việt Nam | C72: Hội đồng TW chỉ đạo biên soạn | D72: CQ | E72: TB | F72: 2000 | G72: 476 | H72: 14,5x20,5 | I72: 31000 | J72: Giáo khoa | K72: 22/3/2007 | L72: CTCP VHTH Hưng Phú | M72: Ko có | N72: Ko có
A73: 72 | B73: Báo cáo Cập nhật nghèo 2006 Nghèo và giảm nghèo ở Việt Nam giai đoạn 1993 - 2004 | C73: Viện KHXH Việt Nam | D73: CQ | E73: 1 | F73: 640 | G73: 84 | H73: 16x24 | I73: Không giá | J73: TT In | K73: 22/3/2007 | L73: CTQG | M73: Ko có | N73: Ko có
A74: 73 | B74: Bình Thuận 30 năm kháng chiến (1945 - 1975 ) | C74: Tỉnh Bình Thuận | D74: LKTG | E74: 1 | F74: 1060 | G74: 704 | H74: 15x22 | I74: Không giá | J74: TPHCM | K74: 22/3/2007 | L74: CTCP VHTH Hưng Phú | M74: Ko có | N74: Ko có
A75: 74 | B75: Các văn bản pháp luật về cạnh tranh | C75: QH | D75: QLP | E75: 1 | F75: 1000 | G75: 276 | H75: 14,5x20,5 | I75: 31000 | J75: TPHCM | K75: 22/3/2007 | L75: CTCP in Gia Định | M75: Ko có | N75: Ko có
A76: 75 | B76: Cuộc đời hoạt động cách mạng của Chủ tịch KhămTày Xiphănđon | C76: Viện Chính trị và Chính quyền quốc gia Lào | D76: TWĐH | E76: 1 | F76: 500 | G76: 100 | H76: 13x19 | I76: 10000 | J76: Quốc tế | K76: 22/3/2007 | L76: CTQG | M76: Ko có | N76: Ko có
A77: 76 | B77: Luật bầu cử đại biểu Quốc hội năm 1997, sửa đổi, bổ sung năm 2001 | C77: QH | D77: CQ | E77: 1 | F77: 6000 | G77: 120 | H77: 13x19 | I77: 12000 | J77: Pháp luật | K77: 30/3/2007 | L77: CTQG | M77: Ko có | N77: Ko có
A78: 77 | B78: Tìm hiểu luật chứng khoán | C78: TS.Phạm Thị Giang Thu | D78: CQ | E78: 1 | F78: 1200 | G78: 220 | H78: 13x19 | I78: 19000 | J78: Pháp luật | K78: 30/3/2007 | L78: CTQG | M78: Ko có | N78: Ko có
A79: 78 | B79: Luật bầu cử đại biểu Quốc hội năm 1997, sửa đổi, bổ sung năm 2001 và các văn bản hướng dẫn thi hành | C79: QH | D79: CQ | E79: 1 | F79: 1000 | G79: 328 | H79: 13x19 | I79: 27000 | J79: Pháp luật | K79: 30/3/2007 | L79: CTQG | M79: Ko có | N79: Ko có
A80: 79 | B80: Tìm hiểu pháp luật về bầu cử đại biểu Quốc hội | C80: Nguyễn Mạnh Hùng | D80: CQ | E80: 1 | F80: 500 | G80: 104 | H80: 13x19 | I80: 11000 | J80: Pháp luật | K80: 30/3/2007 | L80: CTQG | M80: Ko có | N80: Ko có
A81: 80 | B81: Luật nghĩa vụ quân sự năm 1981; sửa đổi, bổ sung các năm 1990, 1994, 2005 và văn bản mới hướng dẫn thi hành | C81: QH | D81: CQ | E81: 1 | F81: 1000 | G81: 236 | H81: 13x19 | I81: 20000 | J81: Pháp luật | K81: 30/3/2007 | L81: CTQG | M81: Ko có | N81: Ko có
A82: 81 | B82: Quy định mới về quản lý tài sản công | C82: QH | D82: CQ | E82: 1 | F82: 700 | G82: 124 | H82: 13x19 | I82: 12000 | J82: Pháp luật | K82: 30/3/2007 | L82: CTQG | M82: Ko có | N82: Ko có
A83: 82 | B83: Luật đấu thầu năm 2005 và văn bản hướng dẫn thi hành | C83: QH | D83: CQ | E83: 1 | F83: 1000 | G83: 268 | H83: 13x19 | I83: 23000 | J83: Pháp luật | K83: 30/3/2007 | L83: CTQG | M83: Ko có | N83: Ko có
A84: 83 | B84: Quy định mới về bảo đảm cơ chế giám sát đầu tư tại cộng đồng | C84: QH | D84: CQ | E84: 1 | F84: 700 | G84: 132 | H84: 13x19 | I84: 12000 | J84: Pháp luật | K84: 30/3/2007 | L84: CTQG | M84: Ko có | N84: Ko có
A85: 84 | B85: Quy định mới về bảo đảm hiệu quả trong phòng chống cháy nổ | C85: QH | D85: CQ | E85: 1 | F85: 700 | G85: 196 | H85: 13x19 | I85: 17000 | J85: Pháp luật | K85: 30/3/2007 | L85: CTQG | M85: Ko có | N85: Ko có
A86: 85 | B86: Quan hệ Nga - ASEAN trong bối cảnh quốc tế mới | C86: Viện KHXH Việt Nam | D86: LK 1phần | E86: 1 | F86: 500 | G86: 376 | H86: 14,5x20,5 | I86: 36000 | J86: Kinh tế | K86: 30/3/2007 | L86: CTQG | M86: Ko có | N86: Ko có
A87: 86 | B87: Bảo vệ, xây dựng và đổi mới đất nước | C87: Đại tướng Lê Đức Anh | D87: TWĐH | E87: 1 | F87: 3040 | G87: 576 | H87: 15x22 | I87: Không giá | J87: Quốc tế | K87: 30/3/2007 | L87: Tiến bộ | M87: Ko có | N87: Ko có
A88: 87 | B88: Dân chủ và dân chủ ở cơ sở nông thôn trong tiến trình đổi mới | C88: GS,TS.Hoàng Chí Bảo | D88: CQ | E88: 1 | F88: 1000 | G88: 256 | H88: 14,5x20,5 | I88: 25000 | J88: Lý luận | K88: 39177 | L88: CTQG | M88: Ko có | N88: Ko có
A89: 88 | B89: Cái mới trong đổi mới | C89: Hà Đăng | D89: CQ | E89: 1 | F89: 500 | G89: 788 | H89: 15x22 | I89: 83000 | J89: Đảng | K89: 39177 | L89: CTQG | M89: Có | N89: Ko có | O89: file word
A90: 89 | B90: Phấn đấu đưa nước ta cơ bản trở thành một nước công nghiệp phát triển theo hướng hiện đại vào năm 2020 | C90: PGS,TSKH. Nguyễn Văn Đặng | D90: CQ | E90: 1 | F90: 500 | G90: 764 | H90: 16x24 | I90: 100000 | J90: Quốc tế | K90: 39177 | L90: Văn hoá phẩm | M90: Ko có | N90: Ko có
A91: 90 | B91: Tư tưởng Hồ Chí Minh về tính dân tộc của văn hoá nghệ thuật | C91: TS.Lê Hữu Ái | D91: LK 1phần | E91: 1 | F91: 600 | G91: 160 | H91: 14,5x20,5 | I91: 21000 | J91: Lý luận | K91: 39177 | L91: CTQG | M91: Ko có | N91: Ko có
A92: 91 | B92: Tài liệu nghiên cứu các Nghị quyết Hội nghị lần thứ tư Ban Chấp hành Trung ương Đảng khoá X (dành cho cán bộ chủ chốt và báo cáo viên) | C92: Ban TT-VHTW | D92: LKTG | E92: 1 | F92: 10000 | G92: 120 | H92: 13x19 | I92: 5000 | J92: Giáo khoa | K92: 39177 | L92: CTQG | M92: Ko có | N92: Ko có
A93: 92 | B93: Việt Nam - WTO những cam kết liên quan đến nông daan, nông nghiệp, nông thôn và doanh nghiệp | C93: Ban TT-VHTW | D93: LKTG | E93: 1 | F93: 10000 | G93: 236 | H93: 13x19 | I93: 10000 | J93: Giáo khoa | K93: 39177 | L93: CTQG | M93: Ko có | N93: Ko có
A94: 93 | B94: Văn kiện Quốc hội Toàn tập Tập 2 (1960 - 1964 ) | C94: QH | D94: LKTG | E94: 1 | F94: 2040 | G94: 1724 | H94: 16x24 | I94: Không giá | J94: Pháp luật | K94: 39177 | L94: Văn hoá phẩm | M94: Ko có | N94: Ko có
A95: 94 | B95: Liên Xô- một từ không bao giờ quên | D95: QLP | E95: 1 | F95: 2500 | G95: 552 | H95: 14,5x20,5 | I95: 49000 | J95: Kinh điển | K95: 39177 | L95: Công ty in Giao thông | M95: Ko có | N95: Ko có
A96: 95 | B96: Pháp lệnh phòng, chống lụt, bão năm 1993; sửa đổi, bổ sung năm 2000 và Nghị định hướng dẫn thi hành | C96: QH | D96: CQ | E96: TB | F96: 540 | G96: 208 | H96: 13x19 | I96: 22000 | J96: Pháp luật | K96: 39182 | L96: CTQG | M96: Ko có | N96: Ko có
A97: 96 | B97: Luật đê điều năm 2006 và văn bản hướng dẫn thi hành | C97: QH | D97: CQ | E97: 1 | F97: 1000 | G97: 136 | H97: 13x19 | I97: 15000 | J97: Pháp luật | K97: 39182 | L97: CTQG | M97: có | N97: Ko có | O97: file word
A98: 97 | B98: Quy định mới hướng dẫn luật đấu thầu năm 2005 | C98: QH | D98: CQ | E98: 1 | F98: 600 | G98: 240 | H98: 13x19 | I98: 25000 | J98: Pháp luật | K98: 39182 | L98: CTQG | M98: có | N98: Ko có | O98: file word
A99: 98 | B99: Môn học pháp luật - Tập bài giảng dùng trong các trường trung học chuyên nghiệp và dạy nghề | C99: Bộ GD - ĐT | D99: CQ | E99: TB | F99: 4000 | G99: 308 | H99: 13x19 | I99: 22000 | J99: Pháp luật | K99: 39182 | L99: CTQG | M99: Ko có | N99: Ko có
A100: 99 | B100: Luật đấu thầu năm 2005 và văn bản hướng dẫn thi hành ( lần 2 ) | C100: QH | D100: CQ | E100: TB | F100: 1040 | G100: 480 | H100: 13x19 | I100: 46000 | J100: Pháp luật | K100: 39182 | L100: CTQG | M100: Ko có | N100: Ko có
A101: 100 | B101: Luật sửa đổi, bổ sung một số điều của luật phòng, chống tham nhũng | C101: QH | D101: LKTG | E101: 1 | F101: 1340 | G101: 72 | H101: 13x19 | I101: 9000 | J101: Pháp luật | K101: 39182 | L101: CTQG | M101: Ko có | N101: Ko có
A102: 101 | B102: Các Hiệp định thương mại khu vực trong GATT/WTO : Điều khoản XXIV và yêu cầu về thương mại nội bộ | C102: UBQG về HTKTQT | D102: LKTG | E102: 1 | F102: 600 | G102: 532 | H102: 14,5x20,5 | I102: Không giá | J102: Quốc tế | K102: 39182 | L102: Văn hoá phẩm | M102: Ko có | N102: Ko có
A103: 102 | B103: Đất nước qua những chặng đường làm báo | C103: TS.Hồng Vinh | D103: TWĐH | E103: 1 | F103: 1500 | G103: 648 | H103: 16x24 | I103: Không giá | J103: Đảng | K103: 39182 | L103: Tiến bộ | M103: có | N103: Ko có | O103: file word
A104: 103 | B104: Quy định pháp luật về bổ nhiệm, miễn nhiệm tuyển dụng, quản lý cán bộ công chức | C104: QH | D104: CQ | E104: TB | F104: 500 | G104: 466 | H104: 13x19 | I104: 38000 | J104: Pháp luật | K104: 19/4/2007 | L104: CTQG | M104: Ko có | N104: Ko có
A105: 104 | B105: Xây dựng đội ngũ cán bộ lãnh đạo, quản lý nhằm đáp ứng yêu cầu của sự nghiệp công nghiệp hoá hiện đại hoá đất nước | C105: GS,TS.Vũ Văn Hiền | D105: LK 1phần | E105: 1 | F105: 800 | G105: 268 | H105: 14,5x20,5 | I105: 26000 | J105: Giáo khoa | K105: 19/4/2007 | L105: CTQG | M105: Ko có | N105: Ko có
A106: 105 | B106: Phương thức lãnh đạo của Đảng đối với nhà nước trong điều kiện xây dựng nhà nước pháp quyền xã hội chủ nghĩa của dân do dân vì dân | C106: GS,TS.Phạm Ngọc Quang TS.Ngô Kim Ngân | D106: LK 1phần | E106: 1 | F106: 600 | G106: 308 | H106: 14,5x20,5 | I106: 30000 | J106: Kinh điển | K106: 19/4/2007 | L106: CTQG | M106: Ko có | N106: Ko có
...

Sheet 2008
A1: TT | B1: Tên sách | C1: Tác giả | D1: Phương thức | E1: Lần xuất bản | F1: Số lượng in | G1: Trang | H1: Khổ | I1: Giá bìa | J1: Ban biên tập | K1: QĐXB | L1: Nơi in | M1: Ghi chú
A2: 1 | B2: Hỏi đáp nghiệp vụ công tác Đảng dành cho Bí thư chi bộ và cấp ưy viên cơ sở | C2: PGS, TS. Đào Duy Quát PGS, TS. Phạm Văn Ninh | D2: QLP | E2: 1 | F2: 2000 | G2: 304 | H2: 14,5x20,5 | I2: 38000 | J2: KT | K2: 39453 | L2: Cty Cổ phần in 15
A3: 2 | B3: Lịch sử cuộc vận động vì các quyền dân sinh, dân chủ ở Việt Nam ( 1936 - 1939 ) | C3: Phạm Hồng Tung | D3: LKMP | E3: 1 | F3: 450 | G3: 204 | H3: 14,5x20,5 | I3: 30000 | J3: Đg | K3: 39455 | L3: CTQG
A4: 3 | B4: Dân chủ trong nghiên cứu khoa học xã hội và nhân văn: Một số vấn đề lý luận và thực tiễn | C4: GS,TS.Hoàng Chí Bảo | D4: LKMP | E4: 1 | F4: 500 | G4: 380 | H4: 14,5x20,5 | I4: 45000 | J4: KĐLL | K4: 39455 | L4: CTQG
A5: 4 | B5: Giáo trình lịch sử tỉnh Lào Cai | C5: Hội đồng Biên soạn tỉnh | D5: LKTG | E5: 1 | F5: 550 | G5: 200 | H5: 13x19 | I5: 52000 | J5: TTNCKHXB | K5: 39455 | L5: CTQG
A6: 5 | B6: Giáo trình địa lý tỉnh Lào Cai | C6: Hội đồng Biên soạn tỉnh | D6: LKTG | E6: 1 | F6: 550 | G6: 172 | H6: 13x19 | I6: 48000 | J6: QT | K6: 39455 | L6: CTQG
A7: 6 | B7: Phát triển kinh tế và bảo vệ chủ quyền biển, đảo Việt Nam | C7: Ban TGTW | D7: LKTG | E7: 1 | F7: 6000 | G7: 232 | H7: 14,5x20,5 | I7: Không giá | J7: GK | K7: 39455 | L7: Tiến Bộ
A8: 7 | B8: Những vấn đề lý luận và thực tiễn mới đặt ra trong tình hình hiện nay - Tập 1 | C8: HĐLLTW | D8: LKTG | E8: 1 | F8: 4500 | G8: 608 | H8: 14,5x20,5 | I8: 33500 | J8: QT | K8: 39455 | L8: CT In Công đoàn VN
A9: 8 | B9: Lịch sử Hội đồng nhân dân tỉnh Hà Tây ( 1946 - 2008 ) | C9: Thường trực HĐND Hà Tây | D9: LKTG | E9: 1 | F9: 1500 | G9: 606 | H9: 14,5x20,5 | I9: Không giá | J9: Văn phòng | K9: 39455 | L9: Công ty CP In Thái Nguyên
A10: 9 | B10: Luật khiếu nại tố cáo năm 1998; sửa đổi, bổ sung năm 2004, 2005 và các văn bản hướng dẫn thi hành | C10: QH | D10: TPH | E10: 1 | F10: 1370 | G10: 252 | H10: 13x19 | I10: 24500 | J10: PL | K10: 39455 | L10: CTQG
A11: 10 | B11: Tư tưởng Hồ Chí Minh về giáo dục thanh niên | C11: TS.Đoàn Nam Đàn | D11: TPH | E11: 1 | F11: 500 | G11: 252 | H11: 13x19 | I11: 25000 | J11: Đg | K11: 39455 | L11: CTQG
A12: 11 | B12: Vai trò của pháp luật trong đời sống xã hội | C12: TS.Nguyễn Minh Đoan | D12: TPH | E12: 1 | F12: 1040 | G12: 296 | H12: 13x19 | I12: 29500 | J12: PL | K12: 39455 | L12: CTQG
A13: 12 | B13: Quy định về chứng minh nhân dân và hộ chiếu | C13: QH | D13: TPH | E13: TB | F13: 1000 | G13: 136 | H13: 13x19 | I13: 15000 | J13: PL | K13: 39455 | L13: CTQG
A14: 13 | B14: Pháp lệnh thực hiện dân chủ ở xã, phường, thị trấn năm 2007 và văn bản hướng dẫn thi hành | C14: QH | D14: TPH | E14: 1 | F14: 2150 | G14: 64 | H14: 13x19 | I14: 8000 | J14: PL | K14: 39455 | L14: CTQG
A15: 14 | B15: Điều lệ Đảng Cộng sản Việt Nam | C15: ĐCSVN | D15: TPH | E15: TB | F15: 10000 | G15: 44 | H15: 12x20 | I15: 4500 | J15: Đg | K15: 39455 | L15: CTQG
A16: 15 | B16: Lược khảo về kinh nghiệm phát hiện, đào tạo và sử dụng nhân tài trong lịch sử Việt Nam | C16: Phạm Hồng Tung | D16: TPH | E16: 1 | F16: 500 | G16: 192 | H16: 14,5x20,5 | I16: 23000 | J16: Đg | K16: 39455 | L16: CTQG
A17: 16 | B17: Bóc lột - Cách nhìn và ứng xử | C17: Viện KHXHNV Quân sự | D17: TPH | E17: 1 | F17: 758 | G17: 268 | H17: 14,5x20,5 | I17: 33000 | J17: KT | K17: 39455 | L17: CTQG
A18: 17 | B18: Triết học giáo dục hiện đại | C18: Lương Vị Hùng Khổng Khang Hoa | D18: TPH | E18: 1 | F18: 473 | G18: 564 | H18: 14,5x20,5 | I18: 63000 | J18: KĐLL | K18: 39455 | L18: CTQG
A19: 18 | B19: Các văn bản pháp luật về chế độ, chính sách đối với cán bộ, công chức lực lượng vũ trang | C19: QH | D19: TPH | E19: 1 | F19: 600 | G19: 616 | H19: 14,5x20,5 | I19: 75000 | J19: PL | K19: 39455 | L19: CTQG
A20: 19 | B20: Công nghệ tiên tiến và công nghệ cao về tiến trình công nghiệp hoá hiện đại hoá ở Việt Nam | C20: TSKH Phan Xuân Dũng | D20: LKMP | E20: 1 | F20: 610 | G20: 272 | H20: 16x24 | I20: 83000 | J20: KT | K20: 39456 | L20: Nhà in Sự Thật
A21: 20 | B21: Tôn Trung Sơn cách mạng Tân Hợi và quan hệ Việt Nam - Trung Quốc | C21: Viện khoa học xã hội Việt Nam - Viện nghiên cứu Trung Quốc | D21: LKMP | E21: 1 | F21: 730 | G21: 176 | H21: 14,5x20,5 | I21: 25000 | J21: KĐLL | K21: 39456 | L21: Nhà in Sự Thật
A22: 21 | B22: Lịch sử công tác kiểm tra của Đảng bộ tỉnh Thái Bình (1930- 2008) | C22: Uỷ ban kiểm tra tỉnh uỷ Thái Bình | D22: LKTG | E22: 1 | F22: 830 | G22: 204 | H22: 14,5x20,5 | I22: 0 | J22: GK | K22: 39456 | L22: Công ty In Tiến Bộ
A23: 22 | B23: Lịch sử Tư tưởng Chính trị - xã hội Việt Nam. Từ Bắc thuộc đến thời Lý - Trần | C23: Lê Văn Quán | D23: TPH | E23: 1 | F23: 500 | G23: 324 | H23: 13x19 | I23: 34000 | J23: KĐLL | K23: 39456 | L23: Nhà in Sự Thật
A24: 23 | B24: Bộ luật tố tụng dân sự năm 2004 và Văn bản HDTH ( Tái bản có bổ sung ) | C24: QH | D24: TPH | E24: TB | F24: 680 | G24: 408 | H24: 19x27 | I24: 96000 | J24: PL | K24: 39456 | L24: Nhà in Sự Thật
A25: 24 | B25: Lịch sử phong trào nông dân và Hội nông dân tỉnh Sơn La (1940-2005) | C25: Ban chấp hành hội nông dân tỉnh Sơn La | D25: QLP | E25: 1 | F25: 1000 | G25: 380 | H25: 14,5x20,5 | I25: 0 | J25: VKHTK | K25: 39457 | L25: CTy in Cầu Giấy
A26: 25 | B26: Văn bản pháp luật về quản lý sản xuất, kinh doanh thuốc lá | C26: QH | D26: TPH | E26: 1 | F26: 180 | G26: 160 | H26: 13x19 | I26: 19000 | J26: PL | K26: 11/1/08 | L26: CTQG
A27: 26 | B27: Địa chí Hải Dương (CDROM ) | C27: Tỉnh uỷ HĐND- UBND tỉnh Hải Dương | D27: LKTG | E27: 1 | F27: 2130 | J27: KT | K27: 39459 | L27: Cty CP Đức Việt | M27: Quý IV 2008
A28: 27 | B28: Bàn về một số vấn đề ở nông thôn nước ta hiện nay | C28: GS, Hồ Văn Thông | D28: TPH | E28: 1 | F28: 410 | G28: 144 | H28: 14,5x20,5 | I28: 22000 | J28: QT | K28: 39459 | L28: Nhà in Sự Thật
A29: 28 | B29: Luật chất lượng sản phẩm, hàng hoá | C29: QH | D29: LKMP | E29: 1 | F29: 5000 | G29: 80 | H29: 13x19 | I29: 10000 | J29: PL | K29: 18/1/2008 | L29: CTQG
A30: 29 | B30: Luật phòng, chống bệnh truyền nhiễm | C30: QH | D30: LKMP | E30: 1 | F30: 4350 | G30: 56 | H30: 13x19 | I30: 8000 | J30: PL | K30: 18/1/2008 | L30: CTQG
A31: 30 | B31: Luật đặc xá | C31: QH | D31: LKMP | E31: 1 | F31: 4450 | G31: 32 | H31: 13x19 | I31: 6000 | J31: PL | K31: 18/1/2008 | L31: CTQG
A32: 31 | B32: Luật thuế thu nhập cá nhân | C32: QH | D32: LKMP | E32: 1 | F32: 6600 | G32: 36 | H32: 13x19 | I32: 6000 | J32: PL | K32: 18/1/2008 | L32: CTQG
A33: 32 | B33: Dạy và học môn tư tưởng Hồ Chí Minh theo phương pháp tích cực | C33: Nguyễn Đăng Quang | D33: LKTG | E33: TB | F33: 1540 | G33: 292 | H33: 14,5x20,5 | I33: 33000 | J33: GK | K33: 18/1/2008 | L33: CTQG
A34: 33 | B34: Nâng cao năng lực cạnh tranh của các doanh nghiệp Việt Nam trong xu thế hội nhập kinh tế quốc tế hiện nay | C34: TS.Nguyễn Hữu Thắng | D34: TPH | E34: 1 | F34: 700 | G34: 240 | H34: 14,5x20,5 | I34: 30000 | J34: GK | K34: 39465 | L34: CTQG
A35: 34 | B35: Văn bản hướng dẫn thi hành luật thống kê | C35: QH | D35: TPH | E35: 1 | F35: 410 | G35: 224 | H35: 13x19 | I35: 23000 | J35: PL | K35: 18/1/2008 | L35: CTQG
A36: 35 | B36: Tập bài giảng lịch sử nhà nước và pháp luật thế giới | C36: Ths. Nguyễn Minh Tuấn | D36: TPH | E36: 1 | F36: 670 | G36: 346 | H36: 14,5x20,5 | I36: 39000 | J36: PL | K36: 18/1/2008 | L36: CTQG
A37: 36 | B37: Tư duy kinh tế Hồ Chí Minh | C37: Cao Ngọc Thắng | D37: LKMP | E37: 1 | F37: 600 | G37: 264 | H37: 13x19 | I37: 27000 | J37: KĐLL | K37: 24/1/2008 | L37: CTQG
A38: 37 | B38: Nguyễn Đức Cảnh - Người con của giai cấp công nhân Việt Nam | C38: PGS,TS. Đức Vượng | D38: LKMP | E38: 1 | F38: 500 | G38: 172 | H38: 14,5x20,5 | I38: 22000 | J38: KĐLL | K38: 24/1/2008 | L38: CTQG
A39: 38 | B39: Giáo trình triết học Mác - Lênin Tập 1 - Chủ nghĩa duy vật biện chứng | C39: Học viện CT-HCQG Hồ Chí Minh | D39: QLP | E39: TB | F39: 540 | G39: 388 | H39: 14,5x20,5 | I39: 48000 | J39: KĐLL | K39: 24/1/2008 | L39: Công ty in Trung Sơn
A40: 39 | B40: Giáo trình triết học Mác - Lênin Tập 2 - Chủ nghĩa duy vật lịch sử | C40: Học viện CT-HCQG Hồ Chí Minh | D40: QLP | E40: TB | F40: 540 | G40: 404 | H40: 14,5x20,5 | I40: 50000 | J40: KĐLL | K40: 24/1/2008 | L40: Công ty in Trung Sơn
A41: 40 | B41: Giáo trình Mỹ học Mác - Lênin | C41: Học viện CT-HCQG Hồ Chí Minh | D41: QLP | E41: TB | F41: 1000 | G41: 486 | H41: 14,5x20,5 | I41: 60000 | J41: KĐLL | K41: 24/1/2008 | L41: Công ty in Trung Sơn
A42: 41 | B42: Về chính sách khuyến khích đầu tư ở Việt Nam | C42: PGS,TS. Trần Thị Minh Châu | D42: TPH | E42: 1 | F42: 500 | G42: 264 | H42: 14,5x20,5 | I42: 30000 | J42: GK | K42: 24/1/2008 | L42: CTQG
A43: 42 | B43: Thực hiện quốc sách Giáo dục -Đào tạo và khoa học - công nghệ trong đào tạo của học viện Chính trị Quân sự | C43: Học viện Chính trị quân sự Tạp trí GDLL Chính trị QS | D43: LKTG | E43: 1 | F43: 700 | G43: 312 | H43: 13x19 | I43: 39000 | J43: Đg | K43: 39488 | L43: Nhà in Sự Thật
A44: 43 | B44: Một số vấn đề về xây dựng Đảng trong Văn kiện Đại hội X | C44: PGS,TS. Lê Minh Thông | D44: LKMP | E44: 1 | F44: 645 | G44: 664 | H44: 14,5x20,5 | I44: 70000 | J44: KĐLL | K44: 15/2/2008 | L44: CTQG
A45: 44 | B45: Tư tưởng giải thoát trong triết học Ấn Độ | C45: PGS,TS. Doãn Chính | D45: LKMP | E45: TB | F45: 600 | G45: 204 | H45: 13x19 | I45: 21000 | J45: KĐLL | K45: 15/2/2008 | L45: CTQG
A46: 45 | B46: Một số vấn đề về xây dựng Đảng và công tác cán bộ | C46: TS.Bùi Ngọc Thanh | D46: LKTG | E46: 1 | F46: 1000 | G46: 232 | H46: 14,5x20,5 | I46: 45000 | J46: KĐLL | K46: 15/2/2008 | L46: CTQG
A47: 46 | B47: Một số hình ảnh lễ kỷ niệm 100 năm ngày thành lập tỉnh và chuyến thăm, làm việc của Tổng Bí thư Nông Đức Mạnh tại Lào Cai | C47: BCHĐB tỉnh Lào Cai | D47: LKTG | E47: 1 | F47: 950 | G47: 92 | H47: 19x26 | I47: Không giá | J47: GK | K47: 15/2/2008 | L47: Tiến Bộ
A48: 47 | B48: Lịch sử nước ta | C48: HCM | D48: QLP | E48: TB | F48: 5000 | G48: 30 | H48: 9x13 | I48: 4000 | J48: KĐLL | K48: 15/2/2008 | L48: Tiến Bộ
A49: 48 | B49: Truyền thống lịch sử, văn hoá và cách mạng huyện Thanh Trì | C49: HU-UBND huyện Thanh Trì | D49: QLP | E49: 1 | F49: 1000 | G49: 510 | H49: 14,5x20,5 | I49: Không giá | J49: Vụ KH-TKBT | K49: 15/2/2008 | L49: XN In Trung tâm TTTM
A50: 49 | B50: Tết Mậu Thân 1968 - bước ngoặt lớn của cuộc kháng chiến chống Mỹ, cứu nước | C50: PGS,TS. Hồ Khang | D50: TPH | E50: 1 | F50: 1000 | G50: 416 | H50: 14,5x20,5 | I50: 46000 | J50: Đg | K50: 15/2/2008 | L50: CTQG
A51: 50 | B51: Nguyễn Đức Cảnh - Người cộng sản kiên trung, nhà hoạt động công đoàn mẫu mực của giai cấp công nhân Việt Nam | C51: Tập thể TG | D51: TWĐH | E51: 1 | F51: 1500 | G51: 332 | H51: 14,5x20,5 | I51: Không giá | J51: Đg | K51: 15/2/2008 | L51: CTQG
A52: 51 | B52: Tập bài giảng đào tạo, bồi dưỡng kỹ năng tin học dùng cho cán bộ lãnh đạo, quản lý và giảng dạy, nghiên cứu khoa học - Tập I | C52: Học viện CT-HCQG HCM | D52: LKMP | E52: 1 | F52: 640 | G52: 268 | H52: 14,5x20,5 | I52: 32000 | J52: KT | K52: 22/2/2008 | L52: CTQG
A53: 52 | B53: Đổi mới và phát triển ở Việt Nam một số vấn đề lý luận và thực tiễn | C53: GS.TS. Nguyễn Phú Trọng | D53: LKMP | E53: 1 | F53: 620 | G53: 486 | H53: 15x22 | I53: 60000 | J53: KĐLL | K53: 22/2/2008 | L53: Tiến Bộ
A54: 53 | B54: Nghị quyết về tổ chức nhiệm vụ, quyền hạn và quy chế hoạt động của Ban chỉ đạo tỉnh, thành phố trực thuộc Trung ương về phòng, chống tham nhũng | C54: QH | D54: LKTG | E54: 1 | F54: 1340 | G54: 24 | H54: 13x19 | I54: 5000 | J54: PL | K54: 22/2/2008 | L54: CTQG
A55: 54 | B55: Nguyễn Văn Cừ - Nhà lãnh đạo lỗi lạc của cách mạng Việt Nam | C55: Đào Phiếu - Triệu Hiển | D55: LKTG | E55: 1 | F55: 500 | G55: 348 | H55: 14,5x20,5 | I55: 76000 | J55: Đg | K55: 22/2/2008 | L55: Tiến Bộ
A56: 55 | B56: Lịch sử Đảng bộ Nghệ An Tập III ( 1975 - 2005 ) | C56: BCHĐB tỉnh Nghệ An | D56: LKTG | E56: 1 | F56: 2000 | G56: 328 | H56: 14,5x20,5 | I56: Không giá | J56: Đg | K56: 22/2/2008 | L56: Tiến Bộ
A57: 56 | B57: Một số vấn đề về pháp luật dân sự Việt Nam từ thế kỷ XV đến thời Pháp thuộc | C57: Bộ Tư pháp | D57: TPH | E57: TB | F57: 420 | G57: 384 | H57: 13x19 | I57: 38000 | J57: PL | K57: 22/2/2008 | L57: CTQG
A58: 57 | B58: Quy chế tạm giữ người theo thủ tục hành chính và văn bản hướng dẫn thi hành | C58: QH | D58: TPH | E58: 1 | F58: 1150 | G58: 52 | H58: 13x19 | I58: 8000 | J58: PL | K58: 22/2/2008 | L58: CTQG
A59: 58 | B59: Luật thi đua, khen thưởng năm 2003; sửa đổi, bổ sung năm 2005 và các văn bản hướng dẫn thi hành | C59: QH | D59: TPH | E59: 1 | F59: 1290 | G59: 376 | H59: 13x19 | I59: 37000 | J59: PL | K59: 22/2/2008 | L59: CTQG
A60: 59 | B60: Hỏi - đáp về xử lý vi phạm hành chính và hình sự trong lĩnh vực giao thông đường sắt | C60: Trần Sơn | D60: TPH | E60: 1 | F60: 500 | G60: 140 | H60: 13x19 | I60: 16000 | J60: PL | K60: 22/2/2008 | L60: CTQG
A61: 60 | B61: Pháp lệnh thi hành án phạt tù năm 1993; sửa đổi, bổ sung năm 2007 | C61: QH | D61: TPH | E61: 1 | F61: 2650 | G61: 56 | H61: 13x19 | I61: 8000 | J61: PL | K61: 22/2/2008 | L61: CTQG
A62: 61 | B62: Pháp lệnh khai thác và bảo vệ công trình thuỷ lợi năm 2001 và Nghị định số 143/2003/NĐ-CP , Nghị định số 154/2007/NĐ-CP hướng dẫn chi tiết thi hành | C62: QH | D62: TPH | E62: 1 | F62: 830 | G62: 116 | H62: 13x19 | I62: 13000 | J62: PL | K62: 22/2/2008 | L62: CTQG
A63: 62 | B63: Văn bản mới hướng dẫn thi hành về nhãn hàng hoá | C63: QH | D63: TPH | E63: 1 | F63: 610 | G63: 68 | H63: 13x19 | I63: 9000 | J63: PL | K63: 22/2/2008 | L63: CTQG
A64: 63 | B64: Pháp lệnh cựu chiến binh năm 2005 và văn bản hướng dẫn thi hành | C64: QH | D64: TPH | E64: TB | F64: 980 | G64: 72 | H64: 13x19 | I64: 9000 | J64: PL | K64: 22/2/2008 | L64: CTQG
A65: 64 | B65: Luật kinh doanh bất động sản năm 2006 và văn bản hướng dẫn thi hành | C65: QH | D65: TPH | E65: 1 | F65: 1000 | G65: 136 | H65: 13x19 | I65: 16000 | J65: PL | K65: 22/2/2008 | L65: CTQG
A66: 65 | B66: Một số văn bản về quản lý đào tạo, cấp giấy phép lái xe cơ giới đường bộ | C66: QH | D66: TPH | E66: 1 | F66: 930 | G66: 140 | H66: 13x19 | I66: 16000 | J66: PL | K66: 22/2/2008 | L66: CTQG
A67: 66 | B67: Một số quy định pháp luật về thi hành án dân sự | C67: QH | D67: TPH | E67: 1 | F67: 475 | G67: 316 | H67: 14,5x20,5 | I67: 36000 | J67: PL | K67: 22/2/2008 | L67: CTQG
A68: 67 | B68: 60 năm tác phẩm sửa đổi lối làm việc | C68: Báo điện tử ĐCSVN | D68: TWĐH | E68: 1 | F68: 2000 | G68: 596 | H68: 16x24 | I68: Không giá | J68: KĐLL | K68: 22/2/2008 | L68: Tiến Bộ
A69: 68 | B69: Tri thức Đông Nam Á | C69: GS. Lương Ninh-GS,NGND Vũ Dương Ninh | D69: TWĐH | E69: 1 | F69: 2000 | G69: 944 | H69: 16x24 | I69: 250000 | J69: QT | K69: 22/2/2008 | L69: Tiến Bộ
A70: 69 | B70: Luật bình đẳng giới năm 2006 và văn bản hướng dẫn thi hành | C70: QH | D70: TPH | E70: 1 | F70: 1650 | G70: 64 | H70: 13x19 | I70: 9500 | J70: PL | K70: 39516 | L70: Nhà in Sự Thật
A71: 70 | B71: Luật chuyển quyền sử dựng đất và các văn bản hướng dẫn thi hành | C71: QH | D71: TPH | E71: 1 | F71: 1100 | G71: 148 | H71: 13x19 | I71: 18000 | J71: PL | K71: 39516 | L71: Nhà in Sự Thật
A72: 71 | B72: Quy định pháp luật về nhà chung cư * Trích các quy định của luật nhà ở, Nghị định số 90/ 2006 /NĐ- CP Hướng dẫn thi hành luật có liên quan đến nhà chung cư ... * Quyết định số 08/ 2008/QĐ- BXD ngày 28-5-2008 của Bộ Trưởng Bộ Xây Dựng về ban hành quy chế quản lý và sử dụng nhà chung cư | C72: QH | D72: TPH | E72: 1 | F72: 1000 | G72: 180 | H72: 13x19 | I72: 21000 | J72: PL | K72: 39516 | L72: Nhà in Sự Thật
A73: 72 | B73: Vì sao kinh tế thị trường là phương tiện, kinh tế nhà nước là chủ đạo? (Sách tham khảo ) | C73: Nguyễn Văn Thanh Quỹ hoà bình & PT Việt Nam | D73: TPH | E73: 1 | F73: 610 | G73: 116 | H73: 13x19 | I73: 20000 | J73: QT | K73: 39517 | L73: Nhà in Sự Thật
A74: 73 | B74: Phát triển trí tuệ và năng lực sáng tạo khoa học trong đào tạo sau đại học | C74: GS,TS. NGND Lê Văn Quang | D74: TPH | E74: 1 | F74: 660 | G74: 208 | H74: 13x19 | I74: 28000 | J74: Đg | K74: 39517 | L74: Nhà in Sự Thật
A75: 74 | B75: Xây dựng và củng cố khối đại đoàn kết dân tộc ở Tây Nguyên (Sách chuyên khảo) | C75: PGS, TS. Trương Minh Dục | D75: TPH | E75: 1 | F75: 1020 | G75: 468 | H75: 14,5x20,5 | I75: 58000 | J75: Đg | K75: 39517 | L75: Nhà in Sự Thật
A76: 75 | B76: Những đặc trưng cơ bản của bộ máy quản lý đất nước và hệ thống Chính trị nước ta. Trước thời kỳ đổi mới | C76: GS ,TSKH. Vũ Minh Giang (Chủ biên) | D76: TPH | E76: 1 | F76: 905 | G76: 292 | H76: 14,5x20,5 | I76: 39000 | J76: KĐLL | K76: 39517 | L76: Nhà in Sự Thật
A77: 76 | B77: Công tác kiểm tra, giám sát góp phần đổi mới phương thức lãnh đạo của Đảng | C77: Nguyễn Văn Chi | D77: TPH | E77: 1 | F77: 3600 | G77: 1530 | H77: 13x19 | I77: 20000 | J77: Đg | K77: 39517 | L77: Nhà in Sự Thật
A78: 77 | B78: Công tác Tư tưởng Chính trị trong phát hiện và sử lý các điểm nóng Chính trị - xã hội trên địa bàn tỉnh Đồng Nai thực trạng và giải pháp (Lưu hành nội bộ ) | C78: ThS Dương Thanh Tân TS. Nguyễn Văn Long TS. Phẩm An Ninh | D78: LKTG | E78: 1 | F78: 1000 | G78: 396 | H78: 14,5x20,5 | I78: 0 | J78: PL | K78: 39518 | L78: Cty in Tạp chí Cộng sản
A79: 78 | B79: Luật hoá chất năm 2007 và văn bản hướng dẫn thi hành | C79: QH | D79: TPH | E79: 1 | F79: 700 | G79: 164 | H79: 13x19 | I79: 19000 | J79: PL | K79: 39519 | L79: Nhà in Sự Thật
A80: 79 | B80: Khởi nghĩa giành chính quyền trong Cách mạng Tháng 8 năm 1945 ở Ninh Thuận | C80: BTGTU Ninh Thuận | D80: LKTG | E80: 1 | F80: 500 | G80: 152 | H80: 13x19 | I80: Không giá | J80: TPHCM | K80: 13/3/2008 | L80: Công ty In Hưng Phú
A81: 80 | B81: Đại biểu Hội đồng nhân dân Những điều cần biết | C81: VPQH | D81: LKTG | E81: 1 | F81: 1000 | G81: 232 | H81: 14,5x20,5 | I81: Không giá | J81: GK | K81: 13/3/2008 | L81: CTQG
A82: 81 | B82: Phạm Văn Đồng - Người con ưu tú của quê hương Quảng Ngãi | C82: Tập thể TG | D82: LKTG | E82: TB | F82: 1530 | G82: 392 | H82: 15x22 | I82: Không giá | J82: Đg | K82: 13/3/2008 | L82: Tiến Bộ
A83: 82 | B83: Mẫu soạn thảo văn bản dùng trong hoạt động quản lý nhà nước của chính quyền xã, phường, thị trấn | C83: TS. Lê Văn In | D83: QLP | E83: 1 | F83: 1000 | G83: 770 | H83: 16x24 | I83: 97000 | J83: TPHCM | K83: 13/3/2008 | L83: Công ty In Hưng Phú
A84: 83 | B84: Luật hôn nhân gia đình | C84: QH | D84: TPH | E84: TB | F84: 5800 | G84: 60 | H84: 13x19 | I84: 7000 | J84: PL | K84: 13/3/2008 | L84: CTQG
A85: 84 | B85: Luật đất đai | C85: QH | D85: TPH | E85: TB | F85: 2000 | G85: 176 | H85: 13x19 | I85: 17000 | J85: PL | K85: 13/3/2008 | L85: CTQG
A86: 85 | B86: Luật bình đẳng giới | C86: QH | D86: TPH | E86: TB | F86: 1000 | G86: 40 | H86: 13x19 | I86: 6000 | J86: PL | K86: 13/3/2008 | L86: CTQG
A87: 86 | B87: Luật hơp tác xã | C87: QH | D87: TPH | E87: TB | F87: 1000 | G87: 60 | H87: 13x19 | I87: 7000 | J87: PL | K87: 13/3/2008 | L87: CTQG
A88: 87 | B88: Luật kế toán | C88: QH | D88: TPH | E88: TB | F88: 1500 | G88: 60 | H88: 13x19 | I88: 7000 | J88: PL | K88: 13/3/2008 | L88: CTQG
A89: 88 | B89: Luật bảo vệ, chăm sóc và giáo dục trẻ em | C89: QH | D89: TPH | E89: TB | F89: 2000 | G89: 40 | H89: 13x19 | I89: 5000 | J89: PL | K89: 13/3/2008 | L89: CTQG
A90: 89 | B90: Hiến pháp nước CHXHCN Việt Nam năm 1992 ( đã được sửa đổi, bổ sung năm 2001 ) | C90: QH | D90: TPH | E90: TB | F90: 2040 | G90: 108 | H90: 13x19 | I90: 11000 | J90: PL | K90: 13/3/2008 | L90: CTQG
A91: 90 | B91: Luật doanh nghiệp | C91: QH | D91: TPH | E91: TB | F91: 2000 | G91: 208 | H91: 13x19 | I91: 20000 | J91: PL | K91: 13/3/2008 | L91: CTQG
A92: 91 | B92: Hoàn thiện thể chế kinh tế thị trường định hướng xã hội chủ nghĩa | C92: Viện nghiên cứu QLKTTW | D92: TPH | E92: 1 | F92: 1000 | G92: 176 | H92: 13x19 | I92: 17000 | J92: KT | K92: 13/3/2008 | L92: CTQG
A93: 92 | B93: Quy định pháp luật về đình công và giải quyết tranh chấp lao động | C93: QH | D93: TPH | E93: 1 | F93: 620 | G93: 180 | H93: 13x19 | I93: 16000 | J93: PL | K93: 13/3/2008 | L93: CTQG
A94: 93 | B94: Pháp lệnh vệ sinh an toàn thực phẩm và các văn bản hướng dẫn thi hành | C94: QH | D94: TPH | E94: TB | F94: 540 | G94: 332 | H94: 14,5x20,5 | I94: 38000 | J94: PL | K94: 13/3/2008 | L94: CTQG
A95: 94 | B95: Thể chế chính trị các nước châu Âu | C95: Tập thể TG | D95: TPH | E95: 1 | F95: 500 | G95: 440 | H95: 14,5x20,5 | I95: 49000 | J95: QT | K95: 13/3/2008 | L95: CTQG
A96: 95 | B96: Pháp luật về hợp đồng trong thương mại và đầu tư - những vấn đề cơ bản | C96: TS. Nguyễn Thị Dung | D96: LKMP | E96: 1 | F96: 970 | G96: 480 | H96: 14,5x20,5 | I96: 53000 | J96: PL | K96: 21/3/2008 | L96: CTQG
A97: 96 | B97: Tài liệu hỏi - đáp về các Nghị quyết Hội nghị Trung ương 6, khoá X | C97: Ban TGTW | D97: LKTG | E97: 1 | F97: 80000 | G97: 40 | H97: 13x19 | I97: 2500 | J97: GK | K97: 21/3/2008 | L97: Tiến Bộ
A98: 97 | B98: Tài liệu nghiên cứu các Nghị quyết Hội nghị Trung ương 6, khoá X ( Dành cho cán bộ chủ chốt và báo cáo viên ) | C98: Ban TGTW | D98: LKTG | E98: 1 | F98: 30000 | G98: 144 | H98: 13x19 | I98: 8600 | J98: GK | K98: 21/3/2008 | L98: CTQG
A99: 98 | B99: Tài liệu học tập các Nghị quyết Hội nghị Trung ương 6, khoá X ( Dành cho cán bộ, đảng viên cơ sở ) | C99: Ban TGTW | D99: LKTG | E99: 1 | F99: 150000 | G99: 64 | H99: 13x19 | I99: 3800 | J99: GK | K99: 21/3/2008 | L99: Tiến Bộ
A100: 99 | B100: Lịch sử triết học | C100: GS,TS. Nguyễn Hữu Vui | D100: QLP | E100: TB | F100: 2000 | G100: 648 | H100: 14,5x20,5 | I100: 55000 | J100: GK | K100: 21/3/2008 | L100: Công ty CP In Thái Nguyên
...

Sheet 2009
A1: NHÀ XUẤT BẢN CHÍNH TRỊ QUỐC GIA | E1: SÁCH XUẤT BẢN NĂM 2009
A2: VỤ KẾ HOẠCH THƯ KÝ BIÊN TẬP
A4: TT | B4: Tên sách | C4: Tác giả | D4: Phương thức | E4: Lần xuất bản | F4: Số lượng in | G4: Trang | H4: Khổ | I4: Giá bìa | J4: Ban biên tập | K4: QĐXB | L4: Nơi in | M4: Ghi chú
A5: 1 | B5: Trợ giúp pháp lý ở Việt Nam | C5: Tạ Thị Minh Lý | D5: LKTG | E5: 1 | F5: 10040 | G5: 136 | H5: 14,5x20,5 | I5: 0 | J5: PL | K5: 1/2009 | L5: Cty in Tiến Bộ
A6: 2 | B6: Hỏi - đáp về bảo hiểm thất nghiệp | C6: Lê Thanh | D6: TPH | E6: 1 | F6: 880 | G6: 144 | H6: 13x19 | I6: 18000 | J6: PL | K6: 39817 | L6: Nhà in Sự Thật
A7: 3 | B7: Con người chính trị Việt Nam truyền thống và hiện đại (Sách chuyên khảo) | C7: GS, TS. Nguyễn Văn Huyên | D7: TPH | E7: 1 | F7: 600 | G7: 368 | H7: 14,5x20,5 | I7: 48000 | J7: Đg | K7: 39820 | L7: Nhà in Sự Thật
A8: 4 | B8: Hồ Chí Minh với việc chữa bệnh làm mất dân chủ | C8: TS. Võ Văn Lộc Đại học Sài Gòn | D8: QLP | E8: 1 | F8: 1000 | G8: 278 | H8: 14,5x20,5 | I8: 55000 | J8: TPHCM | K8: 39823 | L8: Cty in Trần Phú 71-75 Hai Bà Trưng TPHCM | M8: Đã tính ĐM 2008
A9: 5 | B9: Công tác bảo vệ bí mật của Đảng, nhà nước ở các ban, cơ quan Đảng trực thuộc Trung ương. (Lưu hành nội bộ tại các ban, cơ quan Đảng, ban cán sự Đảng, Đảng đoàn và Đảng trực thuộc Trung ương (Mật ) | C9: Phan Văn Thọ | D9: TPH | E9: 1 | F9: 2000 | G9: 268 | H9: 14,5x20,5 | I9: 0 | J9: TTNCKH | K9: 13/01/2009 | L9: Nhà in Sự Thật
A10: 6 | B10: Phát huy những giá trị lịch sử, chính trị pháp lý của hiến pháp 1946 trong sự nghiệp đổi mới hiện nay (Sách tham khảo) | C10: Văn phòng Quốc hội CILRES TTTT - TViện và NCKH | D10: QLP | E10: 1 | F10: 1200 | G10: 316 | H10: 14,5x20,5 | I10: 0 | J10: QT | K10: 16/1/2009 | L10: CTy in và Xuất bản bao bì Hà Nội
A11: 7 | B11: Văn bản pháp luật về xử phạt hành chính trong lĩnh vưc du lịch khí tượng- thuỷ văn, rừng, giống cây, trồng và một số lĩnh vực khác | C11: QH | D11: TPH | E11: 1 | F11: 850 | G11: 436 | H11: 14,5x20,5 | I11: 57000 | J11: PL | K11: 16/01/2009 | L11: Nhà in Sự Thật
A12: 8 | B12: Chế định chứng cứ trong luật tố tụng hình sự Việt Nam Sách chuyên khảo (Tái bản có bổ sung) | C12: TS. Trần Quang Tiệp | D12: TPH | E12: TB | F12: 1000 | G12: 232 | H12: 13x19 | I12: 26000 | J12: PL | K12: 16/01/2009 | L12: Nhà in Sự Thật | M12: Đã tiính ĐM 2008
A13: 9 | B13: Tư tưởng ngoại giao Hồ Chí Minh | C13: Nguyễn Duy Niên | D13: TPH | E13: TB | F13: 500 | G13: 352 | H13: 14,5x20,5 | I13: 39000 | J13: QT | K13: 19/01/2009 | L13: Nhà in Hà Nội Cty sách Hà Nội
A14: 10 | B14: Hồ Chí Minh đỉnh cao truyền thống nhân trí dũng Việt Nam | C14: Nguyễn Khắc Nho | D14: TPH | E14: TB | F14: 500 | G14: 268 | H14: 13x20,50 | I14: 26000 | J14: QT | K14: 19/1/2009 | L14: Nhà In Sự Thật
A15: 11 | B15: Quy định mới về quản lý, cung cấp, sử dụng dịch vụ INTERNET, thông tin điện tử trên INTERNET. | C15: QH | D15: TPH | E15: 1 | F15: 550 | G15: 268 | H15: 13x19 | I15: 30000 | J15: PL | K15: 21/01/2009 | L15: Nhà in Sự Thật
A16: 12 | B16: Nhà nước trong hệ thống chính trị ở Việt Nam hiện nay | C16: PGS, TS. Lê Minh Quân | D16: TPH | E16: 1 | F16: 530 | G16: 168 | H16: 13x19 | I16: 20000 | J16: Đg | K16: 21/01/2009 | L16: Nhà in Sự Thật | M16: Đã tính ĐM 2008
A17: 13 | B17: Lịch sử phong trào công nhân lao động và hoạt động công đoàn tỉnh Trà Vinh (1929-2005) | C17: Liên đoàn lao động tỉnh Trà Vinh | D17: LKTG | E17: 1 | F17: 1200 | G17: 258 | H17: 14,5x20,5 | I17: 0 | J17: TPHCM | K17: 02/2009 | L17: Cty CP Văn hoá Tổng hợp Hưng Phú TPHCM
A18: 14 | B18: Giáo trình đường lối cách mạng của Đảng Cộng sản Việt Nam (Dành cho sinh viện đại học, cao đẳng khối không chuyên ngành Mác- Lênin, tư tưởng Hồ Chí Minh) | C18: Bộ Giáo dục và đào tạo | D18: QLP | E18: TB | F18: 8000 | G18: 264 | H18: 14,5x20,5 | I18: 18500 | J18: GK | K18: 02/2009 | L18: CTy CP in Nghệ An | M18: Sách in nối nộp LC
A19: 15 | B19: Giáo trình Tư tưởng Hồ Chí Minh (Dành cho sinh viên đại học, cao đẳng khối không chuyên ngành Mác- Lênin, tư tưởng Hồ Chí Minh) | C19: Bộ Giáo dục và đào tạo | D19: QLP | E19: TB | F19: 8000 | G19: 292 | H19: 14,5x20,5 | I19: 20500 | J19: GK | K19: 02/2009 | L19: CTy CP in Nghệ An | M19: Sách in nối nộp LC
A20: 16 | B20: Giáo trình những nguyên lý cơ bản của chủ nghiã Mác - Lênin (Dành cho sinh viên đại học, cao đẳng khối không chuyên ngành Mác - Lênin, tư tưởng Hồ Chí Minh) | C20: Bộ Giáo dục và đào tạo | D20: QLP | E20: TB | F20: 8000 | G20: 492 | H20: 14,5x20,5 | I20: 32500 | J20: GK | K20: 02/2009 | L20: Xí nghiệp in Tổng cục Công nghiệp Quốc phòng | M20: Sách in nối nộp LC
A21: 17 | B21: Giáo trình Tư tưởng Hồ Chí Minh (Dành cho sinh viên đại học, cao đẳng khối không chuyên ngành Mác- Lênin, tư tưởng Hồ Chí Minh) | C21: Bộ Giáo dục và đào tạo | D21: QLP | E21: 1 | F21: 20000 | G21: 292 | H21: 14,5x20,5 | I21: 20500 | J21: GK | K21: 02/2009 | L21: XN in ACS Việt Nam Dương Kinh Hải Phòng
A22: 18 | B22: Văn kiện Hội nghị lần thứ chín ban chấp hành Trung ương khoá X (Lưu hành nội bộ) | C22: Đảng Cộng sản Việt Nam | D22: TWĐH | E22: 1 | F22: 30040 | G22: 312 | H22: 13x19 | I22: 0 | J22: Đg | K22: 2/2009 | L22: Nhà in Sự Thật
A23: 19 | B23: 101 câu hỏi và trả lời về công tác tổ chức, kiểm tra của Đảng | C23: Hà Văn Thuật | D23: TPH | E23: 1 | F23: 1000 | G23: 332 | H23: 12x20,5 | I23: 44000 | J23: Đg | K23: 39847 | L23: Nhà in Sự Thật
A24: 20 | B24: Luật quản lý thuế năm 2006 và văn bản hướng dẫn thi hành | C24: QH | D24: TPH | E24: 1 | F24: 650 | G24: 784 | H24: 15x22 | I24: 114000 | J24: PL | K24: 39847 | L24: Nhà in Sự Thật
A25: 21 | B25: Địa chí Thái Nguyên | C25: Tỉnh uỷ - HĐND- UBND tỉnh Thái Nguyên | D25: LKTG | E25: 1 | F25: 2050 | G25: 1154 | H25: 21x29 | I25: 0 | J25: Đg | K25: 39848 | L25: Cty in và Văn hoá phẩm
A26: 22 | B26: Kỷ yếu hội nghị sơ kết 2 năm thực hiện cuộc vận động học tập và làm theo tấm gương đạo đức Hồ Chí Minh | C26: Ban chỉ đạo Trung ương cuộc vận động học tập và làm theo tấm gương đạo đức Hồ Chí Minh | D26: LKTG | E26: 1 | F26: 3030 | G26: 264 | H26: 13x19 | I26: 0 | J26: GK | K26: 39848 | L26: Cty in Thương mại Thông tấn xã Việt Nam
A27: 23 | B27: Luật phòng, chống ma tuý năm 2000 (Sửa đổi, bổ sung năm 2008) | C27: QH | D27: TPH | E27: 1 | F27: 1450 | G27: 92 | H27: 13x19 | I27: 12000 | J27: PL | K27: 39848 | L27: Nhà In Sự Thật
A28: 24 | B28: Sơn Tây - Thuận Hoá và anh hùng dân tộc Nguyễn Huệ Quang Trung | C28: Hội Khoa học lịch sử thừa thiên huế | D28: TPH | E28: 1 | F28: 780 | G28: 484 | H28: 14,5x20,5 | I28: 63000 | J28: Đg | K28: 39851 | L28: Nhà in Sự Thật
A29: 25 | B29: Một số vấn đề về quản lý Nhà Nước trong nền kinh tế thị trường định hướng xã hội chủ nghĩa ở Việt Nam (Sách tham khảo) | C29: GS, TS. Từ Điển | D29: TPH | E29: 1 | F29: 500 | G29: 340 | H29: 14,5x20,5 | I29: 45000 | J29: GK | K29: 39851 | L29: Nhà in Sự Thật
A30: 26 | B30: Hỏi - Đáp về luật phòng, chống bạo lực gia đình | C30: Lan Anh | D30: TPH | E30: 1 | F30: 1150 | G30: 116 | H30: 13x19 | I30: 15000 | J30: PL | K30: 39851 | L30: Nhà in Sự Thật
A31: 27 | B31: Nhà nước cách mạng Việt Nam những năm 1945 - 1946 những sách tạo của Hồ Chí Minh | C31: TS. Lê Phương Thảo | D31: QLP | E31: 1 | F31: 300 | G31: 204 | H31: 14,5x20,5 | I31: 45000 | J31: GK | K31: 39855 | L31: Công ty in Giao thông | M31: Báo cáo QIV
A32: 28 | B32: Hồ Chí Minh trong ký ức bạn bè Quốc Tế | C32: Đỗ Hoàng Linh Phạm Hoàng Hiệp (Biên soạn) | D32: TPH | E32: 1 | F32: 700 | G32: 204 | H32: 14,5x20,5 | I32: 29000 | J32: QT | K32: 39855 | L32: Nhà in Sự Thật
A33: 29 | B33: Hồ Chí Minh từ Pác Bó đến Ba Đình | C33: Đỗ Hoàng Ninh (Biên soạn) | D33: TPH | E33: 1 | F33: 500 | G33: 296 | H33: 14,5x20,5 | I33: 40000 | J33: QT | K33: 13/02/2009 | L33: Nhà In Sự Thật
A34: 30 | B34: Tài liệu Học tập Chính trị dành cho học viên lớp bồi dưỡng kết nạp Đảng (Tái bản có sửa chữa bổ sung) | C34: Ban tuyên giáo Trung ương | D34: TPH | E34: TB | F34: 8000 | G34: 192 | H34: 13x19 | I34: 15500 | J34: GK | K34: 17/02/2009 | L34: Nhà in Sự Thật
A35: 31 | B35: Học thuyết phạm trù trong triết học Mác- Lênin | C35: Lê Công Sự , Hoàng Thị Hạnh | D35: TPH | E35: 1 | F35: 820 | G35: 284 | H35: 15x22 | I35: 44000 | J35: GK | K35: 17/02/2009 | L35: Nhà in Sự thật
A36: 32 | B36: Phong trào công nhân quốc tế - Những vấn đề lịch sử và lý luận. Tập III | C36: Hội đồng xuất bản | D36: TWĐH | E36: 1 | F36: 1000 | G36: 1180 | H36: 15x22 | I36: 167000 | J36: KĐLL | K36: 17/02/2009 | L36: Cty in Tiến Bộ
A37: 33 | B37: Phong trào công nhân quốc tế - Những vấn đề lịch sử và lý luận. Tập IV | C37: Hội đồng xuất bản | D37: TWĐH | E37: 1 | F37: 1000 | G37: 1344 | H37: 15x22 | I37: 174000 | J37: KĐLL | K37: 17/02/2009 | L37: Cty in Tiến Bộ
A38: 34 | B38: Xử lý văn bản quản lý hành chính nhà nước khiếm khuyết (Sách chuyên khảo) | C38: TS. Nguyễn Thế Quyền | D38: QLP | E38: 1 | F38: 2000 | G38: 412 | H38: 14,5x20,5 | I38: 60000 | J38: PL | K38: 18/02/2009 | L38: CTy in Tổng hợp Cầu Giấy
A39: 35 | B39: Các vùng, tỉnh , thành phố trực thuộc Trung ương: Tiềm năng và triển vọng đến năm 2020 | C39: Bộ kế hoạch và đầu tư viện chiến lược phát triển | D39: QLP | E39: 1 | F39: 500 | G39: 690 | H39: 20,5x26,5 | I39: 45000 | J39: KT | K39: 18/02/2009 | L39: Nhà in Sự Thật
A40: 36 | B40: Vấn đề nông nghiệp, nông dân, nông thôn - kinh nghiệm của Việt Nam, kinh nghiệm của Trung Quốc (Sách tham khảo) | C40: GS. TS Phùng Hữu Phú TS. Nguyễn Viết Thông TS. Bùi Văn Thông | D40: LKTG | E40: 1 | F40: 5000 | G40: 500 | H40: 15x22 | I40: 32000 | J40: QT | K40: 19/02/2009 | L40: Cty in Tiến Bộ
A41: 37 | B41: Lịch sử bộ đội biên phòng tỉnh Bình Phước (1975-2005) | C41: Bộ Tư lệnh bộ đội biên phòng Bộ chỉ huy bộ đội biên phòng tỉnh Bình Phước | D41: LKTG | E41: 1 | F41: 800 | G41: 418 | H41: 14,5x20,5 | I41: 0 | J41: TPHCM | K41: 20/02/2009 | L41: Cty CP Hưng Phú TP- HCM
A42: 38 | B42: Pháp lệnh khai thác và bảo vệ công trình thuỷ lợi năm 2001 và các Nghị định hướng dẫn thi hành | C42: QH | D42: TPH | E42: 1 | F42: 600 | G42: 196 | H42: 13x19 | I42: 23000 | J42: PL | K42: 20/2/2009 | L42: Nhà in Sự thật
A43: 39 | B43: Nghệ thuật truyền thống Đông Nam Á (Tái bản lần thứ nhất) | C43: Nguyễn Phan Thọ | D43: TPH | E43: TB | F43: 400 | G43: 360 | H43: 13x19 | I43: 39000 | J43: GK | K43: 20/2/2009 | L43: Nhà in Sự thật
A44: 40 | B44: Bước đầu tìm hiểu những giá trị văn hoá chính trị truyền thống Việt Nam | C44: GS.TS. Nguyễn Văn Huyên, TS. Nguyễn Hoài Văn, PGS,TS Nguyễn Văn Vĩnh | D44: TPH | E44: 1 | F44: 560 | G44: 224 | H44: 14,5x20,5 | I44: 32000 | J44: KĐLL | K44: 20/2/2009 | L44: Nhà in Sự thật | M44: Đã tính ĐM 2008
A45: 41 | B45: Pháp lệnh xử lý vi phạm hành chính và các quy định về xử phạt vi phạm hành chính trong hoạt động thương mại và hành vi gian lận thương mại | C45: QH | D45: TPH | E45: 1 | F45: 1000 | G45: 248 | H45: 14,5x20,5 | I45: 34000 | J45: PL | K45: 20/2/2009 | L45: Nhà in Sự thật
A46: 42 | B46: Quy định pháp luật về bảo hiểm bắt buộc trách nhiệm dân sự của chủ xe cơ giới * Nghị định số 103/2008/NĐ- CP ngày 16-9-2008 về bảo hiểm bắt buộc trách nhiệm dân sự của chủ xe cơ giới * Các văb bản hướng dãn thi hành Nghị định số 103/ 2009/ NĐ- CP | C46: QH | D46: TPH | E46: 1 | F46: 500 | G46: 144 | H46: 13x19 | I46: 17000 | J46: PL | K46: 21/2/2009 | L46: Nhà in Sự Thật
A47: 43 | B47: Lịch sử đảng bộ tỉnh Gia Lai (1945-2005) | C47: Ban chấp hành đảng bộ tỉnh Gia Lai | D47: LKTG | E47: 1 | F47: 2000 | G47: 850 | H47: 19x27 | I47: 0 | J47: TPHCM | K47: 23/02/2009 | L47: Cty CP Văn hoá Tổng hợp Hưng Phú TPHCM
A48: 44 | B48: Cơ sở cho phát triển nông thôn theo vùng ở Tây Nguyên (Sách tham khảo) | C48: AECL- ETEA- AIDA Khoa KT Đại học Tây Nguyên | D48: LKTG | E48: 1 | F48: 300 | G48: 410 | H48: 15x22 | I48: 0 | J48: TPHCM | K48: 23/02/2009 | L48: Cty Văn hoá Tổng hợp Hưng Phú - TP HCM
A49: 45 | B49: Phạm Văn Đồng Tuyển tập (1976-2000). Tập III | C49: Hội đồng chỉ đạo xuất bản | D49: TWĐH | E49: 1 | F49: 1500 | G49: 1144 | H49: 15x22 | I49: 0 | J49: Đg | K49: 23/02/2009 | L49: Cty in Tiến Bộ
A50: 46 | B50: Pháp lệnh sửa đổi 10 điều của pháp lệnh dân số | C50: QH | D50: LKTG | E50: 1 | F50: 1350 | G50: 40 | H50: 13x19 | I50: 7000 | J50: PL | K50: 24/2/2009 | L50: Nhà in Sự thật | M50: Báo cáo QI
A51: 47 | B51: Pháp lệnh sửa đổi điều 10 của pháp lệnh dân số | C51: QH | D51: LKTG | E51: 1 | F51: 1350 | G51: 40 | H51: 13x19 | I51: 7000 | J51: PL | K51: 24/02/2009 | L51: Nhà in Sự Thật | M51: kho nộp 2 lần
A52: 48 | B52: Nguyễn Ái Quốc với việc truyền bá chủ nghĩa Mác- Lênin ở Việt Nam (1921-1930) | C52: PGS, TS. Phạm Xanh | D52: TPH | E52: TB | F52: 500 | G52: 252 | H52: 14,5x20,5 | I52: 35000 | J52: Đg | K52: 24/02/2009 | L52: Nhà in Sự Thật
A53: 49 | B53: Quy định về áp dụng biện pháp đưa vào cơ sở giáo dục, giáo dưỡng | C53: QH | D53: TPH | E53: 1 | F53: 900 | G53: 224 | H53: 13x19 | I53: 26000 | J53: PL | K53: 24/02/2009 | L53: Nhà in Sự Thật
A54: 50 | B54: Nâng cao năng lực lãnh đạo của cán bộ nữ trong hệ thống chính trị | C54: Nguyễn Đức Hạt | D54: TPH | E54: 1 | F54: 1000 | G54: 380 | H54: 14x20,5 | I54: 42000 | J54: KĐLL | K54: 27/02/2009 | L54: Nhà in Sự Thật
A55: 51 | B55: Quá trình đổi mới, tư duy lý luận của đảng từ năm 1986 đến nay | C55: Học viện chính trị - hành chính quốc gia Hồ Chí Minh | D55: TPH | E55: TB | F55: 1000 | G55: 528 | H55: 16x24 | I55: 78000 | J55: KĐLL | K55: 27/02/2009 | L55: Nhà in Sự thật
A56: 52 | B56: Tìm hiểu về quyền và nghĩa vụ bảo vệ môi trường của doanh nghiệp trong hoạt động sản xuất, kinh doanh | C56: Bộ Tư pháp viện khoa học pháp lý | D56: TPH | E56: 1 | F56: 560 | G56: 548 | H56: 16x24 | I56: 94000 | J56: PL | K56: 27/2/2009 | L56: Nhà in Sự Thật
A57: 53 | B57: Đổi mới kinh tế tập thể giai đoạn 2002-2007 | C57: Ngô Văn Dụ PGS, TS. Nguyễn Văn Thạo TS. Nguyễn Tiến Quang (Đồng chủ biên) | D57: LKTG | E57: 1 | F57: 1200 | G57: 484 | H57: 15x22 | I57: 60000 | J57: QT | K57: 03/2009 | L57: Nhà in Sự thật
A58: 54 | B58: Ô Châu cận lục | C58: Dương Văn An | D58: LKTG | E58: 1 | F58: 500 | G58: 430 | H58: 16x24 | I58: 120000 | J58: KĐLL | K58: 3/2009 | L58: Cty cổ phần in Dịch vụ TT Huế
A59: 55 | B59: Văn kiện Quốc Hội toàn tập 5 1976-1981 | C59: QH Nước Cộng hoà xã hội chủ nghĩa Việt Nam | D59: LKTG | E59: 1 | F59: 1640 | G59: 1544 | H59: 16x24 | I59: 0 | J59: PL | K59: 3/2009 | L59: Cty in Tiến Bộ, Hà Nội
A60: 56 | B60: Lịch sử Đảng bộ tỉnh Bình Phước (1975-2005) | C60: Đảng Cộng sản Việt Nam Ban chấp hảnh Đảng bộ tỉnh Bình Phước | D60: LKTG | E60: 1 | F60: 1000 | G60: 426 | H60: 14,5x20,5 | I60: 0 | J60: TPHCM | K60: 3/2009 | L60: Cty CP Văn hoá Tổng hợp Hưng Phú TPHCM
A61: 57 | B61: Bình luận khoa học bộ luật dân sự năm 2005 (Tâp II) Phần thứ ba: Nghĩa vụ dân sự và hợp đồng dân sự | C61: Bộ Tư pháp viện khoa học pháp lý PGS, TS. Hoàng Thế Liên | D61: TPH | E61: 1 | F61: 2200 | G61: 808 | H61: 16x24 | I61: 135000 | J61: PL | K61: 3/2009 | L61: Nhà in Hà Nội Cty sách Hà Nội
A62: 58 | B62: Cơ chế giám sát của nhân dân đối với hoạt động của bộ máy Đảng và nhà nước . Một số vấn đề lý luận và thực tiễn | C62: GSTSKH. Đào Trí Úc | D62: TPH | E62: 1 | F62: 560 | G62: 368 | H62: 14,5x20,5 | I62: 49000 | J62: KĐLL | K62: 39874 | L62: Nhà in Sự Thật
A63: 59 | B63: Đảng Công sản Việt Nam lãnh đạo công cuộc đổi mới | C63: Bùi Kim Đỉnh HVBCTT | D63: TPH | E63: 1 | F63: 1300 | G63: 248 | H63: 14,5x20,5 | I63: 34000 | J63: KĐLL | K63: 39874 | L63: Nhà in Sự Thật | M63: Đã tính ĐM 2008
A64: 60 | B64: Tư tưởng nhân văn Hồ Chí Minh với việc giáo dục đội ngũ cán bộ, đảng viên hiện nay | C64: PGS, TS. Hoàng Trang - PGS, TS. Phạm Ngọc Anh | D64: TPH | E64: TB | F64: 500 | G64: 288 | H64: 14,5x20,5 | I64: 32000 | J64: Đg | K64: 39874 | L64: Nhà in Sự Thật
A65: 61 | B65: Lê Quang Đạo tuyển tập | C65: Hội đồng biên soạn | D65: TWĐH | E65: 1 | F65: 1000 | G65: 854 | H65: 15x22 | I65: 0 | J65: QT | K65: 39874 | L65: Nhà in Sự thật | M65: Đã tình ĐM 2008
A66: 62 | B66: Việt Nam sau một năm gia nhập WTO tăng trưởng và việc làm (Sách tham khảo) | C66: Jean - Pierre Cling Ste'phane Lagre'e Mirelle Razafindrakoto Francois Roubud | D66: LKTG | E66: 1 | F66: 740 | G66: 160 | H66: 14,5x20,5 | I66: 52000 | J66: PL | K66: 39878 | L66: Công ty in tạp Chí Cộng sản
A67: 63 | B67: Luật kinh doanh Việt Nam (Dùng trong các trường đại học cao đẳng )Tập 1 | C67: TS. Lê Minh Toàn | D67: TPH | E67: 1 | F67: 1350 | G67: 416 | H67: 14,5x20,5 | I67: 55000 | J67: KT | K67: 39878 | L67: Nhà in Sự Thật
A68: 64 | B68: Quy hoạch cán bộ lãnh đạo quản lý | C68: TS. Đỗ Minh Cường | D68: TPH | E68: 1 | F68: 1000 | G68: 288 | H68: 14,5x20,5 | I68: 39000 | J68: KĐLL | K68: 39878 | L68: Nhà in Sự Thật
A69: 65 | B69: Thực hiện và áp dụng pháp luật ở Việt Nam (Sách chuyên khảo) | C69: TS. Nguyễn Minh Đoan | D69: TPH | E69: 1 | F69: 600 | G69: 164 | H69: 13x19 | I69: 20000 | J69: PL | K69: 39878 | L69: Nhà in Sự Thật
A70: 66 | B70: Vai trò của pháp luật trong đời sống xã hội (Sách tham khảo) | C70: TS. Nguyễn minh Đoan | D70: TPH | E70: 1 | F70: 500 | G70: 320 | H70: 13x19 | I70: 35000 | J70: PL | K70: 39878 | L70: Nhà in Sự Thật
A71: 67 | B71: Làng Tây Hồ - Phủ Tây Hồ (Sách tham khảo) | C71: Hoàng Giáp - Trương Công Đức | D71: LKTG | E71: 1 | F71: 2000 | G71: 200 | H71: 13x19 | I71: 28000 | J71: QT | K71: 39879 | L71: Nhà in Sự Thật
A72: 68 | B72: Luật quy hoạch đô thị | C72: QH | D72: TPH | E72: 1 | F72: 5000 | G72: 68 | H72: 13x19 | I72: 10000 | J72: PL | K72: 39879 | L72: Nhà in Sự Thật
A73: 69 | B73: Bộ luật hình sự năm 1999 được sửa đổi, bổ sung năm 2009 | C73: QH | D73: TPH | E73: 1 | F73: 7100 | G73: 320 | H73: 13x19 | I73: 35000 | J73: PL | K73: 39879 | L73: Cty in Tạp chí Cộng sản
A74: 70 | B74: Luật lý lịch tư pháp | C74: QH | D74: TPH | E74: 1 | F74: 6100 | G74: 48 | H74: 13x19 | I74: 8500 | J74: PL | K74: 39879 | L74: Nhà in Sự Thật
A75: 71 | B75: Luật cơ quan đại diện Nước Cộng hoà xã hội chủ nghĩa Việt Nam ở nước ngoài | C75: QH | D75: TPH | E75: 1 | F75: 3750 | G75: 36 | H75: 13x19 | I75: 7000 | J75: PL | K75: 39879 | L75: Nhà in Hà Nội Cty sách Hà Nội
A76: 72 | B76: Luật sửa đổi, bổ sung một số điều của các luật liên quan đến đầu tư xây dựng cơ bản | C76: QH | D76: TPH | E76: 1 | F76: 2300 | G76: 28 | H76: 13x19 | I76: 6500 | J76: PL | K76: 39879 | L76: Công ty in Tạp chí cộng sản
A77: 73 | B77: Luật quản lý nợ công | C77: QH | D77: TPH | E77: 1 | F77: 5000 | G77: 52 | H77: 13x19 | I77: 9000 | J77: PL | K77: 39879 | L77: Nhà in Sự Thật
... A80: 76 | B80: Biện chứng giữa văn hoá và sự phát triển xã hội trong quá trình định hướng xã hội chủ nghĩa ở Việt Nam | C80: PGS, TS. Nguyễn Hồng Sơn | D80: LKTG | E80: 1 | F80: 600 | G80: 228 | H80: 14,5x20,5 | I80: 39000 | J80: GK | K80: 39884 | L80: Trung tâm in Kỹ thuật và DV Ảnh cơ quan đại diện TTXVN tại Đà Nẵng
A81: 77 | B81: Kinh nghiệm xây dựng đội ngũ cán bộ ở Trung Quốc (Sách tham khảo) | C81: Trịnh Cư, TS. Nguyễn Duy Hùng, PGS, TS. Lê Văn Yên | D81: TPH | E81: 1 | F81: 1000 | G81: 356 | H81: 14,5x20,5 | I81: 47000 | J81: Đg | K81: 13/03/2009 | L81: Cty in Thương Mại TTXVN
A82: 78 | B82: Quy định pháp luật về quản lý, tuyển dụng, đào tạo, bổ nhiệm, miễn nhiệm cán bộ, công chức | C82: QH | D82: TPH | E82: 1 | F82: 1000 | G82: 488 | H82: 14,5x20,5 | I82: 63000 | J82: PL | K82: 13/03/2009 | L82: Nhà in Hà Nội Cty sách Hà Nội
A83: 79 | B83: Đánh giá, quy hoạch, luân chuyển cán bộ lãnh đạo, quản lý thời kỳ công nghiệp hoá hiện đại hoá đất nước | C83: PGS, TS. Trần Đình Hoan (Chủ biên) | D83: TPH | E83: TB | F83: 1000 | G83: 576 | H83: 14,5x20,5 | I83: 74000 | J83: KĐLL | K83: 14/3/2009 | L83: Cty in Tiến Bộ
A84: 80 | B84: Luật giao thông đường bộ | C84: QH | D84: TPH | E84: TB | F84: 3000 | G84: 92 | H84: 13x19 | I84: 13000 | J84: PL | K84: 16/3/2009 | L84: Nhà in Sự Thật
A85: 81 | B85: Luật sĩ quan quân đội nhân dân Việt Nam năm 1999 (Sửa đổi, bổ sung năm 2008) | C85: QH | D85: TPH | E85: TB | F85: 2000 | G85: 92 | H85: 13x19 | I85: 11500 | J85: PL | K85: 16/3/2009 | L85: Nhà in Sự Thật
A86: 82 | B86: Luật thuế thu nhập cá nhân năm 2007 và văn bản hướng dẫn thi hành * Luật thuế thu nhập cá nhân năm 2007 * Các văn bản hướng dẫn thi hành luật | C86: QH | D86: TPH | E86: TB | F86: 1300 | G86: 392 | H86: 13x19 | I86: 42000 | J86: PL | K86: 16/03/2009 | L86: Nhà in Sự Thật
A87: 83 | B87: Thương mại Việt Nam - Nhật Bản trong tiến trình phát triển quan hệ giữa hai nước | C87: Trần Thị Anh Phương | D87: TPH | E87: 1 | F87: 550 | G87: 176 | H87: 14,5x20,5 | I87: 25000 | J87: KT | K87: 17/3/2009 | L87: Nhà in Sự Thật
A88: 84 | B88: Phạm Văn Đồng Tuyển tập (1966-1975). Tập II | C88: Hội đồng chỉ đạo xuất bản | D88: TWĐH | E88: 1 | F88: 1500 | G88: 1258 | H88: 15x22 | I88: 0 | J88: Đg | K88: 17/3/2009 | L88: Cty in Tiến bộ
A89: 85 | B89: Luật tổ chức chính phủ nam 2001 và van bản hướng dẫn thi hành | C89: QH | D89: TPH | E89: 1 | F89: 850 | G89: 512 | H89: 16x24 | I89: 88000 | J89: PL | K89: 18/03/2009 | L89: Cty in Thương Mại TTXVN
A90: 86 | B90: Phát triển công nghiệp hỗ trợ ở Việt Nam. Lý thuyết, thực tiễn và chính sách (Sách chuyên khảo) | C90: Lê Thế Giới | D90: LKTG | E90: 1 | F90: 600 | G90: 252 | H90: 14,5x20,5 | I90: 40000 | J90: QT | K90: 19/03/2009 | L90: Cty Cp in Dịch vụ Đà Nẵng
A91: 87 | B91: Giáo trình những nguyên lý cơ bản của chủ nghiã Mác - Lênin (Dành cho sinh viên đại học, cao đẳng khối không chuyên ngành Mác - Lênin, tư tưởng Hồ Chí Minh) | C91: Bộ Giáo dục và đào tạo | D91: QLP | E91: 1 | F91: 20000 | G91: 492 | H91: 14,5x20,5 | I91: 32500 | J91: GK | K91: 19/03/2009 | L91: Nhà in Hà Nội Cty sách Hà Nội
A92: 88 | B92: Cuộc gặp gỡ định mệnh | C92: Sơn Tùng | D92: TPH | E92: TB | F92: 700 | G92: 200 | H92: 13x20,50 | I92: 21000 | J92: QT | K92: 19/03/2009 | L92: Nhà in Sự Thật
A93: 89 | B93: Luật đầu tư | C93: QH | D93: TPH | E93: TB | F93: 2000 | G93: 68 | H93: 13x19 | I93: 8000 | J93: PL | K93: 19/03/2009 | L93: Nhà in Sự Thật
A94: 90 | B94: Khu di tích lịch sử Tân Trào | C94: Ngô Quân Lập | D94: LKTG | E94: 1 | F94: 1000 | G94: 192 | H94: 13x19 | I94: 28000 | J94: KĐLL | K94: 23/03/2009 | L94: Nhà in Sự Thật
A95: 91 | B95: Nguyễn Ái Quốc với Quốc Tế Cộng sản 1920-1943) | C95: PGS, TS. Lê Văn Tích Chủ biên) | D95: TPH | E95: 1 | F95: 710 | G95: 192 | H95: 14,5x20,5 | I95: 29000 | J95: KĐLL | K95: 23/03/2009 | L95: Nhà in Sự Thật
A96: 92 | B96: Luật doanh nghiệp năm 2005 và các nghị định hướng dẫn thi hành | C96: QH | D96: TPH | E96: TB | F96: 750 | G96: 604 | H96: 15x22 | I96: 88000 | J96: PL | K96: 23/3/2009 | L96: Nhà in Sự Thật
A97: 93 | B97: Kinh nghiệm công tác nhân sự của một số nước | C97: PGS, TS. Lê Minh Thông TS. Nguyễn Danh Châu | D97: TPH | E97: 1 | F97: 1000 | G97: 100 | H97: 13x19 | I97: 13000 | J97: KT | K97: 24/3/2009 | L97: Nhà in Sự Thật
A98: 94 | B98: 157 câu hỏi- đáp về tuyển chọn và quản lý người nước ngoài làm việc tại Việt Nam | C98: Lê Hà- Thanh Nga- Lê Văn Linh - Vũ Ba Duy- Huy hoàng- Quang Minh | D98: TPH | E98: 1 | F98: 650 | G98: 168 | H98: 13x19 | I98: 20000 | J98: PL | K98: 24/3/2009 | L98: Nhà in Sư thật
A99: 95 | B99: Luật phòng chống tham nhũng và văn bản hướng dẫn thi hành (Tái bản có bổ sung) | C99: QH | D99: TPH | E99: TB | F99: 1000 | G99: 452 | H99: 14,5x20,5 | I99: 59000 | J99: PL | K99: 26/03/2009 | L99: Nhà in Sự Thật
A100: 96 | B100: Tham nhũng và biện pháp chống tham nhũng ở Trung Quốc (Sách tham khảo) | D100: TPH | E100: 1 | F100: 1000 | G100: 240 | H100: 14,5x20,5 | I100: 33000 | J100: QT | K100: 26/03/2009 | L100: Nhà in Sự Thật | M100: Sách phục vụ hội nghi TW 9
A101: 97 | B101: Luật thực hành tiết kiệm chống lãng phí năm 2005 và văn bản hướng dẫn thi hành (Tái bản có bổ sung) | C101: QH | D101: TPH | E101: 1 | F101: 1000 | G101: 416 | H101: 14,5x20,5 | I101: 54000 | J101: PL | K101: 26/03/2009 | L101: Nhà in Sự thật
A102: 98 | B102: AGENT ORANGE IN VIETNAM Yesterday's Crime, Todayy's Tragedy Forwordby Frangói Gros | C102: Association D' Amitie' Franco - Vietnamiênn (Franco - Vietnammese Friendship Association) | D102: TPH | E102: 1 | F102: 500 | G102: 204 | H102: 14,5x20,5 | I102: 0 | J102: QT | K102: 30/3/2009 | L102: Cty in Tiến Bộ
A103: 99 | B103: Pháp lệnh bảo vệ công trình quan trọng liên quan đến an ninh quốc gia năm 2007 và văn bản hướng dẫn thi hành | C103: QH | D103: TPH | E103: 1 | F103: 750 | G103: 48 | H103: 13x19 | I103: 8500 | J103: PL | K103: 30/03/2009 | L103: Nhà in Sự Thật
...

Sheet 2010
A1: SÁCH XUẤT BẢN NĂM 2010
A3: TT | B3: Tên sách | C3: Tác giả | D3: Phương thức | E3: Lần XB | F3: Số lượng in | G3: Số trang | H3: Khổ sách | I3: Giá bìa | J3: Ban biên tập | K3: QĐXB
A5: 1 | B5: Văn kiện đại hội đại biểu toàn quốc lần thứ VII | C5: Mặt trận tổ quốc Việt Nam | D5: LKTG | E5: 1 | F5: 2500 | G5: 160 | H5: 14,5x20,5 | J5: KĐLL | K5: 1/2010
A6: 2 | B6: Luật ban hành văn bản quy phạm pháp luật năm 2008 và nghị định hướng dẫn thi hành * Luật ban hành văn bản quy phạm pháp luật năm 2008 * Ng | C6: QH, CP | D6: TPH | E6: 1 | F6: 500 | G6: 168 | H6: 13x19 | J6: PL | K6: 1/2010
A7: 3 | B7: Đảng Cộng sản Việt Nam 80 năm xây dựng và phát triển | C7: Hội đồng xuất bản | D7: TWDH | E7: 1 | F7: 1500 | G7: 1228 | H7: 16x24 | J7: Đảng | K7: 40179
A8: 4 | B8: Phong trào đồng khởi 50 năm nhìn lại | C8: Tập thể tác giả | D8: TWDH | E8: 1 | F8: 1000 | G8: 616 | H8: 16x24 | J8: Đảng | K8: 1/2010
A9: 5 | B9: Tư tưởng, tấm gương đạo đức Hồ Chí Minh về xây dựng đảng ta thật sự trong sạch, vững mạnh " Là đạo đức, là văn minh" (Tài liệu tham khảo phục vụ nghiên cứu, học tập chủ đề năm 2010 Cuộc vận động " Học tập và làm theo tấm gương đạo đức Hồ Chí Minh" ) | C9: Ban Tuyên giáo Trung ương | D9: LKTG | E9: 1 | F9: 10030 | G9: 248 | H9: 13x19 | J9: GK | K9: 1/2010
A10: 6 | B10: Đề cương học tập chủ đề Tư tưởng, tấm gương đạo đức Hồ Chí Minh về xây dựng đảng ta thật sự trong sạch, vững mạnh " Là đạo đức, là văn minh" (Tài liệu học tập chủ đề năm 2010 Cuộc vận động " Học tập và làm theo tấm gương đạo đức Hồ Chí Minh" dành cho cán | C10: Ban Tuyên giáo Trung ương | D10: LKTG | E10: 1 | F10: 100000 | G10: 30 | H10: 13x19 | J10: GK | K10: 1/2010
A11: 7 | B11: Luật di sản văn hóa năm 2001 được sửa đổi, bổ sung năm 2009 | C11: QH,CP | D11: TPH | E11: 1 | F11: 2000 | G11: 80 | H11: 13x19 | J11: PL | K11: 1/2010
A12: 8 | B12: Phong cách làm việc của người bí thư huyện uỷ hiện nay qua khảo sát vùng đồng bằng sông Hồng (Sách chuyên khảo) | C12: TS. Ngô Kim Ngân- TS. Lâm Quốc Tuấn (Đồng chủ biên) | D12: TPH | E12: 1 | F12: 700 | G12: 232 | H12: 14,5x20,5 | J12: Đảng | K12: 1/2010
A13: 9 | B13: Đại thắng mùa xuân 1975 Sự kiện - Hỏi và Đáp | C13: Hội đồng chỉ đạo xuất bản sách xã phường thị trấn | D13: TPH | E13: 1 | F13: 9000 | G13: 200 | H13: 12,5x20,5 | J13: QT | K13: 1/2010
A14: 10 | B14: Hỏi - Đáp về tiếp dân và giải quyết khiếu nại, tố cáo của chính quyền cấp xã | C14: Hội đồng chỉ đạo xuất bản sách xã phường thị trấn | D14: TPH | E14: 1 | F14: 9000 | G14: 68 | H14: 12,5x20,5 | J14: GK | K14: 1/2010
A15: 11 | B15: Hỏi - Đáp pháp luật về bồi thường thiệt hại, hỗ trợ tái định cư khi nhà nước thu hồi đất | C15: Hội đồng chỉ đạo xuất bản sách xã phường thị trấn | D15: TPH | E15: 1 | F15: 9000 | G15: 280 | H15: 12,5x20,5 | J15: PL | K15: 1/2010
A16: 12 | B16: Luật phòng cháy và chữa cháy và văn bản hướng dẫn thi hành (Tái bản có bổ sung) | C16: QH, CP | D16: TPH | E16: TB | F16: 600 | G16: 408 | H16: 14,5x20,5 | J16: PL | K16: 1/2010
A17: 13 | B17: Luật phòng, chống ma tuý năm 2000 được sửa đổi bổ sung năm 2008 và văn bản hướng dẫn thị hành | C17: QH, CP | D17: TPH | E17: 1 | F17: 1150 | G17: 204 | H17: 13x19 | J17: PL | K17: 1/2010
A18: 14 | B18: Cẩm nang về công tác bồi thường hỗ trợ tái định cư khi nhà nước thu hồi đất | C18: TS. Nguyễn Thị Phượng | D18: TPH | E18: 1 | F18: 620 | G18: 140 | H18: 13x19 | J18: PL | K18: 1/2010
A19: 15 | B19: Hỏi - Đáp về chứng minh nhân dân và hộ chiếu | C19: Hội đồng chỉ đạo xuất bản sách xã phường thị trấn | D19: TPH | E19: 1 | F19: 9000 | G19: 76 | H19: 12,5x20,5 | J19: PL | K19: 1/2010
A20: 16 | B20: Hỏi - Đáp về bảo vệ an ninh trật tự ở cơ sở | C20: Hội đồng chỉ đạo xuất bản sách xã phường thi trấn | D20: TPH | E20: 1 | F20: 9000 | G20: 84 | H20: 12,5x20,5 | J20: PL | K20: 1/2010
A21: 17 | B21: Uỷ ban Trung ương Mặt trận Tổ quốc Việt Nam khoá VII | C21: Mặt trận tổ quốc Việt Nam | D21: LKTG | E21: 1 | F21: 1000 | G21: 152 | H21: 19x25 | J21: KĐLL | K21: 01/2010
A22: 18 | B22: Nhà nước pháp quyền Xã hội chủ nghĩa Việt Nam của dân, do dân, vì dân.Lý luận và thực tiễn | C22: GS, VS. Nguyễn Duy Quý PGS, TS. Nguyễn Tất Viễn (Đồng chủ biên) | D22: TPH | E22: 1 | F22: 560 | G22: 376 | H22: 14,5x20,5 | J22: KĐLL | K22: 01/2010
A23: 19 | B23: Cẩm nang Công tác đảng | C23: Hội đồng chỉ đạo xuất bản sách xã phường, thị trấn | D23: TPH | E23: 1 | F23: 9000 | G23: 272 | H23: 12,5x20,5 | J23: KĐLL | K23: 01/2010
A24: 20 | B24: Luật hình sự Việt Nam Quyển 2 (Phần các tội phạm) | C24: TS. Phạm Văn Beo | D24: TPH | E24: 1 | F24: 2000 | G24: 660 | H24: 16x24 | J24: PL | K24: 1/2010
A25: 21 | B25: Bình luận luật sửa đổi bổ sung một số điều của bộ luật hình sự năm 1999 | C25: GS, TS. Nguyễn Ngọc Anh Ths. Đỗ Khắc Hưởng | D25: TPH | E25: 1 | F25: 1020 | G25: 112 | H25: 16x24 | J25: PL | K25: 01/2010
A26: 22 | B26: Hỏi - Đáp về dân chủ ở cơ sở | C26: Hội đồng chỉ đạo xuất bản sách xã, phường, thị trấn | D26: TPH | E26: 1 | F26: 9000 | G26: 132 | H26: 12,5x20,5 | J26: PL | K26: 1/2010
A27: 23 | B27: Hỏi - Đáp về cải cách thủ tục trong hoạt động thu, nộp thuế | C27: Hội đồng chỉ đạo xuất bản sách, xã phường, thị trấn | D27: TPH | E27: 1 | F27: 9000 | G27: 228 | H27: 12,5x20,5 | J27: PL | K27: 1/2010
A28: 24 | B28: Quản lý, chỉ đạo công tác tư pháp xã, phường, thị trấn | C28: Hội đồng chỉ đạo xuất bản sách xã phường, thị trấn | D28: TPH | E28: 1 | F28: 9000 | G28: 212 | H28: 12,5x20,5 | J28: PL | K28: 1/2010
... A36: 32 | B36: Cuộc tổng tiến công của quân giải phóng miền Nam Việt Nam năm 1968 (Qua tài liệu lưu trữ của chính quyền Sài Gòn) | C36: Trung tâm lưu trữ Quốc gia | D36: LKTG | E36: 1 | F36: 600 | G36: 400 | H36: 16x24 | J36: PL | K36: 1/2010
A37: 33 | B37: Giáo trình chủ nghĩa xã hội khoa học (Tái bản có sửa chữa bổ sung) | C37: Hội đồng chỉ đạo biên soạn | D37: TPH | E37: TB | F37: 500 | G37: 560 | H37: 14,5x20,5 | J37: GK | K37: 1/2010
A38: 34 | B38: Bình luận khoa học bộ luật dân sự năm 2005 (Tập III) Phần thứ tư: Thừa kế Phần thứ năm: Quy dịnh về chuyển quyền sử dụng đất Phần thứ sáu: Quyền sở hữu trí tuệ | C38: Bộ Tư pháp viện khoa học pháp lý GS, TS. Hoàng Thế Liên | D38: TPH | E38: 1 | F38: 2200 | G38: 612 | H38: 16x24 | J38: PL | K38: 1/2010
A39: 35 | B39: Tư tưởng Hồ Chí Minh về kinh tế | C39: HVBCTT TS. Ngô Văn Lương | D39: LKTG | E39: 1 | F39: 1030 | G39: 304 | H39: 13x19 | J39: KT | K39: 1/2010
A40: 36 | B40: Lịch sử Đảng bộ xã An Bình (1975 - 2005) | C40: Đảng bộ Huyện Dĩ An BCH Đảng bộ xã An Bình | D40: LKTG | E40: 1 | F40: 530 | G40: 216 | H40: 14,5x20,5 | J40: TPHCM | K40: 1/2010
A41: 37 | B41: Khu di tích lịch sử Tân Trào | C41: Ngô Quân Lập | D41: LKTG | E41: TB | F41: 2000 | G41: 192 | H41: 13x19 | J41: KĐLL | K41: 40184
A42: 38 | B42: Lịch sử truyền thống công an quận Hoàn Kiếm (1945 - 2010) | C42: Công an quận Hoàn Kiếm | D42: LKTG | E42: 1 | F42: 500 | G42: 276 | H42: 14,5x20,5 | J42: TTNCKH | K42: 40186
A43: 39 | B43: Quan hệ kinh tế giữa công nhân, nông dân và trí thức ở Việt Nam hiện nay | C43: Đặng Quang Định | D43: TPH | E43: 1 | F43: 640 | G43: 220 | H43: 13x19 | J43: KĐLL | K43: 40186
A44: 40 | B44: Tư tưởng Hồ Chí Minh về hợp tác xã những vấn đề lý luận và thực tiễn | C44: GS, TS. Lê Hữu Nghĩa | D44: TPH | E44: 1 | F44: 850 | G44: 492 | H44: 16x24 | J44: KT | K44: 40189
A45: 41 | B45: Một số giải pháp nhằm phát triển bền vững nông thôn vùng đồng bằng Bắc bộ trong quá trình xây dựng, phát triển các khu công nghiệp (Qua khảo sát các tỉnh Vĩnh Phúc, Hải Dương, Ninh Bình) | C45: TS Đỗ Đức Quân | D45: TPH | E45: 1 | F45: 500 | G45: 168 | H45: 14,5x20,5 | J45: KĐLL | K45: 40190
A46: 42 | B46: Lợi Nhuận (Sách tham khảo) | C46: TS. Trần Xuân Kiên | D46: TPH | E46: 1 | F46: 680 | G46: 216 | H46: 14,5x20,5 | J46: KĐLL | K46: 40190
A47: 43 | B47: Phát huy tính tích cực xã hội của đội ngũ cán bộ nước ta hiện nay (Tái bản có sửa chữa bổ sung) | C47: PGS, TS. Nguyễn Văn Tài | D47: TPH | E47: 1 | F47: 680 | G47: 248 | H47: 14,5x20,5 | J47: GK | K47: 13/01/2010
A48: 44 | B48: Tham luận tại đại hội đại biểu toàn quốc lần thứ VII | C48: Mặt trận tổ quốc Việt Nam | D48: LKTG | E48: 1 | F48: 1000 | G48: 656 | H48: 14,5x20,5 | J48: KĐLL | K48: 22/1/2010
A49: 45 | B49: Lịch sử Đảng bộ và nhân dân xã Thái Hà (1927 - 2005) | C49: Ban chấp hành đảng bộ xã Thái Hà | D49: LKTG | E49: 1 | F49: 350 | G49: 432 | H49: 14,5x20,5 | J49: KĐLL | K49: 25/01/2010
A50: 46 | B50: Foreign direct investment in viet nam determinats and impacts | C50: centre for analysis and forecasting | D50: LKTG | E50: 1 | F50: 500 | G50: 176 | H50: 16x24 | J50: PL | K50: 02/2010
A51: 47 | B51: Bán cầu châu Á mới Sự chuyển giao tất yếu quyền lực toàn cầu sang phương Đông (Sách tham khảo) | C51: KISHORE MAHBUBANI | D51: TWDH | E51: 1 | F51: 1000 | G51: 344 | H51: 16x24 | J51: QT | K51: 2/2010
A52: 48 | B52: Lê Khả Phiêu tuyển tập, Tập I (1976 - 1998) | C52: Tập thể tác giả | D52: TWDH | E52: 1 | F52: 1000 | G52: 808 | H52: 15x22 | J52: KĐLL | K52: 2/2010
A53: 49 | B53: Lịch sử lực lượng vũ trang nhân dân huyện Hải Lăng (1945 - 2005) | C53: BCHQSự tỉnh Quảng Trị BCHQSự huyện Hải Lăng | D53: LKTG | E53: 1 | F53: 540 | G53: 300 | H53: 14,5x20,5 | J53: Đảng | K53: 2/2010
A54: 50 | B54: Luật người cao tuổi | C54: QH | D54: TPH | E54: TB | F54: 4000 | G54: 32 | H54: 13x19 | J54: PL | K54: 2/2010
A55: 51 | B55: Luật thuế tài nguyên | C55: QH | D55: TPH | E55: TB | F55: 4000 | G55: 20 | H55: 13x19 | J55: PL | K55: 2/2010
A56: 52 | B56: Lịch sử đảng bộ huyên Ba Tơ tỉnh Quảng Ngãi | C56: BCH Đảng bộ Huyện Ba Tơ tỉnh Quảng Ngãi | D56: QLP | E56: 1 | F56: 2000 | G56: 426 | H56: 14,5x20,5 | J56: QT | K56: 2/2010
A57: 53 | B57: Tài liệu học tập chính trị dành cho học viên lớp bồi dưỡng kết nạp Đảng (Tái bản có sửa chữa bổ sung) | C57: Ban Tuyên giáo Trung ương | D57: TPH | E57: TB | F57: 6000 | G57: 192 | H57: 13x19 | J57: GK | K57: 2/2010
A58: 54 | B58: Tài liệu bồi dưỡng lý luận chính trị dành cho Đảng viên mới (Tái bản có sửa chữa bổ sung) | C58: Ban Tuyên Giáo Trung ương | D58: TPH | E58: TB | F58: 6000 | G58: 224 | H58: 13x19 | J58: GK | K58: 2/2010
A59: 55 | B59: Luật xây dựng năm 2003 (Sửa đổi, bổ sung năm 2009) Và nghị định hướng dẫn thi hành * Luật xây dựng năm 2003 được sửa đổi, bổ sung năm 2009 * | C59: QH | D59: TPH | E59: 1 | F59: 1050 | G59: 544 | H59: 14,5x20,5 | J59: PL | K59: 2/2010
A60: 56 | B60: Danh mục các văn bản hết hiệu lực trong lĩnh vực công thương, tài chính, ngân hàng,và xã hội y tế | C60: QH | D60: TPH | E60: 1 | F60: 700 | G60: 172 | H60: 14,5x20,5 | J60: PL | K60: 2/2010
A61: 57 | B61: Quy định về chứng minh nhân dân và hộ chiếu (Tái bản có bổ sung) | C61: QH | D61: TPH | E61: TB | F61: 600 | G61: 168 | H61: 13x19 | J61: PL | K61: 2/2010
A62: 58 | B62: Nghị định về kinh doanh xăng dầu và khí dầu mỏ hoá lỏng * Nghị định số 84/2009/ND - CP ngày 15-10-2009 của chính phủ về kinh doanh xăng dầu (Thay thế nghị định số 55/2007/NĐ-CP và quyết định số 04/2009/QĐ-TTg) | C62: QH | D62: TPH | E62: 1 | F62: 620 | G62: 180 | H62: 13x19 | J62: PL | K62: 2/2010
A63: 59 | B63: Di chúc của Chủ tịch Hồ Chí Minh Lý luận và thực tiễn | C63: Sở Văn hoá, thể thao và du lịch thừa Thiên Huế Bảo tảng Hồ Chí Minh | D63: TPH | E63: 1 | F63: 500 | G63: 360 | H63: 14,5x20,5 | J63: Đảng | K63: 2/2010
A64: 60 | B64: Ngoại giao nhân dân trong quan hệ đối ngoại của Mỹ | C64: TS. Nguyễn Thị Thanh Thuỷ | D64: TPH | E64: 1 | F64: 500 | G64: 232 | H64: 13x19 | J64: Đảng | K64: 2/2010
A65: 61 | B65: Một số vấn đề về xây dựng tổ chức cơ sở Đảng hiện nay | C65: Nguyễn Đức Hà | D65: TPH | E65: 1 | F65: 1460 | G65: 240 | H65: 14,5x20,5 | J65: KĐLL | K65: 2/2010
A66: 62 | B66: Hỏi đáp và chỉ dẫn áp dụng luật thi hành án dân sự năm 2008 và các văn bản hướng dẫn thị hành | C66: ThS. Nguyễn Văn Nghĩa Nguyễn Quang Minh | D66: TPH | E66: 1 | F66: 500 | G66: 348 | H66: 14,5x20,5 | J66: PL | K66: 2/2010
A67: 63 | B67: Luật đất đai năm 2003 (Sửa đổi ,bổ sung năm 2009) và các bghị định hướng dẫn thi hành * Luật đất đại năm 2003 đựơc sửa đổi, bổ sung năm 2009 * Các Nghị | C67: QH, CP | D67: TPH | E67: 1 | F67: 1120 | G67: 276 | H67: 14,5x20,5 | J67: PL | K67: 2/2010
A68: 64 | B68: Các quy chế về cảnh báo, phòng, chống thiên tai (Áp thấp nhiệt đới, bão, lụt, động đất, sóng thần...) | C68: Uỷ ban Thường vụ QH | D68: TPH | E68: 1 | F68: 740 | G68: 114 | H68: 13x19 | J68: PL | K68: 2/2010
A69: 65 | B69: Đảng Cộng sản Việt Nam lãnh đạo xây dựng, củng cố nhà nước (1986 - 1996)Sách chuyên khảo | C69: TS. Đoàn Minh Huấn | D69: TPH | E69: 1 | F69: 550 | G69: 304 | H69: 14,5x20,5 | J69: Đảng | K69: 2/2010
A70: 66 | B70: Chủ quyền quốc gia dân tộc trong xu thế toàn cầu hoá và vấn đề đặt ra với Việt Nam | C70: TS. Phan Văn Rân PGS, TS. Nguyễn Hoàng Giáp | D70: TPH | E70: 1 | F70: 470 | G70: 232 | H70: 14,5x20,5 | J70: Đảng | K70: 2/2010
A71: 67 | B71: Hồ Chí Minh trong trái tim Trí thức và văn nghệ sĩ | C71: TS. Văn Thị Thanh Mai | D71: TPH | E71: 1 | F71: 730 | G71: 424 | H71: 14,5x20,5 | J71: KĐLL | K71: 2/2010
A72: 68 | B72: Hỏi - Đáp pháp luật về phòng chống tham nhũng | C72: Bích Loan | D72: TPH | E72: 1 | F72: 750 | G72: 284 | H72: 13x19 | J72: PL | K72: 2/2010
A73: 69 | B73: Chiến lược biển Việt Nam từ quan điểm đến thực tiễn (Sách tham khảo) | C73: Ban Tuyên giáo Trung ương | D73: LKTG | E73: 1 | F73: 3000 | G73: 380 | H73: 14,5x20,5 | J73: KT | K73: 2/2010
... A86: 82 | B86: Văn kiện Quốc hội toàn tập 6 1981 - 1987 Quyển 1 1981 - 1983 | C86: QH Nước Cộng hoà xã hội chủ nghĩa Việt Nam | D86: LKTG | E86: 1 | F86: 1600 | G86: 1404 | H86: 16x24 | J86: PL | K86: 3/2010
A87: 83 | B87: Luật trách nhiệm bồi thường của nhà nước | C87: QH, CP | D87: TPH | E87: TB | F87: 2000 | G87: 60 | H87: 13x19 | J87: PL | K87: 3/2010
A88: 84 | B88: Luật dân quân tự vệ | C88: QH,CP | D88: TPH | E88: TB | F88: 4000 | G88: 60 | H88: 13x19 | J88: PL | K88: 3/2010
A89: 85 | B89: Luật cán bộ, công chức | C89: QH,CP | D89: TPH | E89: TB | F89: 2000 | G89: 60 | H89: 13x19 | J89: PL | K89: 3/2010
A90: 86 | B90: Tập bài giảng chính trị học | C90: Tập thể tác giả TS. Lê Văn Phụng (Chủ biên) | D90: LKTG | E90: 1 | F90: 1000 | G90: 400 | H90: 13x19 | J90: Đảng | K90: 3/2010
A91: 87 | B91: Xoá đói giảm nghèo ở MALAIXIA và Thái Lan bài học kinh nghiệm cho Việt Nam | C91: Ths. Võ Thị Thu Nguyệt | D91: TPH | E91: 1 | F91: 460 | G91: 200 | H91: 13x19 | J91: Đảng | K91: 3/2010
A92: 88 | B92: Phụ nữ và giới (Sách tham khảo) | C92: Bùi Thị Tỉnh | D92: TPH | E92: 1 | F92: 500 | G92: 240 | H92: 14,5x20,5 | J92: GK | K92: 3/2010
A93: 89 | B93: Phản biện xã hội và phát huy dân chủ pháp quyền (Sách tham khảo) | C93: TS. Hồ Bá Thâm CN. Nguyễn Tôn Thị Tường Vân | D93: TPH | E93: TB | F93: 590 | G93: 188 | H93: 14,5x20,5 | J93: Đảng | K93: 3/2010
A94: 90 | B94: Đảng lãnh đạo công tác tư tưởng trong thời kỳ đổi mới | C94: HVCT-HCQGHCM TS. Nguyễn Danh Tiên (Chủ biên) | D94: TPH | E94: 1 | F94: 550 | G94: 256 | H94: 14,5x20,5 | J94: Đảng | K94: 3/2010
A95: 91 | B95: Văn kiện Quốc hội toàn tập 6 1981 - 1987 Quyển 2 1984 - 1987 | C95: QH Nước Cộng hoà xã hội chủ nghĩa Việt Nam | D95: LKTG | E95: 1 | F95: 1600 | G95: 1552 | H95: 16x24 | J95: PL | K95: 3/2010
A96: 92 | B96: Lịch sử xứ uỷ Nam Bộ và trung ương cục Miền Nam (1954 - 1975) | C96: HVCT-HCQGHCM VLSĐ PGS, TS. Nguyễn Quý | D96: TWDH | E96: 1 | F96: 1000 | G96: 596 | H96: 16x24 | J96: Đảng | K96: 3/2010
A97: 93 | B97: Di chúc của Chủ tịch Hồ Chí Minh | C97: Hồ Chí Minh | D97: TPH | E97: TB | F97: 3000 | G97: 48 | H97: 15x22 | J97: Đảng | K97: 3/2010
A98: 94 | B98: Văn hoá chính trị và lịch sử dưới góc nhìn văn hoá chính trị (Chuyên luận) | C98: Phạm Hồng Tung | D98: TPH | E98: TB | F98: 565 | G98: 412 | H98: 14,5x20,5 | J98: Đảng | K98: 3/2010
A99: 95 | B99: Đảng và các tổ chức Chính trị - xã hội trong hệ thống chính trị Việt Nam hiện nay (Xuất bản lần thứ hai) | C99: HVCT - HCQGHCM VCTH TS. Nguyễn Hữu Đổng (chủ biên) | D99: TPH | E99: TB | F99: 740 | G99: 176 | H99: 13x19 | J99: Đảng | K99: 3/2010
A100: 96 | B100: Nhà nước trong hệ thống Chính trị ở Việt Nam hiện nay (Xuất bản lần thứ hai) | C100: HVCT - HCQGHCM VCTH PGS, TS. Lê Minh Quân (Chủ biên) | D100: TPH | E100: TB | F100: 670 | G100: 168 | H100: 13x19 | J100: Đảng | K100: 3/2010
A101: 97 | B101: Bệnh quan liêu trong công tác cán bộ ở nước ta hiện nay thực trạng nguyên nhân và giải quyết | C101: PGS, TS. Trương Thị Thông PGS, TS. Lê Kim Việt (Đồng chủ biên ) | D101: TPH | E101: TB | F101: 710 | G101: 200 | H101: 12x20,5 | J101: Đảng | K101: 3/2010
A102: 98 | B102: Võ Nguyên Giáp - Danh tướng thời đại Hồ Chí Minh | C102: Đại tá Trần Trọng Trung | D102: TPH | E102: TB | F102: 2000 | G102: 912 | H102: 16x24 | J102: KĐLL | K102: 3/2010
A103: 99 | B103: Những chặng đường lịch sử | C103: Đại tướng Võ Nguyên Giáp | D103: TPH | E103: TB | F103: 2000 | G103: 648 | H103: 14,5x20,5 | J103: KĐLL | K103: 3/2010
A104: 100 | B104: Một số vấn đề về biến đổi cơ cấu xã hội Việt Nam hiện nay | C104: GS, TS. Tạ Ngọc Tấn (Chủ biên) | D104: TPH | E104: 1 | F104: 550 | G104: 408 | H104: 14,5x20,5 | J104: KĐLL | K104: 3/2010
A105: 101 | B105: Công bằng xã hội trong tiến bộ xã hội | C105: TS. Nguyễn Minh Hoàn | D105: TPH | E105: TB | F105: 650 | G105: 256 | H105: 14,5x20,5 | J105: KĐLL | K105: 3/2010
A106: 102 | B106: Các văn bản chủ yếu của thành uỷ Hà Nội khoá XIV nhiệm kỳ 2005 - 2010 tập III ban hành năm 2008 (Lưu hành nội bộ) | C106: Đảng Cộng sản Việt Nam thành uỷ Hà Nội | D106: LKTG | E106: 1 | F106: 1000 | G106: 724 | H106: 16x24 | J106: TTNCKH | K106: 3/2010
A107: 103 | B107: Khái lược Kinh tế Chính trị Mác - Lênin (Dùng cho sinh viên các trường đại học thuộc khối ngành kinh tế và quản trị kinh doanh ) | C107: GS, TS. Phạm Quang Phan PGS, TS. Tô Đức Hạnh | D107: TPH | E107: TB | F107: 730 | G107: 388 | H107: 14,5x20,5 | J107: KT | K107: 3/2010
A108: 104 | B108: Các quy định về xử phạt vi phạm hành chính trong lĩnh vực hoá chất, quản lý, bảo vệ rừng, lâm sản, đất đai và một số lĩnh vực khác | C108: QH, CP | D108: TPH | E108: 1 | F108: 750 | G108: 348 | H108: 14,5x20,5 | J108: PL | K108: 3/2010
A109: 105 | B109: Cơ chế quản lý tài sản công trong khu vực hành chính sự nghiệp ở Việt Nam (Sách chuyên khảo) | C109: TS. Nguyễn Mạnh Hùng | D109: TPH | E109: 1 | F109: 970 | G109: 292 | H109: 13x19 | J109: KT | K109: 3/2010
A110: 106 | B110: Quy định pháp luật về quy trình giải quyết tố cáo | C110: QH, CP | D110: TPH | E110: 1 | F110: 920 | G110: 104 | H110: 13x19 | J110: PL | K110: 3/2010
A111: 107 | B111: Thực hiện và áp dụng pháp luật ở Việt Nam (Sách tham khảo) | C111: TS. Nguyễn Minh Đoan | D111: TPH | E111: TB | F111: 500 | G111: 164 | H111: 13x19 | J111: PL | K111: 3/2010
A112: 108 | B112: Pháp lệnh cảnh vệ | C112: QH,CP | D112: TPH | E112: TB | F112: 1000 | G112: 24 | H112: 13x19 | J112: PL | K112: 3/2010
A113: 109 | B113: Giáo dục Đại học ở Miền Bắc thời kỳ 1945 - 1975 | C113: TS. Ngô Văn Hà | D113: TPH | E113: 1 | F113: 500 | G113: 280 | H113: 14,5x20,5 | J113: Đảng | K113: 3/2010
A114: 110 | B114: Các tội xâm phạm sở hữu trong bộ luật hình sự năm 1999 được sửa đổi, bổ sung năm 2009 (Sách chuyên khảo) | C114: Ths. Nguyễn Mai Bộ | D114: TPH | E114: 1 | F114: 770 | G114: 500 | H114: 14,5x20,5 | J114: PL | K114: 3/2010
A115: 111 | B115: Chỉ thị và các văn bản hướng dẫn về Đại hội Đảng bộ các cấp tiến tới Đại hội Đại biểu toàn quốc lần thứ XI của Đảng | C115: ĐCSVN | D115: TPH | E115: 1 | F115: 1650 | G115: 240 | H115: 13x19 | J115: KĐLL | K115: 3/2010
A116: 112 | B116: Triển vọng kinh tế Việt Nam trong thế kỷ XXI (Sách tham khảo) | C116: TS. Trần Xuân Kiên | D116: TPH | E116: 1 | F116: 500 | G116: 220 | H116: 14,5x20,5 | J116: TTNCKH | K116: 3/2010
A117: 113 | B117: Trình tự, thủ tục giải quyết các vụ việc dân sự | C117: Dương Bạch Long | D117: TPH | E117: TB | F117: 690 | G117: 608 | H117: 14,5x20,5 | J117: PL | K117: 3/2010
A118: 114 | B118: Những điều cần biết về thủ tục hành chính trong cấp " Giếy chứng nhận quyền sử dụng đất, quyền sở hữu nhà ở và tài sản khác gắn liền với đất" | C118: Nguyễn Xuân Anh Dương Bách Long | D118: TPH | E118: 1 | F118: 940 | G118: 268 | H118: 13x19 | J118: PL | K118: 3/2010
A119: 115 | B119: Tư tưởng Hồ Chí Minh về văn hoá Đảng (Xuất bản lần thứ hai) | C119: PGS, TS. Phạm Ngọc Anh (Chủ biên) | D119: TPH | E119: TB | F119: 750 | G119: 228 | H119: 14,5x20,5 | J119: Đảng | K119: 3/2010
A120: 116 | B120: Hỏi - Đáp về công tác Đảng ở cơ sở | C120: Hội đồng chỉ đạo xuất bản sách xã phường thị trấn | D120: TPH | E120: 1 | F120: 9000 | G120: 252 | H120: 12,5x20,5 | J120: Đảng | K120: 3/2010
A121: 117 | B121: Hỏi - Đáp về công tác của cấp uỷ và bí thư chi bộ | C121: Hội đồng chỉ đạo xuất bản sách xã phường thị trấn | D121: TPH | E121: 1 | F121: 9000 | G121: 216 | H121: 12,5x20,5 | J121: Đảng | K121: 3/2010
...

Sheet 2011
A1: SÁCH XUẤT BẢN NĂM 2011
A2: TT | B2: Tên sách | C2: Tác giả | D2: Phương thức | E2: Lần xuất bản | F2: SL in | G2: Trang | H2: Khổ | I2: Giá bìa | J2: BBT | K2: QĐXB | L2: Nơi in | M2: Ghi chú
A3: 1 | B3: Tuyên ngôn độc lập của Chủ tịch Hồ Chí Minh - Giá trị lý luận và ý nghĩa thời đại | C3: Bảo tàng Hồ Chí Minh | D3: TPH | E3: 1 | F3: 690 | G3: 408 | H3: 16x24 | I3: 79000 | J3: Đg | K3: 1/2011 | L3: Cty TNHH MTV in Văn Hoá phẩm
A4: 2 | B4: Phong trào công nhân quốc tế -những vấn đề lịch sử và lý luận, tập VII (Sách tham khảo) | C4: Hội đồng xuất bản | D4: TWĐH | E4: 1 | F4: 1000 | G4: 1092 | H4: 15x22 | I4: 155000 | J4: KĐLL | K4: 1/2011 | L4: Cty in Tiến Bộ Hà Nội | M4: 14/1/2011
A5: 3 | B5: Đổi mới công tác tư tưởng, lý luận phục vụ sự nghiệp xây dựng và bảo vệ Tổ quốc | C5: TS. Phạm Tất Thắng (Chủ biên) | D5: TPH | E5: 1 | F5: 7000 | G5: 364 | H5: 14.5x20.5 | I5: 48000 | J5: TTPH | K5: 1/1/2011 | L5: Cty Cp in Thái Nguyên | M5: Sách 2010 NLC 14/1/2011
A6: 4 | B6: 80 năm (1930-2010) Đảng Cộng sản Việt Nam - những chặng đường lịch sử vẻ vang | C6: PGS.TS. Vũ Như Khôi | D6: TPH | E6: 1 | F6: 830 | G6: 700 | H6: 16x24 | I6: 0 | J6: QT | K6: 1/2011 | L6: Cty CP in Thiên Kim | M6: Sách 2010 NLC 14/1/2011
A7: 5 | B7: Hồ Chí Minh toàn tập (Xuất bản lần thứ ba), tập 1 1912 - 1924 | C7: Hội đồng xuất bản | D7: TWĐH | E7: TB | F7: 1500 | G7: 576 | H7: 16x24 | I7: 0 | J7: Đg | K7: 1/2011 | L7: Cty in Tiến Bộ
A8: 6 | B8: Hồ Chí Minh toàn tập (Xuất bản lần thứ ba), tập 2 1924 - 1929 | C8: Hội đồng xuất bản | D8: TWĐH | E8: TB | F8: 1500 | G8: 650 | H8: 16x24 | I8: 0 | J8: Đg | K8: 1/2011 | L8: Cty in Tiến Bộ
A9: 7 | B9: Hồ Chí Minh toàn tập (Xuất bản lần thứ ba), tập 3 1930 - 1945 | C9: Hội đồng xuất bản | D9: TWĐH | E9: TB | F9: 1500 | G9: 700 | H9: 16x24 | I9: 0 | J9: Đg | K9: 1/2011 | L9: Cty in Tiến Bộ
A10: 8 | B10: Giáo trình Tư tưởng Hồ Chí Minh (Tái bản có sửa chữa, bổ sung) | C10: Hội đồng Trung ương chỉ đạo biên soạn giáo trình quốc gia các bộ môn khoa học Mác- Lênin, tư tưởng Hồ Chí Minh | D10: TPH | E10: TB | F10: 1000 | G10: 492 | H10: 14,5x20,5 | I10: 66000 | J10: GK | K10: 1/2011 | L10: Nhà in Sự Thật
A11: 9 | B11: Vai trò của các tổ chức xã hội đối với phát triển và quản lý xã hội | C11: TS. Thang Văn Phúc, PGS, TS. Nguyễn Minh Phương (Đồng Chủ biên) | D11: TPH | E11: 1 | F11: 800 | G11: 592 | H11: 14,5x20,5 | I11: 83000 | J11: GK | K11: 1/2011 | L11: Nhà in Sự Thật
A12: 10 | B12: Recognizing and reducing corruption risks in land management in Vietnam (Reference book) | C12: The world bank in Vietnam, Embassy of Denmark, Embassy of Sweden | D12: LKTG | E12: 1 | F12: 300 | G12: 76 | H12: 19x24 | I12: 0 | J12: PL | K12: 1/2011 | L12: Cty in Tạp chí cộng sản
A13: 11 | B13: Luật thuế tài nguyên | C13: QH, CP | D13: TPH | E13: TB | F13: 1500 | G13: 20 | H13: 13x19 | I13: 5000 | J13: PL | K13: 1/2011 | L13: Cty TNHH NTV in và Văn Hoá Phẩm | M13: Sách 31/12/2010 nộp LC 28/1/2011
A14: 12 | B14: Dân chủ nhân quyền - giá trị toàn cầu và đặc thù quốc gia (Lưu hành nội bộ) | C14: Hội đồng Lý luận Trung ương | D14: TWĐH | E14: 1 | F14: 1000 | G14: 472 | H14: 16x24 | I14: 0 | J14: KT | K14: 40544 | L14: CtyTNHH MTV in và Văn hoá phẩm
A15: 13 | B15: Thanh Hoá một thời để nhớ | C15: Hồ Mẫu Ngoạt | D15: LKTG | E15: 1 | F15: 300 | G15: 424 | H15: 14,5x20,5 | I15: 0 | J15: Đg | K15: 40544 | L15: Cty in Tiến Bộ
A16: 14 | B16: Xác định tiêu chuẩn và phương pháp đánh giá chính quyền xã trong sạch, vững mạnh | C16: TS. Nguyễn Hữu Đức, Ths. Phan Văn Hùng (Đồng chủ biên) | D16: TPH | E16: TB | F16: 534 | G16: 176 | H16: 13x19 | I16: 27000 | J16: Đg | K16: 1/2011 | L16: Nhà in Sự Thật
A17: 15 | B17: Luật quốc tịch Việt Nam năm 2008 và văn bản hướng dẫn thi hành (Tái bản có bổ sung) | C17: QH, CP | D17: TPH | E17: TB | F17: 1000 | G17: 192 | H17: 13x19 | I17: 27000 | J17: PL | K17: 1/2011 | L17: Nhà in Sự Thật
A18: 16 | B18: Hỏi - Đáp một số vấn đề về các tội xâm phạm trật tự quản lý hành chính trong Bộ luật hình sự hiện hành | C18: TS. Nguyễn Vũ Tiến, TS. Đỗ Đức Hồng Hà | D18: TPH | E18: 1 | F18: 950 | G18: 92 | H18: 13x19 | I18: 15000 | J18: PL | K18: 1/2011 | L18: Nhà in Sự Thật
A19: 17 | B19: Luật thi đua, khen thưởng năm 2003 (Sửa đổi, bổ sung năm 2005, 2009 và văn bản hướng dẫn thi hành) | C19: QH, CP | D19: TPH | E19: 1 | F19: 1000 | G19: 204 | H19: 13x19 | I19: 23000 | J19: PL | K19: 1/2011 | L19: Nhà in Sự Thật | Q19: 540
A20: 18 | B20: Chế định chứng cứ trong Luật tố tụng hình sự Việt Nam (sách chuyên khảo) | C20: TS. Trần Quang Tiệp | D20: TPH | E20: TB | F20: 485 | G20: 232 | H20: 13x19 | I20: 34000 | J20: PL | K20: 1/2011 | L20: Nhà in Sự Thật
A21: 19 | B21: Luật cán bộ, công chức năm 2008 và văn bản hướng dẫn thi hành | C21: QH, CP | D21: TPH | E21: TB | F21: 1250 | G21: 260 | H21: 13x19 | I21: 27000 | J21: PL | K21: 1/2011 | L21: Nhà in Sự Thật
A22: 20 | B22: Trào lưu xã hội dân chủ ở một số nước phương Tây hiện nay (sách tham khảo) | C22: Tống Đức Thảo, Bùi Việt Phương (Đồng chủ biên) | D22: TPH | E22: 1 | F22: 600 | G22: 244 | H22: 14,5x20,5 | I22: 40000 | J22: KĐLL | K22: 1/2011 | L22: Nhà in Sự Thật
A23: 21 | B23: Lịch sử Đảng bộ và nhân dân xã Vĩnh Thạch (1930-2009) | C23: Huyện ủy Vĩnh Linh | D23: LKTG | E23: 1 | F23: 250 | G23: 284 | H23: 14,5x20,5 | I23: 0 | J23: GK | K23: 1/2011 | L23: Cty in Thống kê và sản xuất bao bì Huế
A24: 22 | B24: Văn kiện Đảng về an sinh xã hội | C24: Hội đồng biên soạn | D24: TWĐH | E24: 1 | F24: 1000 | G24: 296 | H24: 16x24 | I24: 0 | J24: KT | K24: 1/2011 | L24: Cty TNHH MTV in và Văn hoá phẩm
A25: 23 | B25: Nhận diện và giảm thiểu các rủi ro dẫn đến tham nhũng trong quản lý đất đai ở Việt Nam (sách tham khảo) | C25: Ngân hàng thế giới tại Việt Nam, Đại sứ quán Đan Mạch | D25: LKTG | E25: 1 | F25: 2000 | G25: 72 | H25: 19x24 | I25: 0 | J25: PL | K25: 1/2011 | L25: Cty in Tạp chí cộng sản | M25: BCTTết (8-18/2/2011)
A26: 24 | B26: Quá trình đổi mới tư duy lý luận của Đảng từ năm 1986 đến nay | C26: HVCT - HCQG TP HCM, Tô Huy Rứa, Hoàng Chí Bảo, Trần Khắc Việt, Lê Ngọc Tòng (Đồng chủ biên) | D26: TPH | E26: TB | F26: 534 | G26: 524 | H26: 16x24 | I26: 105000 | J26: KĐLL | K26: 1/2011 | L26: Nhà in Sự Thật
A27: 25 | B27: Chủ nghĩa Mác - Lênin với vận mệnh và tương lai của chủ nghĩa xã hội hiện thực (Xuất bản lần thứ hai) | C27: GS, TS. Nguyễn Ngọc Long (Chủ biên) | D27: TPH | E27: TB | F27: 534 | G27: 532 | H27: 14,5x20,5 | I27: 80000 | J27: KĐLL | K27: 1/2011 | L27: Nhà in Sự Thật
A28: 26 | B28: Học thuyết bảo vệ Tổ quốc xã hội chủ nghĩa của V. I. Lênin - giá trị lịch sử và hiện thực | C28: Viện khoa học xã hội nhân văn quân sự | D28: TPH | E28: 1 | F28: 680 | G28: 396 | H28: 14,5x20,5 | I28: 59000 | J28: Đg | K28: 1/2011 | L28: Nhà in Sự Thật
A29: 27 | B29: Luật dân quân tự vệ | C29: QH, CP | D29: TPH | E29: 1 | F29: 2000 | G29: 60 | H29: 13x19 | I29: 10000 | J29: PL | K29: 1/2011 | L29: Nhà in Sự Thật | M29: BCT (21-26/2/2011)
A30: 28 | B30: Văn kiện Quốc hội Toàn tập, tập 7 (1987-1992) Quyển 1 (1987-1989) | C30: Quốc hội nước Cộng hoà xã hội chủ nghĩa Việt Nam | D30: LKTG | E30: 1 | F30: 1600 | G30: 1480 | H30: 16x24 | I30: 0 | J30: PL | K30: 40513 | L30: Cty in Tiến Bộ Hà Nội
A31: 29 | B31: Văn kiện Quốc hội Toàn tập, tập 7 (1987-1992) Quyển 2 (1989-1990) | C31: Quốc hội nước Cộng hoà xã hội chủ nghĩa Việt Nam | D31: LKTG | E31: 1 | F31: 1600 | G31: 1772 | H31: 16x24 | I31: 0 | J31: PL | K31: 12/2010 | L31: Cty in Tiến Bộ Hà Nội
A32: 30 | B32: Lịch sử Tây Nam Bộ kháng chiến, tập 1 (1945 - 1954) | C32: Hội đồng chỉ đạo biên soạn | D32: TWĐH | E32: 1 | F32: 1800 | G32: 956 | H32: 16x24 | I32: 0 | J32: GK | K32: 1/2011 | L32: Cty in Tiến Bộ Hà Nội
A33: 31 | B33: Chất lượng tăng trưởng kinh tế Đồng Nai (Sách tham khảo) | C33: Sở KH và CN Đồng Nai, PGS, TS. Ngô Quang Minh, TS. Nguyễn Trọng Toàn, TS. Phạm Văn Sáng, TS. Bùi Văn Huyền | D33: TPH | E33: 1 | F33: 570 | G33: 320 | H33: 14,5x20,5 | I33: 58000 | J33: QT | K33: 1/2011 | L33: Nhà in Sự Thật
A34: 32 | B34: Chính sách phát triển thị trường bất động sản ở Việt Nam | C34: TS. Đinh Văn Ân (Chủ biên) | D34: TPH | E34: 1 | F34: 930 | G34: 464 | H34: 14,5x20,5 | I34: 65000 | J34: KT | K34: 1/2011 | L34: Nhà in Sự Thật
A35: 33 | B35: Luật phòng cháy và chữa cháy và văn bản hướng dẫn thi hành (Tái bản có BS) | C35: QH, CP | D35: TPH | E35: TB | F35: 1034 | G35: 408 | H35: 14,5x20,5 | I35: 56000 | J35: PL | K35: 1/2011 | L35: Nhà in Sự Thật
A36: 34 | B36: Luật người lao động Việt Nam đi làm việc ở nước ngoài theo hợp đồng | C36: QH, CP | D36: TPH | E36: TB | F36: 1034 | G36: 84 | H36: 13x19 | I36: 13000 | J36: PL | K36: 1/2011 | L36: Nhà in Sự Thật
A37: 35 | B37: Bàn về phương pháp giảng dạy bậc đại học (Tài liệu tham khảo phục vụ việc giảng dạy đối với giảng viên Học viện Chính sách và Phát triển) | C37: Học viện Chính sách và Phát triển, PGS, TS. Ngô Doãn Vịnh | D37: TPH | E37: TB | F37: 534 | G37: 120 | H37: 10x15 | I37: 20000 | J37: KT | K37: 1/2011 | L37: Nhà in Sự Thật | M37: BCT (1-4/3/11)
A38: 36 | B38: Vận dụng và phát triển chủ nghĩa Mác - Lênin của Hồ Chí Minh và Đảng ta (Thời kỳ trước đổi mới) | C38: HVCT - HCQG TP HCM, PGS, TS. Bùi Đình Phong, PGS, TS. Phạm Ngọc Anh (Đồng chủ biên) | D38: TPH | E38: 1 | F38: 500 | G38: 568 | H38: 15x22 | I38: 94000 | J38: KĐLL | K38: 1/2011 | L38: Nhà in Sự Thật
A39: 37 | B39: Lịch sử Đảng bộ và nhân dân xã Vĩnh Kim (1930 - 2011) | C39: Huyện uỷ Vĩnh Linh, BCHĐB xã Vĩnh Kim | D39: LKTG | E39: 1 | F39: 250 | G39: 272 | H39: 14,5x20,5 | I39: 0 | J39: QT | K39: 1/2011 | L39: Cty Thông kê và sản xuất bao bì Huế
A40: 38 | B40: Xử lý tình huống công tác Đảng giai đoạn hiện nay | C40: HVCTHCQGTPHCM - TS. Ngô Huy Tiếp, TS. Đinh Ngọc Giang (Đồng chủ biên) | D40: TPH | E40: 1 | F40: 860 | G40: 520 | H40: 14,5x20,5 | I40: 78000 | J40: TPHCM | K40: 1/2011 | L40: Cty TNHH một thành viên in báo nhân dân
A41: 39 | B41: Phụ nữ Việt Nam trong di sản văn hoá dân tộc | C41: Hội KHLS Thừa Thiên Huế | D41: TPH | E41: 1 | F41: 730 | G41: 420 | H41: 14,5x20,5 | I41: 63000 | J41: Đg | K41: 1/2011 | L41: Nhà in Sự Thật
A42: 40 | B42: Luật hình sự Việt Nam Quyển I (Phần chung) (Tái bản có sửa chữa, BS) | C42: TS. Phạm Văn Beo | D42: TPH | E42: TB | F42: 3034 | G42: 512 | H42: 16x24 | I42: 90000 | J42: PL | K42: 1/2011 | L42: Cty CP in Tổng Hợp Cần Thơ
A43: 41 | B43: Luật bầu cử đại biểu quốc hội năm 1997, sửa đổi, bổ sung năm 2001 và 2010 | C43: QH, CP | D43: TPH | E43: TB | F43: 2034 | G43: 136 | H43: 13x19 | I43: 16000 | J43: PL | K43: 1/2011 | L43: Cty in Tạp chí Cộng sản
A44: 42 | B44: Luật bầu cử đại biểu Hội đồng nhân dân năm 2003 sửa đổi, bổ sung năm 2010 | C44: QH, CP | D44: TPH | E44: TB | F44: 2034 | G44: 114 | H44: 13x19 | I44: 16000 | J44: PL | K44: 1/2011 | L44: Cty in Tạp chí Cộng sản
A45: 43 | B45: Lịch sử Nam Bộ kháng chiến, tập I (1945 - 1954) | C45: Hội đồng chỉ đạo biên soạn Lịch sử Nam Bộ kháng chiến | D45: TWĐH | E45: 1 | F45: 1800 | G45: 956 | H45: 16x24 | I45: 0 | J45: GK | K45: 1/2011 | L45: Cty in Tiến Bộ Hà Nội | M45: Nộp LC 25/3/2011
A46: 44 | B46: Gương sáng làm theo lời Bác | C46: TS. Lê Minh Nghĩa (Chủ biên) | D46: TWĐH | E46: 1 | F46: 1000 | G46: 238 | H46: 14,5x20,5 | I46: 0 | J46: Cần Thơ | K46: 1/2011 | L46: Cty in Tổng hợp Cần Thơ | M46: NLC1/4/2011
A47: 45 | B47: Kỷ yếu Đại hội đại biểu các dân tộc thiểu số Việt Nam tỉnh Sơn La lần thứ nhất | C47: Tỉnh uỷ, HĐND, UBND, UB MTTQ VN | D47: LKTG | E47: 1 | F47: 1500 | G47: 152 | H47: 20,5x29,5 | I47: 0 | J47: KT | K47: 1/2011 | L47: Xưởng in NXB Văn hoá dân tộc | M47: 20/5/11 NLC
A48: 46 | B48: Thuỷ chung cùng năm tháng | C48: Tỉnh uỷ Phú Yên | D48: LKTG | E48: 1 | F48: 1030 | G48: 592 | H48: 16x24 | I48: 0 | J48: TPHCM | K48: 1/2011 | L48: Cty TNHH một thành viên in báo Nhân dân | M48: NLC ngày1/7/2011
A49: 47 | B49: Sự sụp đổ các nền kinh tế trong tương lai - làm thế nào để các quốc gia có thể thịnh vượng khi giá dầu lên tới 200 USD/ thùng | C49: TS. STEPHEN LEEB, GLEN STRATHY | D49: TWĐH+ TPH | E49: 1 | F49: 1700 | G49: 304 | H49: 14,5x20,5 | I49: 0 | J49: KT | K49: 2/2011 | L49: Xưởng in NXB Văn hoá dân tộc
A50: 48 | B50: Định hướng chiến lược đối ngoại Việt Nam đến 2020 (Sách tham khảo) | C50: Học viện Ngoại giao, Phạm Bình Minh (Chủ biên) | D50: TPH | E50: TB | F50: 534 | G50: 240 | H50: 16x24 | I50: 46000 | J50: QT | K50: 2/2011 | L50: Nhà in Sự Thật
A51: 49 | B51: Độc lập dân tộc và chủ nghĩa xã hội- mục tiêu chiến lược và con đường tiếp cận | C51: PGS, TS. Đinh Trần Dương | D51: TPH | E51: 1 | F51: 580 | G51: 456 | H51: 16x24 | I51: 91000 | J51: Đg | K51: 2/2011 | L51: Nhà in Sự Thật
A52: 50 | B52: Hợp tác xã nhìn từ thực tiễn ở Đồng Nai (Sách tham khảo) | C52: Sở KH và CN Đồng Nai, Bùi Văn Huyền, Phạm Văn Sáng, Nguyễn Quốc Thái | D52: TPH | E52: 1 | F52: 550 | G52: 300 | H52: 14,5x20,5 | I52: 49000 | J52: PL | K52: 2/2011 | L52: Nhà in Sự Thật
A53: 51 | B53: Hỏi - Đáp về xử phạt vi phạm hành chính trong lĩnh vực lao động, dạy nghề, bảo hiểm xã hội và bảo hiểm thất nghiệp | C53: Lê Thanh Nga, Nguyễn Thị Huyền (CB) | D53: TPH | E53: 1 | F53: 730 | G53: 328 | H53: 14,5x20,5 | I53: 50000 | J53: PL | K53: 2/2011 | L53: Nhà in Sự Thật
A54: 52 | B54: Luật tố tụng hành chính | C54: QH, CP | D54: TPH | E54: TB | F54: 2034 | G54: 184 | H54: 13x19 | I54: 16000 | J54: PL | K54: 2/2011 | L54: Nhà in Sự Thật
A55: 53 | B55: Luật chứng khoán năm 2006 được sửa đổi, bổ sung năm 2010 | C55: QH, CP | D55: TPH | E55: TB | F55: 1034 | G55: 264 | H55: 13x19 | I55: 25000 | J55: PL | K55: 2/2011 | L55: Nhà in Sự Thật
A56: 54 | B56: Lịch sử phong trào công nhân và công đoàn đường sắt Việt Nam (1880 - 2010) | C56: Công đoàn đường sắt Việt Nam | D56: LKTG | E56: 1 | F56: 700 | G56: 884 | H56: 16x24 | I56: 0 | J56: TTNCKH | K56: 2/2011 | L56: Cty TNHH in và Văn Hoá Phẩm
A57: 55 | B57: Quan điểm kinh tế trong một số tác phẩm kinh điển Mác - Lênin về thời kỳ quá độ lên chủ nghĩa xã hội (Tài liệu tham khảo) | C57: TS. Ngô Văn Lương, TS. Phạm Ngọc Dũng | D57: TPH | E57: 1 | F57: 1050 | G57: 284 | H57: 14,5x20,5 | I57: 40000 | J57: KĐLL | K57: 2/2011 | L57: Nhà in Sự Thật
A58: 56 | B58: Giáo trình phương pháp nghiên cứu khoa học (Tài liệu hướng dẫn nghiên cứu và ứng dụng thực tiễn) | C58: Học viện Chính sách và phát triển, PGS, TS. Ngô Doãn Vịnh | D58: LKTG | E58: 1 | F58: 500 | G58: 160 | H58: 14,5x20,5 | I58: 35000 | J58: KT | K58: 2/2011 | L58: Nhà in Sự Thật
A59: 57 | B59: Học hay cày giỏi | C59: Trần Kim Đồng | D59: LKTG | E59: 1 | F59: 300 | G59: 172 | H59: 14,5x20,5 | I59: 56000 | J59: GK | K59: 2/2011 | L59: Nhà in Sự Thật
A60: 58 | B60: Các cương lĩnh cách mạng của Đảng Cộng sản VN (Tái bản có sửa chữa) | C60: Lê Mậu Hãn | D60: TPH | E60: TB | F60: 1034 | G60: 148 | H60: 13x19 | I60: 27000 | J60: Đg | K60: 2/2011 | L60: Nhà in Sự Thật
A61: 59 | B61: Tìm hiểu pháp luật xử phạt vi phạm hành chính trong lĩnh vực phòng, chống bạo lực gia đình | C61: TS. Vũ Ngọc Anh, Ths. Vũ Vân Anh | D61: TPH | E61: 1 | F61: 730 | G61: 116 | H61: 13x19 | I61: 19000 | J61: PL | K61: 2/2011 | L61: Nhà in Sự Thật
A62: 60 | B62: Luật an toàn thực phẩm | C62: QH, CP | D62: TPH | E62: TB | F62: 2034 | G62: 76 | H62: 13x19 | I62: 11000 | J62: PL | K62: 2/2011 | L62: Cty in Tạp chí Cộng sản
A63: 61 | B63: Luật bảo vệ, chăm sóc và giáo dục trẻ em | C63: QH, CP | D63: TPH | E63: TB | F63: 2034 | G63: 40 | H63: 13x19 | I63: 8000 | J63: PL | K63: 2/2011 | L63: Cty in Tổng hợp Cần Thơ
A64: 62 | B64: Luật thi hành án hình sự | C64: QH, CP | D64: TPH | E64: TB | F64: 2034 | G64: 184 | H64: 13x19 | I64: 22000 | J64: PL | K64: 2/2011 | L64: Cty in Tổng hợp Cần Thơ
A65: 63 | B65: Luật hôn nhân và gia đình năm 2000, sửa đổi bổ sung năm 2010 | C65: QH, CP | D65: TPH | E65: TB | F65: 2034 | G65: 124 | H65: 13x19 | I65: 13000 | J65: PL | K65: 2/2011 | L65: Cty in Tổng hợp Cần Thơ
A66: 64 | B66: Luật thuế sử dụng đất phi nông nghiệp | C66: QH, CP | D66: TPH | E66: TB | F66: 1034 | G66: 20 | H66: 13x19 | I66: 6000 | J66: PL | K66: 2/2011 | L66: Cty in Tổng hợp Cần Thơ
A67: 65 | B67: Luật bưu chính | C67: QH, CP | D67: TPH | E67: TB | F67: 1034 | G67: 48 | H67: 13x19 | I67: 8000 | J67: PL | K67: 2/2011 | L67: Cty in Tổng hợp Cần Thơ
A68: 66 | B68: Luật nuôi con nuôi | C68: QH, CP | D68: TPH | E68: TB | F68: 2034 | G68: 44 | H68: 13x19 | I68: 8000 | J68: PL | K68: 2/2011 | L68: Cty in Tổng hợp Cần Thơ
A69: 67 | B69: Luật cư trú | C69: QH, CP | D69: TPH | E69: TB | F69: 1034 | G69: 36 | H69: 13x19 | I69: 9000 | J69: PL | K69: 2/2011 | L69: Cty in Tổng hợp Cần Thơ
A70: 68 | B70: Luật người khuyết tật | C70: QH, CP | D70: TPH | E70: TB | F70: 1034 | G70: 18 | H70: 13x19 | I70: 8000 | J70: PL | K70: 2/2011 | L70: Cty in Tổng hợp Cần Thơ
A71: 69 | B71: Luật trọng tài thương mại | C71: QH, CP | D71: TPH | E71: TB | F71: 1034 | G71: 72 | H71: 13x19 | I71: 11000 | J71: PL | K71: 2/2011 | L71: Cty in Tổng hợp Cần Thơ
A72: 70 | B72: Luật các tổ chức tín dụng | C72: QH, CP | D72: TPH | E72: TB | F72: 1034 | G72: 156 | H72: 13x19 | I72: 20000 | J72: PL | K72: 2/2011 | L72: Cty in Tổng hợp Cần Thơ
A73: 71 | B73: Bộ luật hình sự năm 1999 được sửa đổi, bổ sung năm 2009 | C73: QH, CP | D73: TPH | E73: TB | F73: 2034 | G73: 320 | H73: 13x19 | I73: 35000 | J73: PL | K73: 2/2011 | L73: Cty in Tổng hợp Cần Thơ
A74: 72 | B74: Bộ luật dân sự | C74: QH, CP | D74: TPH | E74: TB | F74: 1034 | G74: 388 | H74: 13x19 | I74: 37000 | J74: PL | K74: 2/2011 | L74: Cty in Tổng hợp Cần Thơ | M74: BCT (7-11/3/11)
A75: 73 | B75: Tài liệu học tập chính trị dành cho học viên lớp bồi dưỡng kết nạp Đảng (Tái bản) | C75: Ban Tuyên giáo Trung ương | D75: TPH | E75: TB | F75: 6000 | G75: 192 | H75: 13x19 | I75: 15500 | J75: GK | K75: 2/2011 | L75: Nhà in Sự Thật
A76: 74 | B76: Sơ thảo lịch sử 60 năm báo Nhân dân | C76: Đinh Thế Huynh | D76: LKTG | E76: 1 | F76: 2000 | G76: 296 | H76: 14.5x20.5 | I76: 0 | J76: KĐLL | K76: 2/2011 | L76: Cty TNHH một thành viên in và Văn Hoá Phẩm
A77: 75 | B77: Niên giám các điều ước quốc tế nước Cộng hoà XHCNVN ký năm 1996 | C77: Bộ Ngoại giao | D77: TPH | E77: 1 | F77: 500 | G77: 620 | H77: 15x22 | I77: 134000 | J77: PL | K77: 2/2011 | L77: Nhà in Sự Thật | M77: Cho Hồng báo cáo QI (đầu năm ->18/3/2011)
A78: 76 | B78: Văn kiện Đảng về lao động việc làm | C78: Hội đồng biên soạn | D78: TWĐH | E78: 1 | F78: 1000 | G78: 480 | H78: 16x24 | I78: 0 | J78: KT | K78: 2/2011 | L78: Cty TNHH một thành viên in và Văn Hoá Phẩm
A79: 77 | B79: Nguyễn Quang Lâm - cuộc đời trọn vẹn nghĩa tình | C79: TS. Nguyễn Duy Hùng... | D79: TPH | E79: 1 | F79: 800 | G79: 388 | H79: 14,5x20,5 | I79: 160000 | J79: KĐLL | K79: 2/2011 | L79: Cty TNHH MTV in và Văn hoá phẩm
A80: 78 | B80: Bộ luật tố tụng hình sự của nước Cộng hoà xã hội chủ nghĩa Việt Nam | C80: QH, CP | D80: TPH | E80: 1 | F80: 3034 | G80: 256 | H80: 13x19 | I80: 30000 | J80: PL | K80: 2/2011 | L80: Cty in Báo Nhân Dân TP Hồ Chí Minh
A81: 79 | B81: Luật kinh doanh bảo hiểm năm 2000 được sửa đổi, bổ sung năm 2010 | C81: QH, CP | D81: TPH | E81: TB | F81: 2034 | G81: 164 | H81: 13x19 | I81: 17000 | J81: PL | K81: 2/2011 | L81: CTy in Báo Nhân Dân TP Hồ Chí Minh
A82: 80 | B82: Luật đất đai năm 2003 được sửa đổi, bổ sung năm 2009 | C82: QH, CP | D82: TPH | E82: TB | F82: 2034 | G82: 180 | H82: 13x19 | I82: 21000 | J82: PL | K82: 2/2011 | L82: CTy in Báo Nhân Dân TP Hồ Chí Minh
A83: 81 | B83: Luật bảo vệ quyền lợi người tiêu dùng | C83: QH, CP | D83: TPH | E83: TB | F83: 2034 | G83: 40 | H83: 13x19 | I83: 6000 | J83: PL | K83: 2/2011 | L83: CTy in Báo Nhân Dân TP Hồ Chí Minh | M83: BCT (21-25/3/2011)
A84: 82 | B84: Giới thiệu chiến lược quốc gia phòng, chống tham nhũng đến năm 2020 | C84: Thanh tra chính phủ, Viện KH Thanh tra | D84: QLP | E84: 1 | F84: 5000 | G84: 144 | H84: 14,5x20,5 | I84: 0 | J84: KT | K84: 2/2011 | L84: Cty TNHH Đầu tư và phát triển công nghệ truyền thông Hà Nội
A85: 83 | B85: Luật thi hành án dân sự | C85: QH, CP | D85: TPH | E85: TB | F85: 2034 | G85: 164 | H85: 13x19 | I85: 20000 | J85: PL | K85: 2/2011 | L85: Cty CP in Tổng Hợp Cần Thơ
A86: 84 | B86: Luật bảo hiểm y tế | C86: QH, CP | D86: TPH | E86: TB | F86: 2034 | G86: 48 | H86: 13x19 | I86: 9000 | J86: PL | K86: 2/2011 | L86: Cty CP in Tổng Hợp Cần Thơ
A87: 85 | B87: Luật cán bộ công chức | C87: QH, CP | D87: TPH | E87: TB | F87: 2034 | G87: 60 | H87: 13x19 | I87: 9500 | J87: PL | K87: 2/2011 | L87: Cty CP in Tổng Hợp Cần Thơ
A88: 86 | B88: Luật bảo hiểm xã hội | C88: QH, CP | D88: TPH | E88: TB | F88: 2034 | G88: 88 | H88: 13x19 | I88: 13000 | J88: PL | K88: 2/2011 | L88: Cty CP in Tổng Hợp Cần Thơ
A89: 87 | B89: Văn kiện Quốc hội toàn tập, tập 7 (1987 - 1992) quyển 3 (1991 - 1992) | C89: Quốc hội nước Cộng hoà xã hội chủ nghĩa Việt Nam | D89: LKTG | E89: 1 | F89: 1600 | G89: 1676 | H89: 16x24 | I89: 0 | J89: PL | K89: 2/2011 | L89: Cty in Tiến Bộ
A90: 88 | B90: Luật sử dụng năng lượng tiết kiệm và hiệu quả | C90: QH, CP | D90: TPH | E90: TB | F90: 1034 | G90: 48 | H90: 13x19 | I90: 8000 | J90: PL | K90: 2/2011 | L90: Cty in Tổng Hợp Cần Thơ
A91: 89 | B91: Luật phòng chống bạo lực gia đình | C91: QH, CP | D91: TPH | E91: TB | F91: 1034 | G91: 40 | H91: 13x19 | I91: 7000 | J91: PL | K91: 2/2011 | L91: Cty in Tổng Hợp Cần Thơ
A92: 90 | B92: Luật ngân hàng nhà nước VN | C92: QH, CP | D92: TPH | E92: TB | F92: 1034 | G92: 44 | H92: 13x19 | I92: 8000 | J92: PL | K92: 2/2011 | L92: Cty in Tổng Hợp Cần Thơ
A93: 91 | B93: Luật giao thông đường bộ | C93: QH, CP | D93: TPH | E93: TB | F93: 2034 | G93: 92 | H93: 13x19 | I93: 13000 | J93: PL | K93: 2/2011 | L93: Cty in Tổng Hợp Cần Thơ
A94: 92 | B94: Lịch sử công tác Đảng, công tác chính trị Cục hậu cần Quân khu 7 (1945 - 2010) | C94: Bộ tư lệnh Quân khu 7 Cục hậu cần | D94: LKTG | E94: 1 | F94: 630 | G94: 516 | H94: 16x24 | I94: 0 | J94: TPHCM | K94: 2/2011 | L94: Cty in Báo Nhân Dân
A95: 93 | B95: Lịch sử Tiểu đoàn 440 Bà Rịa - Long Khánh (1967 - 1979) | C95: Đảng ủy - Bộ chỉ huy quân sự tỉnh Bà Rịa - Vũng Tàu | D95: LKTG | E95: 1 | F95: 830 | G95: 280 | H95: 14,5x20,5 | I95: 0 | J95: TPHCM | K95: 2/2011 | L95: Cty in Khuyến học phía Nam
A96: 94 | B96: Ký ức đời tôi (Hồi ký) | C96: Thiếu tướng Nguyễn Văn Lưỡng | D96: QLP | E96: 1 | F96: 500 | G96: 312 | H96: 14,5x20,5 | I96: 0 | J96: Cần Thơ | K96: 2/2011 | L96: Xưởng in Quân khu 9
A97: 95 | B97: Điều lệ Đảng Cộng sản Việt Nam | C97: ĐCSVN | D97: TPH | E97: 1 | F97: 64000 | G97: 72 | H97: 10x14,5 | I97: 7000 | J97: Đg | K97: 3/2011 | L97: Cty in Tiến Bộ Hà Nội
A98: 96 | B98: Cương lĩnh chính trị - ngọn cờ tư tưởng lý luận chỉ đạo sự nghiệp cách mạng của chúng ta | C98: GS.TS. Nguyễn Phú Trọng | D98: TPH | E98: TB | F98: 3100 | G98: 96 | H98: 13x19 | I98: 14000 | J98: GK | K98: 3/2011 | L98: Xưởng in NXB Dân tộc văn hoá
A99: 97 | B99: Chiến lược phát triển kinh tế-xã hội 2011-2020 | C99: ĐCSVN | D99: TPH | E99: 1 | F99: 5200 | G99: 68 | H99: 13x19 | I99: 10000 | J99: Đg | K99: 3/2011 | L99: CTy TNHH in THương mại Thuận Phát
A100: 98 | B100: Cương lĩnh xây dựng đất nước trong thời kỳ quá độ lên chủ nghĩa xã hội (Bổ sung phát triển năm 2011) | C100: ĐCSVN | D100: TPH | E100: 1 | F100: 5200 | G100: 36 | H100: 13x19 | I100: 7000 | J100: Đg | K100: 3/2011 | L100: CTy TNHH in THương mại Thuận Phát
...

Sheet 2012
A2: TT | B2: Tên sách | C2: Tác giả | D2: Phương thức | E2: Lần xuất bản | F2: SL in | G2: Trang | H2: Khổ | I2: Giá bìa | J2: BBT | K2: QĐXB | L2: Nơi in | M2: Ghi chú
A3: 1 | B3: Luật cơ yếu | C3: QH | D3: TPH | E3: 1 | F3: 3200 | G3: 32 | H3: 13x19 | I3: 8000 | J3: PL | K3: 1/2012 | L3: In Giao thông | M3: BC tuần (16 đến 20/1/2012): 9 cuốn
A4: 2 | B4: Các văn bản thực hiện Nghị quyết Đại hội đại biểu Đảng bộ huyện Đan Phượng lần thứ XXII, nhiệm kỳ 2010-2015 | C4: Ban Chấp hành Đảng bộ huyện Đan Phượng | D4: LKTG | E4: 1 | F4: 330 | G4: 216 | H4: 13x19 | I4: 0 | J4: TT NCKH | K4: 1/2012 | L4: Nhà in Sự thật
A5: 3 | B5: Công tác giám sát góp phần ngăn ngừa nguy cơ của Đảng cầm quyền | C5: Tập thể tác giả | D5: TPH | E5: 1 | F5: 500 | G5: 404 | H5: 14,5x20,5 | I5: 65000 | J5: SGK | K5: 1/2012 | L5: Nhà in Sự thật
A6: 4 | B6: Ngoại giao Việt Nam- Góc nhìn và suy ngẫm (Sách tham khảo) | C6: Nguyễn Khắc Huỳnh | D6: TPH | E6: 1 | F6: 800 | G6: 288 | H6: 14,5x20,5 | I6: 48000 | J6: QT | K6: 1/2012 | L6: Nhà in Sự thật
A7: 5 | B7: Phát huy vai trò của các tổ chức xã hội ở VN | C7: TS.Thang Văn Phúc, PGS, TS. Nguyễn Minh Phương (Đồng chủ biên) | D7: TPH | E7: 1 | F7: 600 | G7: 420 | H7: 14,5x20,5 | I7: 67000 | J7: SGK | K7: 1/2012 | L7: Nhà in Sự thật
A8: 6 | B8: Tác động của dư luận xã hội đối với ý thức pháp luật của đội ngũ cán bộ cấp cơ sở | C8: TS. Ngọ Văn Nhân | D8: TPH | E8: 1 | F8: 800 | G8: 380 | H8: 14,5x20,5 | I8: 61000 | J8: KĐLL | K8: 1/2012 | L8: Nhà in Sự thật
A9: 7 | B9: Đại biểu Quốc hội khóa XIII (2011-2016) | C9: Quốc hội nước CHXHCN VN | D9: LKTG | E9: 1 | F9: 1700 | G9: 256 | H9: 15x22 | I9: 0 | J9: KT | K9: 1/2012 | L9: In Ngọc Châu
A10: 8 | B10: Giá trị tinh thần truyền thống của dân tộc Việt Nam | C10: GS, NGND Trần Văn Giàu | D10: TWĐH+TPH | E10: 1 | F10: 1000 | G10: 476 | H10: 15x22 | I10: 0 | J10: CN tp HCM | K10: 1/2012 | L10: Cty In báo ND TP HCM
A11: 9 | B11: Văn kiện Quốc hội Toàn tập, tập 8 (1992-1997), quyển 2 (1994-1995) | C11: QH | D11: LKTG | E11: 1 | F11: 1600 | G11: 1400 | H11: 16x24 | I11: 0 | J11: PL | K11: 1/2012 | L11: Cty in Tiến bộ
A12: 10 | B12: Quy định pháp luật về xử phạt vi phạm hành chính về thuốc, mỹ phẩm, trang thiết bị y tế, khám bệnh, chữa bệnh | C12: QH | D12: TPH | F12: 600 | G12: 200 | H12: 13x19 | I12: 29000 | J12: PL | K12: 2/2012 | L12: Nhà in Sự thật | M12: BC tuần (30/1 đến 3/2/2012): 9 cuốn
A13: 11 | B13: Chuyện kể về một thời (Hồi ký) | C13: Lê Hữu Thăng | D13: LKTG | E13: 1 | F13: 1500 | G13: 336 | H13: 13,5x20,5 | I13: 85000 | J13: KĐLL | K13: 2/2012 | L13: In Truyền thông VN
A14: 12 | B14: Câu hỏi và trả lời về môn Thể chế chính trị thế giới đương đại (Sách tham khảo) | C14: TS. Nguyễn Thị Phượng | D14: TPH | F14: 700 | G14: 300 | H14: 14,5x20,5 | I14: 50000 | J14: PL | K14: 2/2012 | L14: Nhà in Sự thật
A15: 13 | B15: Lịch sử Đảng bộ và nhân dân xã Tây Kỳ (1930-2010) | C15: Ban Chấp hành Đảng bộ xã Tây Kỳ | D15: LKTG | E15: 1 | F15: 300 | G15: 400 | H15: 14,5x20,5 | I15: 0 | J15: TT PH | K15: 2/2012 | L15: Nhà in Sự thật
A16: 14 | B16: Luật khám bệnh, chữa bệnh năm 2009 và văn bản hướng dẫn thi hành | C16: QH | D16: TPH | F16: 1400 | G16: 488 | H16: 14,5x20,5 | I16: 73000 | J16: PL | K16: 2/2012 | L16: Nhà in Sự thật
A17: 15 | B17: Dịch vụ logistics ở Việt Nam trong tiến trình hội nhập quốc tế (Sách chuyên khảo) | C17: Trường đại học Kinh tế quốc dân, Viện nghiên cứu Kinh tế và Phát triển, GS, TS, NGƯT Đặng Đình Đào - TS. Nguyễn Minh Sơn (Đồng chủ biên) | D17: LKTG | E17: 1 | F17: 500 | G17: 508 | H17: 14,5x20,5 | I17: 115000 | J17: Đảng | K17: 2/2012 | L17: Cty CP in HN
A18: 16 | B18: Kỷ yếu hoạt động của Đoàn đại biểu Quốc hội tỉnh Lạng Sơn khóa XI, XII | C18: Quốc hội nước CHXHCNVN, Đoàn đại biểu Quốc hội tỉnh Lạng Sơn | D18: LKTG | E18: 1 | F18: 300 | G18: 448 | H18: 14,5x20,5 | I18: 0 | J18: KT | K18: 2/2012 | L18: In Ngọc Châu
A19: 17 | B19: Lịch sử Đảng bộ huyện Thanh Trì (1930-2010) | C19: Đảng bộ Thành phố Hà Nội, Ban Chấp hành Đảng bộ huyện Thanh Trì | D19: LKTG | E19: 1 | F19: 1000 | G19: 516 | H19: 15,5x23,5 | I19: 0 | J19: Đảng | K19: 2/2012 | L19: In Truyền thông VN
A20: 18 | B20: Ban Chỉ đạo và Văn phòng Ban Chỉ đạo Trung ương về phòng, chống tham nhũng (2006-2011) | C20: Văn phòng Ban Chỉ đạo Trung ương về phòng, chống tham nhũng | D20: LKTG | E20: 1 | F20: 700 | G20: 392 | H20: 20x28 | I20: 0 | J20: TT NCKH | K20: 2/2012 | L20: In và VHP
A21: 19 | B21: Lịch sử ngành Dầu khí VN (Đến năm 2010), tập I | C21: Tập đoàn Dầu khí VN | D21: LKTG | E21: 1 | F21: 5000 | G21: 450 | H21: 19x27 | I21: 0 | J21: KT | K21: 2/2012 | L21: Cty TNHH MTV In báo Nhân dân | M21: BC tuần (6 đến 10/2/2012): 7 cuốn
A22: 20 | B22: Lịch sử ngành Dầu khí VN (Đến năm 2010), tập II | C22: Tập đoàn Dầu khí VN | D22: LKTG | E22: 1 | F22: 5000 | G22: 684 | H22: 19x27 | I22: 0 | J22: KT | K22: 2/2012 | L22: Cty TNHH MTV In báo Nhân dân
A23: 21 | B23: Lịch sử ngành Dầu khí VN (Đến năm 2010), tập III | C23: Tập đoàn Dầu khí VN | D23: LKTG | E23: 1 | F23: 5000 | G23: 592 | H23: 19x27 | I23: 0 | J23: KT | K23: 2/2012 | L23: Cty TNHH MTV In báo Nhân dân
A24: 22 | B24: Văn bản của Ban Chấp hành Trung ương, Bộ Chính trị, Ban Bí thư và Ủy ban Kiểm tra Trung ương về công tác kiểm tra, giám sát và kỷ luật của Đảng | C24: Ủy ban Kiểm tra Trung ương | D24: TPH | E24: 1 | F24: 25038 | G24: 352 | H24: 13x19 | I24: 47000 | J24: SGK | K24: 2/2012 | L24: Cty in Tiến bộ
A25: 23 | B25: Một số vấn đề chính trị quốc tế trong giai đoạn hiện nay | C25: PGS, TS. Ng. Hoàng Giáp (Chủ biên), PGS, TS. Ng. Thị Quế, PGS, TS. Thái Văn Long, PGS, TS. Phan Văn Rân | D25: TPH | E25: 1 | F25: 500 | G25: 304 | H25: 14,5x20,5 | I25: 51000 | J25: Đảng | K25: 2/2012 | L25: Nhà in Sự thật
A26: 24 | B26: Phát triển đồng bộ và tương xứng văn hóa với kinh tế | C26: Viện nghiên cứu Phát triển thành phố Hồ Chí Minh, TS. Hồ Bá Thâm (Chủ biên) | D26: TPH | E26: 1 | F26: 500 | G26: 360 | H26: 14,5x20,5 | I26: 71000 | J26: CN tp HCM | K26: 2/2012 | L26: Cty In báo ND TP HCM
A27: 25 | B27: Phong trào chấn hưng Phật giáo ở miền Bắc Việt Nam (1924-1954) | C27: Lê Tâm Đắc | D27: TPH | E27: 1 | F27: 500 | G27: 304 | H27: 14,5x20,5 | I27: 51000 | J27: Đảng | K27: 2/2012 | L27: Nhà in Sự thật
A28: 26 | B28: Truyền thông- lý thuyết và kỹ năng cơ bản | C28: Học viện Báo chí và Tuyên truyền, PGS, TS. Ng. Văn Dững (Chủ biên), TS. Đỗ Thị Thu Hằng | D28: TPH | E28: TB | F28: 1550 | G28: 315 | H28: 14,5x20,5 | I28: 52000 | J28: QT | K28: 2/2012 | L28: In và TM Thuận Phát
A29: 27 | B29: Lịch sử Đảng bộ và nhân dân xã Trung Hải (1930-2010) | C29: Ban Chấp hành Đảng bộ xã Trung Hải | D29: LKTG | E29: 1 | F29: 400 | G29: 456 | H29: 14,5x20,5 | I29: 0 | J29: Đảng | K29: 2/2012 | L29: In Truyền thông VN
A30: 28 | B30: Quy định xử phạt vi phạm hành chính trong lĩnh vực giao thông đường thủy nội địa | C30: QH | D30: TPH | E30: 1 | F30: 700 | G30: 160 | H30: 13x19 | I30: 25000 | J30: PL | K30: 2/2012 | L30: Nhà in Sự thật | M30: BC tuần (13 đến 17/2/2012): 6 cuốn
A31: 29 | B31: Quy định pháp luật về xử phạt vi phạm hành chính trong lĩnh vực điện lực | C31: QH | D31: TPH | E31: 1 | F31: 550 | G31: 104 | H31: 13x19 | I31: 18000 | J31: PL | K31: 2/2012 | L31: Nhà in Sự thật
A32: 30 | B32: Giáo trình Lôgíc học (Tài liệu hướng dẫn nghiên cứu và ứng dụng thực tiễn) | C32: Học viện Chính sách và Phát triển, PGS,TS. Trần Đình Thảo (Chủ biên) | D32: LKTG | E32: 1 | F32: 500 | G32: 232 | H32: 14,5x20,5 | I32: 58000 | J32: KT | K32: 2/2012 | L32: Nhà in Sự thật
A33: 31 | B33: Đồng chí Đỗ Mười- Dấu ấn qua những chặng đường lịch sử | C33: Tập thể tác giả | D33: TWĐH | E33: 1 | F33: 1000 | G33: 532 | H33: 15x22 | I33: 0 | J33: KĐLL | K33: 2/2012 | L33: Cty in Tiến bộ
A34: 32 | B34: The effects of foreign direct investment on economic growth and income convergence in the Association of Southeast Asian Nations | C34: Le Van Chien, PhD | D34: QLP | E34: 1 | F34: 200 | G34: 268 | H34: 16x24 | I34: 95000 | J34: SGK | K34: 2/2012 | L34: Cty in NXB VHDT
A35: 33 | B35: Kỷ yếu Vụ Cán bộ Ban Tổ chức Trung ương Đảng - Tổ chức, hoạt động và các thành viên | C35: Ban liên lạc Vụ Cán bộ | D35: LKTG | E35: 1 | F35: 240 | G35: 127 | H35: 16x24 | I35: 0 | J35: Vụ Tổ chức | K35: 2/2012 | L35: Nhà in Sự thật
A36: 34 | B36: Những vấn đề lý luận thực tiễn về Luật hình sự quốc tế | C36: ĐH Quốc gia HN, khoa Luật, TS. Nguyễn Ngọc Chí (Chủ biên) | D36: QLP | E36: 1 | F36: 500 | G36: 276 | H36: 16x24 | I36: 0 | J36: PL | K36: 2/2012 | L36: Cty CP in Sách Việt Nam | M36: BC tuần (20 đến 24/2/2012): 14 cuốn
A37: 35 | B37: Giáo trình Lịch sử Đảng Cộng sản Việt Nam (Tái bản có sửa chữa, bổ sung) | C37: Hội đồng Trung ương chỉ đạo biên soạn giáo trình quốc gia các bộ môn khoa học Mác-Lênin, tư tưởng HCM | D37: TPH | E37: TB | F37: 1037 | G37: 509 | H37: 14,5x20,5 | I37: 80000 | J37: SGK | K37: 2/2012 | L37: In khuyến học phía Nam
A38: 36 | B38: Người Hoa ở Bình Dương | C38: Hội Khoa học lịch sử tỉnh Bình Dương, TS. Huỳnh Ngọc Đáng (Chủ biên) | D38: LKTG | E38: 1 | F38: 930 | G38: 592 | H38: 19x27 | I38: 0 | J38: CN tp HCM | K38: 2/2012 | L38: Cty In báo ND TP HCM
A39: 37 | B39: Thăng Long - Hà Nội- Truyền thống, tầm nhìn, động lực vươn tới | C39: Phạm Quang Nghị | D39: LKTG | E39: 1 | F39: 1000 | G39: 600 | H39: 16x24 | I39: 0 | J39: QT | K39: 2/2012 | L39: Cty in Tiến bộ
A40: 38 | B40: Lịch sử miền Đông Nam Bộ và cực Nam Trung Bộ kháng chiến (1945-1975) | C40: Đảng ủy, Bộ Tư lệnh Quân khu 7 | D40: TWĐH | E40: 1 | F40: 1000 | G40: 914 | H40: 16x24 | I40: 0 | J40: CN tp HCM | K40: 2/2012 | L40: Cty In báo ND TP HCM
A41: 39 | B41: Hiến pháp nước CHXHCN Việt Nam năm 1992 (Đã được sửa đổi, bổ sung năm 2001) | C41: QH | D41: TPH | E41: TB | F41: 1037 | G41: 107 | H41: 13x19 | I41: 20000 | J41: PL | K41: 2/2012 | L41: Cty In báo ND TP HCM
A42: 40 | B42: Bộ luật lao động của nước CHXHCN Việt Nam (Sửa đổi, bổ sung các năm 2002, 2006, 2007) Văn bản hợp nhất Bộ luật lao động qua các lần sửa đổi, bổ sung (Tái bản lần thứ sáu) | C42: QH | D42: TPH | E42: 6 | F42: 2037 | G42: 128 | H42: 13x19 | I42: 21000 | J42: PL | K42: 2/2012 | L42: Nhà in Sự thật
A43: 41 | B43: Cơ cấu xã hội, phân tầng xã hội trong điều kiện đổi mới ở Việt Nam | C43: GS, TS. Lê Hữu Nghĩa - GS, TS. Lê Ngọc Hùng (Đồng chủ biên) | D43: TPH | E43: 1 | F43: 480 | G43: 340 | H43: 14,5x20,5 | I43: 56000 | J43: Đảng | K43: 2/2012 | L43: Nhà in Sự thật
A44: 42 | B44: Hỏi - đáp về chế độ, chính sách đối với cán bộ, công chức xã, phường, thị trấn | C44: ThS. Nguyễn Thế Vịnh, CN. Nguyễn Thị Ngọc Anh (Đồng chủ biên) | D44: Tủ sách xã phường | F44: 1500 | G44: 220 | H44: 12,5x20,5 | I44: 39000 | J44: Đảng | K44: 2/2012 | L44: Nhà in Sự thật
A45: 43 | B45: Tài liệu học tập Kết luận Hội nghị lần thứ ba Ban Chấp hành Trung ương Đảng khóa XI (Dùng cho cán bộ, đảng viên ở cơ sở) | C45: Ban Tuyên giáo Trung ương | D45: TPH (trợ giá) | E45: 1 | F45: 9000 | G45: 56 | H45: 13x19 | I45: 4500 | J45: SGK | K45: 2/2012 | L45: Cty in Tiến bộ
A46: 44 | B46: Học tập và làm theo tấm gương đạo đức HCM suốt đời phấn đấu cần, kiệm, liêm, chính, chí công vô tư, làm người công bộc tận tụy, trung thành của nhân dân, đời tư trong sáng, cuộc sống riêng giản dị (Tài liệu sinh hoạt chi bộ, đoàn thể và tại các cơ quan, đơn vị năm 2011-2012) | C46: Ban Tuyên giáo Trung ương | D46: TPH (trợ giá) | E46: 1 | F46: 5000 | G46: 68 | H46: 10x14.5 | I46: 5000 | J46: SGK | K46: 2/2012 | L46: Cty in Tiến bộ
A47: 45 | B47: Hồ Chí Minh về suốt đời phấn đấu cần, kiệm, liêm, chính, chí công vô tư, làm người công bộc tận tụy, trung thành của nhân dân, đời tư trong sáng, cuộc sống riêng giản dị (Tài liệu tham khảo) | C47: Ban Tuyên giáo Trung ương | D47: TPH (trợ giá) | E47: 1 | F47: 5000 | G47: 180 | H47: 10x14.5 | I47: 12000 | J47: SGK | K47: 2/2012 | L47: In và VHP
A48: 46 | B48: C.Mác-Ăngghen Tuyển tập, tập II, tiếng Lào | C48: Mác, Ph.Ăngghen | D48: LKTG | E48: 1 | F48: 500 | G48: 1044 | H48: 15x22 | I48: 0 | J48: SGK | K48: 2/2012 | L48: Cty in Tiến bộ
A49: 47 | B49: Hồ Chí Minh Tuyển tập, tập III (1954-1969), tiếng Lào | C49: Hồ Chí Minh | D49: LKTG | E49: 1 | F49: 500 | G49: 1008 | H49: 15x22 | I49: 0 | J49: SGK | K49: 2/2012 | L49: Cty in Tiến bộ | Q49: 540
A50: 48 | B50: Luật khiếu nại | C50: QH | D50: TPH | F50: 4037 | G50: 68 | H50: 13x19 | I50: 12000 | J50: PL | K50: 2/2012 | L50: Cty CP In Tổng hợp Cần Thơ | M50: BC tuần (27/2 đến 2/3/2012): 19 cuốn
A51: 49 | B51: Bộ luật dân sự | C51: QH | D51: TPH | E51: TB | F51: 2037 | G51: 388 | H51: 13x19 | I51: 45000 | J51: PL | K51: 2/2012 | L51: Cty CP In Tổng hợp Cần Thơ
A52: 50 | B52: Luật tố cáo | C52: QH | D52: TPH | E52: TB | F52: 4037 | G52: 48 | H52: 13x19 | I52: 10000 | J52: PL | K52: 2/2012 | L52: Cty CP In Tổng hợp Cần Thơ
A53: 51 | B53: Luật phòng, chống mua bán người | C53: QH | D53: TPH | E53: TB | F53: 2037 | G53: 44 | H53: 13x19 | I53: 8000 | J53: PL | K53: 2/2012 | L53: Cty CP In Tổng hợp Cần Thơ
A54: 52 | B54: Luật đo lường | C54: QH | D54: TPH | F54: 4037 | G54: 52 | H54: 13x19 | I54: 11000 | J54: PL | K54: 2/2012 | L54: Cty CP In Tổng hợp Cần Thơ
A55: 53 | B55: Luật lưu trữ | C55: QH | D55: TPH | F55: 4037 | G55: 44 | H55: 13x19 | I55: 10000 | J55: PL | K55: 2/2012 | L55: Cty CP In Tổng hợp Cần Thơ
A56: 54 | B56: Bộ luật tố tụng dân sự năm 2004 sửa đổi, bổ sung năm 2011 | C56: QH | D56: TPH | F56: 2037 | G56: 376 | H56: 13x19 | I56: 48000 | J56: PL | K56: 2/2012 | L56: Cty CP In Tổng hợp Cần Thơ
A57: 55 | B57: Tiểu đoàn 307 trong kháng chiến chống thực dân Pháp (1948-1954) | C57: Đảng ủy - Bộ Tư lệnh Quân khu 9 | D57: LKTG | E57: 1 | F57: 1000 | G57: 272 | H57: 14,5x20,5 | I57: 0 | J57: CN Cần Thơ | K57: 2/2012 | L57: Cty CP In Tổng hợp Cần Thơ
A58: 56 | B58: Cẩm nang về kỹ năng giám sát của Đảng (Xuất bản lần thứ hai có bổ sung, sửa chữa) | C58: Hội đồng chỉ đạo xuất bản sách xã, phường, thị trấn | D58: Tủ sách xã phường | E58: 2 | F58: 9090 | G58: 244 | H58: 12,5x20,5 | I58: 0 | J58: SGK | K58: 2/2012 | L58: XN in Tổng cục CNQP
A59: 57 | B59: Định hướng xã hội chủ nghĩa - tiến tới xã hội nhân đạo hoàn bị (Sách chuyên khảo) | C59: GS, TS. Lưu Văn Sùng | D59: TPH | E59: 1 | F59: 500 | G59: 196 | H59: 13x19 | I59: 29000 | J59: PL | K59: 2/2012 | L59: Nhà in Sự thật
A60: 58 | B60: Các kỹ năng cần thiết dành cho cán bộ chính quyền cấp cơ sở | C60: TS.Nguyễn Thị Hà, ThS. Lê Văn Hòa (Đồng chủ biên) | D60: TPH | F60: 850 | G60: 336 | H60: 12,5x20,5 | I60: 55000 | J60: KT | K60: 2/2012 | L60: Nhà in Sự thật
A61: 59 | B61: Tài liệu học tập lý luận chính trị dành cho học viên lớp đối tượng kết nạp Đảng (Sửa chữa, bổ sung theo Văn kiện Đại hội XI của Đảng) | C61: Ban Tuyên giáo Trung ương | D61: TPH | E61: TB | F61: 5037 | G61: 212 | H61: 13x19 | I61: 27000 | J61: SGK | K61: 2/2012 | L61: Nhà in Sự thật
A62: 60 | B62: Tìm hiểu pháp luật về phòng, chống ma túy | C62: GS, TS. Nguyễn Ngọc Anh, ThS. Đỗ Khắc Hưởng, ThS. Nguyễn Ngọc Vân | D62: TPH | E62: 1 | F62: 900 | G62: 192 | H62: 12,5x20,5 | I62: 35000 | J62: PL | K62: 2/2012 | L62: Nhà in Sự thật
A63: 61 | B63: Luật thi hành án hình sự năm 2010 và văn bản hướng dẫn thi hành | C63: QH | D63: TPH | E63: 1 | F63: 1800 | G63: 324 | H63: 13x19 | I63: 42000 | J63: PL | K63: 2/2012 | L63: Nhà in Sự thật
A64: 62 | B64: 100 câu hỏi - đáp về nhiệm vụ giữ gìn an ninh trật tự của thôn, tổ dân phố | C64: Hội đồng chỉ đạo xuất bản sách xã, phường, thị trấn | D64: Tủ sách xã phường | E64: 1 | F64: 14250 | G64: 135 | H64: 12,5x20,5 | I64: 0 | J64: Vụ KH | K64: 2/2012 | L64: XN in Tổng cục CNQP
A65: 63 | B65: Những điều cần biết khi sống chung với điện | C65: Hội đồng chỉ đạo xuất bản sách xã, phường, thị trấn | D65: Tủ sách xã phường | E65: 1 | F65: 14250 | G65: 147 | H65: 12,5x20,5 | I65: 0 | J65: Vụ KH | K65: 2/2012 | L65: XN in Tổng cục CNQP
A66: 64 | B66: Hỏi - đáp về tình hình thế giới và chính sách đối ngoại của Đảng và Nhà nước ta | C66: Học viện Ngoại giao | D66: TPH | E66: TB | F66: 600 | G66: 464 | H66: 12,5x20,5 | I66: 73000 | J66: QT | K66: 2/2012 | L66: Nhà in Sự thật
A67: 65 | B67: Luật cán bộ, công chức năm 2008 và văn bản hướng dẫn thi hành (Tái bản lần thứ nhất có bổ sung) | C67: QH | D67: TPH | E67: TB | F67: 1000 | G67: 604 | H67: 14,5x20,5 | I67: 88000 | J67: PL | K67: 2/2012 | L67: Nhà in Sự thật
A68: 66 | B68: Thịnh vượng chung - Kinh tế học cho hành tinh đông đúc (Sách tham khảo) | C68: Jeffrey D. Sachs | D68: TWĐH | E68: 1 | F68: 1000 | G68: 592 | H68: 14,5x20,5 | I68: 0 | J68: QT | K68: 2/2012 | L68: Cty TNHH MTV In- TM TTXVN
A69: 67 | B69: Văn kiện Quốc hội Toàn tập, tập 8 (1992-1997), quyển 3 (1995-1996) | C69: Quốc hội nước CHXHCN VN | D69: LKTG | E69: 1 | F69: 1600 | G69: 1796 | H69: 16x24 | I69: 0 | J69: PL | K69: 3/2012 | L69: Cty in Tiến bộ | M69: BC tuần (5 đến 9/3/2012): 20 cuốn
A70: 68 | B70: Từ điển kinh tế Nga-Việt-Anh | C70: Tập thể tác giả | D70: TPH | E70: 1 | F70: 500 | G70: 440 | H70: 14x22 | I70: 84000 | J70: Đảng | K70: 3/2012 | L70: Nhà in Sự thật
A71: 69 | B71: Lịch sử Đảng bộ huyện Quảng Uyên (1930-2010) | C71: Đảng bộ tỉnh Cao Bằng, Ban Chấp hành Đảng bộ huyện Quảng Uyên | D71: LKTG | E71: 1 | F71: 700 | G71: 456 | H71: 14,5x20,5 | I71: 0 | J71: SGK | K71: 3/2012 | L71: In và VHP
A72: 70 | B72: Tôn giáo và quan hệ quốc tế (Sách tham khảo) | C72: Học viện Ngoại giao, PGS.TS. Lê Thanh Bình - ThS. Đỗ Thanh Hải (Đồng chủ biên) | D72: TPH | E72: 1 | F72: 730 | G72: 252 | H72: 14,5x20,5 | I72: 43000 | J72: KĐLL | K72: 3/2012 | L72: In và VHP
A73: 71 | B73: Một số giải pháp bảo đảm việc chấp hành kỷ luật và thi hành kỷ luật trong Đảng hiện nay | C73: ThS. Nguyễn Công Học (Chủ biên) | D73: TPH | E73: 1 | F73: 500 | G73: 200 | H73: 14,5x20,5 | I73: 36000 | J73: SGK | K73: 3/2012 | L73: Nhà in Sự thật
A74: 72 | B74: Nhập môn tin học | C74: Hội đồng chỉ đạo xuất bản sách xã, phường, thị trấn | D74: Tủ sách xã phường | F74: 14250 | G74: 256 | H74: 12,5x20,5 | I74: 0 | J74: Vụ KH | K74: 3/2012 | L74: Cty in Tiến bộ
A75: 73 | B75: Các kỹ năng cần thiết dành cho cán bộ chính quyền cấp cơ sở | C75: Hội đồng chỉ đạo xuất bản sách xã, phường, thị trấn | D75: Tủ sách xã phường | F75: 14250 | G75: 336 | H75: 12,5x20,5 | I75: 0 | J75: KT | K75: 3/2012 | L75: Nhà in Sự thật
A76: 74 | B76: Hỏi - đáp về tình hình thế giới và chính sách đối ngoại của Đảng và Nhà nước ta | C76: Hội đồng chỉ đạo xuất bản sách xã, phường, thị trấn | D76: Tủ sách xã phường | F76: 9090 | G76: 308 | H76: 12,5x20,5 | I76: 0 | J76: QT | K76: 3/2012 | L76: Cty in Tiến bộ
A77: 75 | B77: Hỏi - đáp về dinh dưỡng | C77: Hội đồng chỉ đạo xuất bản sách xã, phường, thị trấn | D77: Tủ sách xã phường | F77: 14250 | G77: 203 | H77: 12,5x20,5 | I77: 0 | J77: Vụ KH | K77: 3/2012 | L77: In và TM Thuận Phát
A78: 76 | B78: Hỏi - đáp về lãnh đạo, quản lý của ủy ban nhân dân cấp xã (Tái bản có sửa chữa, bổ sung) | C78: Hội đồng chỉ đạo xuất bản sách xã, phường, thị trấn | D78: Tủ sách xã phường | E78: TB | F78: 9090 | G78: 292 | H78: 12,5x20,5 | I78: 0 | J78: SGK | K78: 3/2012 | L78: In và TM Thuận Phát
A79: 77 | B79: Tìm hiểu pháp luật về phòng, chống ma túy | C79: Hội đồng chỉ đạo xuất bản sách xã, phường, thị trấn | D79: Tủ sách xã phường | F79: 14250 | G79: 192 | H79: 12,5x20,5 | I79: 0 | J79: PL | K79: 3/2012 | L79: Nhà in Sự thật
A80: 78 | B80: Cẩm nang tư vấn, phản biện và đóng góp xây dựng chính sách của các tổ chức xã hội Việt Nam | C80: Trung tâm nghiên cứu quản lý và phát triển bền vững- Quỹ hỗ trợ các sáng kiến tư pháp | D80: TPH | E80: 1 | F80: 338 | G80: 104 | H80: 13x19 | I80: 0 | J80: PL | K80: 3/2012 | L80: In Học Liệu
A81: 79 | B81: Tài liệu nghiên cứu Kết luận Hội nghị lần thứ ba Ban Chấp hành Trung ương Đảng khóa XI (Dùng cho cán bộ chủ chốt và báo cáo viên) | C81: Ban Tuyên giáo Trung ương | D81: TPH | E81: TB | F81: 2037 | G81: 72 | H81: 13x19 | I81: 5500 | J81: SGK | K81: 3/2012 | L81: XN in Tổng cục CNQP
A82: 80 | B82: Hỏi - đáp về chính sách dân số và xây dựng gia đình Việt Nam (Tái bản có sửa chữa, bổ sung) | C82: Hội đồng chỉ đạo xuất bản sách xã, phường, thị trấn | D82: Tủ sách xã phường | F82: 9090 | G82: 180 | H82: 12,5x20,5 | I82: 0 | J82: QT | K82: 3/2012 | L82: XN in ACS Việt Nam
A83: 81 | B83: 152 thủ tục hành chính về thuế (Được thực hiện ở cấp Chi cục Thuế) | C83: Hội đồng chỉ đạo xuất bản sách xã, phường, thị trấn | D83: Tủ sách xã phường | F83: 14250 | G83: 384 | H83: 12,5x20,5 | I83: 0 | J83: KT | K83: 3/2012 | L83: XN in ACS Việt Nam
A84: 82 | B84: Hỏi - đáp về Đảng, Nhà nước, đoàn thể và công tác tổ chức, kiểm tra của Đảng (Tái bản có sửa chữa, bổ sung) | C84: Hội đồng chỉ đạo xuất bản sách xã, phường, thị trấn | D84: Tủ sách xã phường | F84: 9090 | G84: 268 | H84: 12,5x20,5 | I84: 0 | J84: Đảng | K84: 3/2012 | L84: XN in ACS Việt Nam
A85: 83 | B85: Cẩm nang công tác Hội Cựu chiến binh ở cơ sở | C85: Hội đồng chỉ đạo xuất bản sách xã, phường, thị trấn | D85: Tủ sách xã phường | F85: 14250 | G85: 300 | H85: 12,5x20,5 | I85: 0 | J85: KĐLL | K85: 3/2012 | L85: Nhà in Sự thật
A86: 84 | B86: Hỏi - đáp về chế độ, chính sách đối với cán bộ, công chức xã, phường, thị trấn | C86: Hội đồng chỉ đạo xuất bản sách xã, phường, thị trấn | D86: Tủ sách xã phường | F86: 14250 | G86: 220 | H86: 12,5x20,5 | I86: 0 | J86: Đảng | K86: 3/2012 | L86: Nhà in Sự thật
A87: 85 | B87: Điều lệ Đảng khóa XI và một số quy định, hướng dẫn thi hành | C87: Hội đồng chỉ đạo xuất bản sách xã, phường, thị trấn | D87: Tủ sách xã phường | F87: 2000 | G87: 228 | H87: 12,5x20,5 | I87: 0 | J87: Đảng | K87: 3/2012 | L87: Cty in Tiến bộ
A88: 86 | B88: Vận dụng học thuyết lưu thông tiền tệ của C.Mác trong điều tiết nền kinh tế ở VN hiện nay (Sách tham khảo) | C88: Học viện Chính trị-Hành chính quốc gia HCM, Viện Kinh tế- PGS, TS. Phạm Quốc Trung- PGS, TS. Phạm Thị Túy (Đồng chủ biên) | D88: TPH | E88: 1 | F88: 500 | G88: 251 | H88: 14,5x20,5 | I88: 43000 | J88: KT | K88: 3/2012 | L88: In và TM Thuận Phát
A89: 87 | B89: History of Vienam-Laos, Laos-Vietnam special relationship (1930-2007) | C89: ĐCS VN, ĐNDCM Lào | D89: TWĐH | E89: 1 | F89: 1000 | G89: 976 | H89: 16x24 | I89: 0 | J89: QT | K89: 3/2012 | L89: Cty in Tiến bộ | M89: BC tuần (12 đến 16/3): 15 cuốn
A90: 88 | B90: Hồ Chí Minh với con đường giải phóng dân tộc | C90: Tập thể tác giả | D90: TPH | E90: 1 | F90: 650 | G90: 424 | H90: 16x24 | I90: 70000 | J90: Đảng | K90: 3/2012 | L90: In- TM TTXVN
A91: 89 | B91: Bình luận khoa học Bộ luật hình sự năm 1999 sửa đổi, bổ sung năm 2009- Phần chung | C91: TS. Nguyễn Đức Mai (Chủ biên), TS. Đỗ Thị Ngọc Tuyết | D91: TPH | E91: 1 | F91: 1400 | G91: 244 | H91: 16x24 | I91: 55000 | J91: PL | K91: 3/2012 | L91: Nhà in Sự thật
A92: 90 | B92: Các đại hội và hội nghị Trung ương của Đảng Cộng sản Việt Nam thời kỳ đổi mới | C92: PGS, NGND. Lê Mậu Hãn- ThS. Thái Phương | D92: TPH | E92: 1 | F92: 700 | G92: 236 | H92: 14,5x20,5 | I92: 41000 | J92: KĐLL | K92: 3/2012 | L92: Nhà in Sự thật
A93: 91 | B93: Các nghị quyết và một số văn bản quan trọng tại kỳ họp thứ hai Quốc hội khóa XIII | C93: Quốc hội nước CHXHCN Việt Nam | D93: TPH | E93: 1 | F93: 2440 | G93: 320 | H93: 13x19 | I93: 42000 | J93: PL | K93: 3/2012 | L93: In- TM TTXVN
A94: 92 | B94: Trên những trận địa phòng không | C94: Trung tướng Nguyễn Xuân Mậu | D94: TPH | E94: 1 | F94: 800 | G94: 408 | H94: 15x22 | I94: 80000 | J94: KĐLL | K94: 3/2012 | L94: Nhà in Sự thật
A95: 93 | B95: Một số cảm nhận về tư tưởng- hành động của Hồ Chí Minh (Tái bản lần thứ nhất) | C95: Đoàn Duy Thành | D95: TPH | E95: TB | F95: 570 | G95: 156 | H95: 14,5x20,5 | I95: 24000 | J95: SGK | K95: 3/2012 | L95: XN in NXB VHDT
A96: 94 | B96: Tài liệu bồi dưỡng lý luận chính trị dành cho đảng viên mới | C96: Ban Tuyên giáo Trung ương | D96: TPH | E96: TB | F96: 10037 | G96: 212 | H96: 13x19 | I96: 27000 | J96: SGK | K96: 3/2012 | L96: Cty In báo ND TP HCM
A97: 95 | B97: Luật bảo vệ quyền lợi người tiêu dùng năm 2010 và một số văn bản hướng dẫn thi hành | C97: QH | D97: TPH | E97: 1 | F97: 1250 | G97: 100 | H97: 13x19 | I97: 17000 | J97: PL | K97: 3/2012 | L97: Nhà in Sự thật
A98: 96 | B98: Luật thanh tra năm 2010 và văn bản hướng dẫn thi hành | C98: QH | D98: TPH | E98: 1 | F98: 1300 | G98: 268 | H98: 13x19 | I98: 36000 | J98: PL | K98: 3/2012 | L98: Nhà in Sự thật
A99: 97 | B99: Tài liệu bồi dưỡng lý luận chính trị dành cho đảng viên mới | C99: Ban Tuyên giáo Trung ương | D99: TPH | E99: TB | F99: 4000 | G99: 212 | H99: 13x19 | I99: 27000 | J99: SGK | K99: 3/2012 | L99: In và TM Thuận Phát
A100: 98 | B100: Luật kinh doanh- Dùng cho đào tạo các ngành kinh tế, quản trị kinh doanh, tài chính- ngân hàng | C100: GVC, TS. Vũ Quang (Chủ biên) | D100: TPH | E100: 1 | F100: 1530 | G100: 444 | H100: 14,5x20,5 | I100: 65000 | J100: KT | K100: 3/2012 | L100: Nhà in Sự thật
A101: 99 | B101: Giáo trình Chủ nghĩa xã hội khoa học (Tái bản có sửa chữa, bổ sung) | C101: Hội đồng Trung ương chỉ đạo biên soạn giáo trình quốc gia các bộ môn khoa học Mác-Lênin, tư tưởng HCM | D101: TPH | E101: TB | F101: 1037 | G101: 556 | H101: 14,5x20,5 | I101: 87000 | J101: SGK | K101: 3/2012 | L101: Cty In báo ND TP HCM
...

Sheet 2013
B1: SÁCH XUẤT BẢN NĂM 2013
A3: TT | B3: Tên sách | C3: Tác giả | D3: Phương thức | E3: Lần XB | F3: SL in | G3: Số trang | H3: Khổ sách | I3: Giá bìa | J3: BBT | K3: Thời gian có sách | L3: Nơi in | M3: Ghi chú
A4: 1 | B4: Luật sửa đổi, bổ sung một số điều của Luật thuế thu nhập cá nhân | C4: QH | D4: TPH | E4: 1 | F4: 2000 | G4: 40 | H4: 13x19 | I4: 10000 | J4: PL | K4: 1-2013 | L4: TTXVN | M4: BC tuần (7 đến 11/1): 11
A5: 2 | B5: Luật hoạt động chữ thập đỏ | C5: QH | D5: TPH | E5: TB | F5: 4535 | G5: 28 | H5: 13x19 | I5: 7000 | J5: PL | K5: 1-2013 | L5: Nhà in ST
A6: 3 | B6: Pháp lệnh quản lý, sử dụng vũ khí, vật liệu nổ và công cụ hỗ trợ | C6: QH | D6: TPH | E6: TB | F6: 535 | G6: 48 | H6: 13x19 | I6: 10000 | J6: PL | K6: 1-2013 | L6: Nhà in ST
A7: 4 | B7: Luật phòng, chống tham nhũng năm 2005, sửa đổi, bổ sung năm 2007, 2012 | C7: QH | D7: TPH | E7: 1 | F7: 3500 | G7: 164 | H7: 13x19 | I7: 24000 | J7: PL | K7: 1-2013 | L7: In và VHP
A8: 5 | B8: Luật sửa đổi, bổ sung một số điều của Luật quản lý thuế (Tủ sách pháp luật phổ thông) | C8: QH | D8: TPH | E8: 1 | F8: 2400 | G8: 156 | H8: 13x19 | I8: 23000 | J8: PL | K8: 1-2013 | L8: Nhà in ST
A9: 6 | B9: Hỏi - đáp về Bộ luật lao động năm 2012 | C9: Thanh Nga (Chủ biên) | D9: TPH | E9: 1 | F9: 850 | G9: 256 | H9: 13x19 | I9: 36000 | J9: PL | K9: 1-2013 | L9: In và VHP
A10: 7 | B10: Chế độ tổng thống Hợp chúng quốc Hoa Kỳ và sự hình thành Nhà nước pháp quyền Mỹ (Sách tham khảo) | C10: TS. Nguyễn Tất Đạt (Nguyễn Chí Du) | D10: TPH | E10: 1 | F10: 530 | G10: 192 | H10: 13x19 | I10: 28000 | J10: Đảng | K10: 1-2013 | L10: Thuận Phát
A11: 8 | B11: Hồ Chí Minh tiểu sử | C11: Bảo tàng Hồ Chí Minh | D11: TPH | E11: TB | F11: 1535 | G11: 280 | H11: 12,5x20,5 | I11: 49000 | J11: KĐLL | K11: 1-2013 | L11: Nhà in ST
A12: 9 | B12: Mỹ thuật môi trường đô thị Thăng Long - Hà Nội | C12: TS. Nguyễn Văn Dương | D12: TPH | E12: 1 | F12: 500 | G12: 228 | H12: 14,5x20,5 | I12: 67000 | J12: Đảng | K12: 1-2013 | L12: Tổng cục CNQP
A13: 10 | B13: Văn kiện Đại hội đại biểu toàn quốc lần thứ XI | C13: Đảng Cộng sản Việt Nam | D13: TPH | E13: TB | F13: 8535 | G13: 338 | H13: 13x19 | I13: 32000 | J13: Đảng | K13: 1-2013 | L13: In và VHP
A14: 11 | B14: Năm quốc tế Hợp tác xã - 2012 "Hợp tác xã xây dựng thế giới tốt đẹp hơn" | C14: Liên minh Hợp tác xã Việt Nam, TS. Đào Xuân Cần (CB) | D14: LKTG | E14: 1 | F14: 2000 | G14: 260 | H14: 14,5x20,5 | I14: 0 | J14: GK | K14: 1-2013 | L14: Ngọc Châu
A15: 12 | B15: Luật thuế thu nhập cá nhân năm 2007 sđ, bs năm 2012 | C15: QH | D15: TPH | E15: 1 | F15: 3000 | G15: 72 | H15: 13x19 | I15: 14000 | J15: PL | K15: 1-2013 | L15: Tổng cục CNQP | M15: BC tuần (14 đến 18/1): 23
A16: 13 | B16: Luật Thủ đô | C16: QH | D16: TPH | E16: 1 | F16: 4000 | G16: 32 | H16: 13x19 | I16: 8000 | J16: PL | K16: 1-2013 | L16: Nhà in ST
A17: 14 | B17: Nghị quyết của Quốc hội về việc lấy phiếu tín nhiệm, bỏ phiếu tín nhiệm đối với người giữ chức vụ do Quốc hội, Hội đồng nhân dân bầu hoặc phê chuẩn | C17: QH | D17: TPH | E17: 1 | F17: 1100 | G17: 24 | H17: 13x19 | I17: 8000 | J17: PL | K17: 1-2013 | L17: Nhà in ST
A18: 15 | B18: Luật sđ, bs một số điều của Luật luật sư | C18: QH | D18: TPH | E18: 1 | F18: 1850 | G18: 144 | H18: 13x19 | I18: 22000 | J18: PL | K18: 1-2013 | L18: Thuận Phát
A19: 16 | B19: Luật quản lý thuế năm 2006 sđ, bs năm 2012 | C19: QH | D19: TPH | E19: 1 | F19: 2700 | G19: 252 | H19: 13x19 | I19: 34000 | J19: PL | K19: 1-2013 | L19: In sách VN
A20: 17 | B20: Luật sđ, bs một số điều của Luật phòng, chống tham nhũng | C20: QH | D20: TPH | E20: 1 | F20: 2000 | G20: 96 | H20: 13x19 | I20: 16000 | J20: PL | K20: 1-2013 | L20: Nhà in ST
A21: 18 | B21: Luật dự trữ quốc gia | C21: QH | D21: TPH | E21: 1 | F21: 3200 | G21: 56 | H21: 13x19 | I21: 11000 | J21: PL | K21: 1-2013 | L21: Nhà in ST
A22: 19 | B22: Luật sđ, bs một số điều của Luật điện lực | C22: QH | D22: TPH | E22: 1 | F22: 1800 | G22: 100 | H22: 13x19 | I22: 17000 | J22: PL | K22: 1-2013 | L22: Học Liệu
A23: 20 | B23: Luật điện lực năm 2004 sđ, bs năm 2012 | C23: QH | D23: TPH | E23: 1 | F23: 1700 | G23: 168 | H23: 13x19 | I23: 24000 | J23: PL | K23: 1-2013 | L23: Học Liệu
A24: 21 | B24: Luật luật sư năm 2006 sđ, bs năm 2012 | C24: QH | D24: TPH | E24: 1 | F24: 2840 | G24: 220 | H24: 13x19 | I24: 30000 | J24: PL | K24: 1-2013 | L24: Thuận Phát
A25: 22 | B25: Báo cáo chính trị của Ban Chấp hành Trung ương Đảng khóa X tại Đại hội đại biểu toàn quốc lần thứ XI | C25: Đảng Cộng sản VN | D25: TPH | E25: TB | F25: 5735 | G25: 128 | H25: 13x19 | I25: 17000 | J25: Đảng | K25: 1-2013 | L25: Nhà in ST
A26: 23 | B26: Chiến lược phát triển kinh tế- xã hội 2011-2020 | C26: Đảng Cộng sản VN | D26: TPH | E26: TB | F26: 7035 | G26: 68 | H26: 13x19 | I26: 10000 | J26: Đảng | K26: 1-2013 | L26: Thuận Phát
A27: 24 | B27: Cương lĩnh xây dựng đất nước trong thời kỳ quá độ lên chủ nghĩa xã hội (Bổ sung, phát triển năm 2011) | C27: Đảng Cộng sản VN | D27: TPH | E27: TB | F27: 5235 | G27: 36 | H27: 13x19 | I27: 7000 | J27: Đảng | K27: 1-2013 | L27: Thuận Phát
A28: 25 | B28: Nghiên cứu so sánh Hiến pháp các quốc gia ASEAN | C28: Đại học Luật Hà Nội, TS. Tô Văn Hòa | D28: TPH | E28: 1 | F28: 600 | G28: 404 | H28: 14,5x20,5 | I28: 65000 | J28: PL | K28: 1-2013 | L28: Nhà in ST
A29: 26 | B29: Lực lượng vũ trang tỉnh Bạc Liêu - 30 năm xây dựng và chiến đấu bảo vệ Tổ quốc (1975-2005) | C29: Đảng ủy- Bộ Chỉ huy quân sự tỉnh Bạc Liêu | D29: LKTG | E29: 1 | F29: 600 | G29: 332 | H29: 14,5x20,5 | I29: 0 | J29: CN Cần Thơ | K29: 1-2013 | L29: In Tổng hợp Cần Thơ
A30: 27 | B30: Lịch sử đấu tranh cách mạng của Đảng bộ và nhân dân xã Bình Thới (1930-1975) | C30: Ban Chấp hành Đảng bộ xã Bình Thới | D30: LKTG | E30: 1 | F30: 320 | G30: 224 | H30: 14,5x20,5 | I30: 0 | J30: Đảng | K30: 1-2013 | L30: Phú Thịnh
A31: 28 | B31: Sổ tay người đại biểu nhân dân | D31: QLP | E31: 1 | F31: 10000 | G31: 208 | H31: 16x24 | I31: 65000 | J31: KĐLL | K31: 1-2013 | L31: Đông Dương
A32: 29 | B32: Sổ tay đảng viên | D32: QLP | E32: 1 | F32: 10000 | G32: 208 | H32: 16x24 | I32: 65000 | J32: KĐLL | K32: 1-2013 | L32: Đông Dương
A33: 30 | B33: Sổ sinh hoạt chi bộ | D33: QLP | E33: 1 | F33: 1000 | G33: 192 | H33: 19x27 | I33: 80000 | J33: KĐLL | K33: 1-2013 | L33: Thuận Thiên Phú
A34: 31 | B34: Lịch sử Nghệ An, tập I, từ nguyên thủy đến Cách mạng Tháng Tám 1945 | C34: Tỉnh ủy- HĐND-UBND tỉnh Nghệ An | D34: LKTG | E34: 1 | F34: 1000 | G34: 1044 | H34: 16x24 | I34: 0 | J34: Đảng | K34: 1-2013 | L34: Phú Thịnh
A35: 32 | B35: Lịch sử Nghệ An, tập I, từ năm 1945 đến năm 2005 | C35: Tỉnh ủy- HĐND-UBND tỉnh Nghệ An | D35: LKTG | E35: 1 | F35: 1000 | G35: 845 | H35: 16x24 | I35: 0 | J35: Đảng | K35: 1-2013 | L35: Phú Thịnh
A36: 33 | B36: Các lý thuyết kinh tế vận dụng vào Việt Nam, tập 2 | C36: Hội đồng lý luận TW | D36: TWĐH | E36: 1 | F36: 1000 | G36: 540 | H36: 16x24 | I36: 0 | J36: KT | K36: 1-2013 | L36: Tiến bộ
A37: 34 | B37: Phát triển kinh tế tri thức trên địa bàn Thành phố Hà Nội giai đoạn 2011-2020 | C37: Viện nghiên cứu phát triển KT-XH Hà Nội, TS. Ng. Đình Dương- TS. Ng. Thành Công (Đồng CB) | D37: LKTG | E37: 1 | F37: 300 | G37: 480 | H37: 16x24 | I37: 0 | J37: Đảng | K37: 1-2013 | L37: Phú Thịnh
A38: 35 | B38: Tài liệu bồi dưỡng lý luận chính trị dành cho đảng viên mới | C38: Ban Tuyên giáo Trung ương | D38: TPH | E38: TB | F38: 2036 | G38: 212 | H38: 13x19 | I38: 27000 | J38: GK | K38: 1-2013 | L38: Bình Định | M38: BC tuần (21 đến 25/1): 16
A39: 36 | B39: Tài liệu học tập lý luận chính trị dành cho học viên lớp đối tượng kết nạp Đảng | C39: Ban Tuyên giáo Trung ương | D39: TPH | E39: TB | F39: 4036 | G39: 212 | H39: 13x19 | I39: 27000 | J39: GK | K39: 1-2013 | L39: Bình Định
A40: 37 | B40: Luật công chứng | C40: QH | D40: TPH | E40: TB | F40: 1035 | G40: 56 | H40: 13x19 | I40: 11000 | J40: PL | K40: 1-2013 | L40: Nhà in ST
A41: 38 | B41: Luật công an nhân dân | C41: QH | D41: TPH | E41: TB | F41: 1035 | G41: 40 | H41: 13x19 | I41: 9000 | J41: PL | K41: 1-2013 | L41: Nhà in ST
A42: 39 | B42: Luật quản lý nợ công | C42: QH | D42: TPH | E42: TB | F42: 1035 | G42: 52 | H42: 13x19 | I42: 11000 | J42: PL | K42: 1-2013 | L42: Nhà in ST
A43: 40 | B43: Luật trọng tài thương mại | C43: QH | D43: TPH | E43: NB 2012 | F43: 500 | G43: 72 | H43: 13x19 | I43: 11000 | J43: PL | K43: 1-2013 | L43: Nhà in ST
A44: 41 | B44: Nghị định của Chính phủ hướng dẫn thi hành Luật chứng khoán | C44: QH | D44: TPH | E44: 1 | F44: 600 | G44: 244 | H44: 13x19 | I44: 30000 | J44: PL | K44: 1-2013 | L44: Nhà in ST
A45: 42 | B45: Tư tưởng Hồ Chí Minh và Đảng Cộng sản Việt Nam về xây dựng con người mới, văn hóa mới | C45: Nguyễn Trung Thu | D45: TPH | E45: 1 | F45: 600 | G45: 368 | H45: 14,5x20,5 | I45: 60000 | J45: KĐLL | K45: 1-2013 | L45: In và VHP
A46: 43 | B46: Quản lý nhà nước về bưu chính, viễn thông và công nghệ thông tin (Dùng cho đào tạo cán bộ quản lý và quản trị kinh doanh | C46: TS. Lê Minh Toàn | D46: TPH | E46: 1 | F46: 620 | G46: 356 | H46: 14,5x20,5 | I46: 58000 | J46: KT | K46: 1-2013 | L46: Nhà in ST
A47: 44 | B47: Vai trò của Hội bảo vệ người tiêu dùng trong việc bảo vệ người tiêu dùng | C47: TS. Ng.T. Vân Anh (CB) | D47: TPH | E47: 1 | F47: 600 | G47: 264 | H47: 14,5x20,5 | I47: 45000 | J47: KT | K47: 1-2013 | L47: Nhà in ST
A48: 45 | B48: Mô hình tập đoàn kinh tế nhà nước ở Việt Nam đến năm 2020 | C48: GS, TS. Phạm Quang Trung (CB) | D48: TPH | E48: 1 | F48: 530 | G48: 352 | H48: 14,5x20,5 | I48: 57000 | J48: KT | K48: 1-2013 | L48: In sách VN
A49: 46 | B49: Lịch sử Đảng bộ và nhân dân xã Vĩnh Khê (1930-2010) | C49: Huyện ủy Vĩnh Linh- BCH ĐB xã Vĩnh Khê | D49: LKTG | E49: 1 | F49: 250 | G49: 264 | H49: 14,5x20,5 | I49: 0 | J49: KT | K49: 1-2013 | L49: Bình Định
A50: 47 | B50: Lịch sử Đảng bộ và nhân dân xã Vĩnh Tân (1930-2010) | C50: ĐB huyện Vĩnh Linh- BCH ĐB xã Vĩnh Tân | D50: LKTG | E50: 1 | F50: 400 | G50: 204 | H50: 14,5x20,5 | I50: 0 | J50: KT | K50: 1-2013 | L50: Bình Định
A51: 48 | B51: Thân thế và sự nghiệp Cụ Huỳnh Thúc Kháng (1876-1947) | C51: UBND tỉnh Quảng Nam | D51: LKTG | E51: 1 | F51: 500 | G51: 860 | H51: 14,5x20,5 | I51: 0 | J51: Đảng | K51: 1-2013 | L51: Bình Định
A52: 49 | B52: Manufacturing and Environment Management | C52: Soemon Takakuwa (CB), Nguyen Hong Son, Nguyen Dang minh (Đồng CB) | D52: LKTG | E52: 1 | F52: 500 | G52: 372 | H52: 16x24 | I52: 500000 | J52: QT | K52: 1-2013 | L52: Phú Thịnh
A53: 50 | B53: Quản lý văn hóa Việt Nam trong tiến trình đổi mới và hội nhập quốc tế | C53: Phan Hồng Giang- Bùi Hoài Sơn (Đồng CB) | D53: TWĐH+TPH | E53: 1 | F53: 1000 | G53: 532 | H53: 16x24 | I53: 0 | J53: Đảng | K53: 1-2013 | L53: In sách VN | M53: BC tháng 1: 84
A54: 51 | B54: Luật cạnh tranh năm 2004 (song ngữ V-A) The law on competition in 2004 | C54: QH | D54: TPH | E54: 1 | F54: 650 | G54: 168 | H54: 13x19 | I54: 26000 | J54: PL | K54: 1-2013 | L54: Nhà in ST | M54: BC tuần (28/1 đến 1/2): 12
A55: 52 | B55: Luật công đoàn | C55: QH | D55: TPH | E55: 1 | F55: 1535 | G55: 32 | H55: 13x19 | I55: 8000 | J55: PL | K55: 1-2013 | L55: Nhà in ST
A56: 53 | B56: Hướng dẫn nghiệp vụ công tác văn phòng cấp ủy ở cơ sở | C56: Đỗ Quốc Toán (CB), Phạm T. Thinh | D56: TPH | E56: 1 | F56: 900 | G56: 208 | H56: 12,5x20,5 | I56: 37000 | J56: Đảng | K56: 1-2013 | L56: Nhà in ST
A57: 54 | B57: Nghị định số 136/2007/NĐ-CP của Chính phủ về xuất cảnh, nhập cảnh của công dân VN được sđ, bs theo Nghị định số 65/2012/NĐ-CP của Chính phủ | C57: QH | D57: TPH | E57: 1 | F57: 770 | G57: 84 | H57: 13x19 | I57: 15000 | J57: PL | K57: 1-2013 | L57: Nhà in ST
A58: 55 | B58: Sổ tay công tác phòng, chống tham nhũng | C58: Thanh tra Chính phủ - Viện KH Thanh tra | D58: TPH | E58: 1 | F58: 400 | G58: 180 | H58: 12,5x20,5 | I58: 33000 | J58: Đảng | K58: 1-2013 | L58: Nhà in ST
A59: 56 | B59: Nghị định số 85/2009/NĐ-CP hướng dẫn thi hành Luật đấu thầu và lựa chọn nhà thầu theo Luật xây dựng sđ, bs theo Nghị định số 68/2012/NĐ-CP | C59: QH | D59: TPH | E59: 1 | F59: 560 | G59: 304 | H59: 13x19 | I59: 40000 | J59: PL | K59: 1-2013 | L59: Nhà in ST
A60: 57 | B60: Lối sống và tư duy của cộng đồng người Việt vùng Đông Nam Bộ trong quá trình đổi mới và hội nhập quốc tế | C60: PGS, TS. Doãn Chính (CB) | D60: TPH | E60: 1 | F60: 500 | G60: 736 | H60: 14,5x20,5 | I60: 139000 | J60: KĐLL | K60: 1-2013 | L60: In sách VN
A61: 58 | B61: Lịch sử biên niên Đảng Cộng sản Việt Nam, tập III - Đảng lãnh đạo kháng chiến và kiến quốc (1945-1954) (Xuất bản lần thứ hai) | C61: Học viện CT-HC QG HCM- Viện Lịch sử Đảng | D61: TPH | E61: TB | F61: 400 | G61: 1044 | H61: 14,5x20,5 | I61: 185000 | J61: GK | K61: 1-2013 | L61: Nhà in ST
A62: 59 | B62: Tài liệu phục vụ việc tổ chức lấy ý kiến nhân dân về dự thảo sửa đổi Hiến pháp năm 1992 | C62: UB dự thảo sửa đổi Hiến pháp năm 1992 | D62: LKTG | E62: 1 | F62: 2500 | G62: 252 | H62: 16x24 | I62: 0 | J62: PL | K62: 1-2013 | L62: Truyền thông VN
A63: 60 | B63: Cục diện thế giới đến 2020 (Sách tham khảo) | C63: Học viện Ngoại giao - Phạm Bình Minh (CB) | D63: TPH | E63: TB | F63: 600 | G63: 600 | H63: 16x24 | I63: 124000 | J63: QT | K63: 1-2013 | L63: Truyền thông VN
A64: 61 | B64: Đồng chí Phạm Hùng với cách mạng VN và quê hương Vĩnh Long | C64: Ban Tuyên giáo Trung ương- Học viện CT-HC QG HCM- Tỉnh ủy Vĩnh Long | D64: LKTG | E64: TB | F64: 300 | G64: 496 | H64: 16x24 | I64: 0 | J64: Đảng | K64: 1-2013 | L64: Phú Thịnh
A65: 62 | B65: Đồng chí Võ Chí Công với cách mạng VN và quê hương Quảng Nam- Đà Nẵng | C65: Ban Tuyên giáo Trung ương- Học viện CT-HC QG HCM- Tỉnh ủy Quảng Nam | D65: LKTG | E65: 1 | F65: 500 | G65: 640 | H65: 16x24 | I65: 0 | J65: Đảng | K65: 1-2013 | L65: Phú Thịnh
A66: 63 | B66: Lịch sử Đảng bộ và nhân dân xã Tây Phong (1930-2010) | C66: BCH ĐB xã Tây Phong | D66: LKTG | E66: 1 | F66: 350 | G66: 368 | H66: 14,5x20,5 | I66: 0 | J66: KĐLL | K66: 1-2013 | L66: Phú Thịnh | M66: BC tuần (4 đến 7/2): 12 | R66: 540
A67: 64 | B67: Triết lý giáo dục thế giới và VN | C67: Phạm Minh Hạc | D67: TPH | E67: 1 | F67: 630 | G67: 483 | H67: 14,5x20,5 | I67: 76000 | J67: Đảng | K67: 1-2013 | L67: Thuận Phát
A68: 65 | B68: Tìm hiểu tác phẩm Tư bản của C. Mác | C68: PGS, TS. Ng. Minh Khải, PGS, TS. Bùi Ngọc Quỵnh (Đồng CB) | D68: TPH | E68: 1 | F68: 500 | G68: 556 | H68: 14,5x20,5 | I68: 87000 | J68: Đảng | K68: 1-2013 | L68: Học Liệu
A69: 66 | B69: Lịch sử đấu tranh cách mạng của Đảng bộ và nhân dân xã Bình Châu (1930-1975) | C69: BCH ĐB xã Bình Châu | D69: LKTG | E69: 1 | F69: 500 | G69: 240 | H69: 14,5x20,5 | I69: 0 | J69: KT | K69: 1-2013 | L69: Ngọc Châu
A70: 67 | B70: Lịch sử Mặt trận Tổ quốc tỉnh Phú Yên (1930-2010) | C70: UB MTTQVN tỉnh Phú Yên | D70: LKTG | E70: 1 | F70: 1000 | G70: 360 | H70: 14,5x20,5 | I70: 0 | J70: Đảng | K70: 1-2013 | L70: Phú Thịnh
A71: 68 | B71: Một số vấn đề cơ bản về chính sách xã hội ở VN hiện nay | C71: GS, TS. Mai Ngọc Cường (CB) | D71: TPH | E71: 1 | F71: 500 | G71: 404 | H71: 14,5x20,5 | I71: 65000 | J71: KT | K71: 1-2013 | L71: Nhà in ST
A72: 69 | B72: Luật thi đua, khen thưởng năm 2003 (sửa đổi, bổ sung năm 2005, 2009) và VBHDTH (TB lần thứ hai, có bs) | C72: QH | D72: TPH | E72: TB | F72: 535 | G72: 388 | H72: 14,5x20,5 | I72: 59000 | J72: PL | K72: 1-2013 | L72: Nhà in ST
A73: 70 | B73: Chiến lược nhân tài của Trung Quốc từ năm 1978 đến nay (XB lần thứ hai) | C73: TS. Ng.T. Thu Phương (CB) | D73: QLP | E73: TB | F73: 200 | G73: 316 | H73: 14,5x20,5 | I73: 0 | J73: KĐLL | K73: 12-2012 | L73: Phú Thịnh
A74: 71 | B74: Foresight và cách tiếp cận foresight trong xây dựng chiến lược nguồn nhân lực giảng dạy công nghệ thông tin | C74: GS, TS. Trần Thọ Đạt (CB) | D74: QLP | E74: 1 | F74: 500 | G74: 324 | H74: 14,5x20,5 | I74: 64000 | J74: KT | K74: 1-2013 | L74: XN in VHDT
A75: 72 | B75: Ba người khổng lồ trong kinh tế học: Adam Smith, Các Mác và John Maynard Keynes | C75: Mark Skousen | D75: TWĐH+TPH | E75: 1 | F75: 1000 | G75: 380 | H75: 14,5x20,5 | I75: 0 | J75: KT | K75: 1-2013 | L75: Tiến bộ
A76: 73 | B76: Tham nhũng từ góc nhìn của người dân, doanh nghiệp và cán bộ, công chức, viên chức- Kết quả khảo sát xã hội học (XB lần thứ hai) (Sách tham khảo) | C76: The World Bank, Thanh tra VN | D76: LKTG | E76: TB | F76: 1000 | G76: 128 | H76: 20,5x28 | I76: 0 | J76: KT | K76: 1-2012 | L76: In và VHP
A77: 74 | B77: Corruption from the Perspective of Citizens, Firms, and Public Officials - Results of Sociological Surveys (Second editon) (Reference book) | C77: The World Bank, Thanh tra VN | D77: LKTG | E77: TB | F77: 1000 | G77: 128 | H77: 20,5x28 | I77: 0 | J77: KT | K77: 1-2013 | L77: In và VHP
A78: 75 | B78: Thủ Dầu Một - Bình Dương: Đất nước - con người | C78: Sở Văn hóa, Thể thao và Du lịch tỉnh Bình Dương, TS. Hồ Sơn Điệp (CB) | D78: LKTG | E78: 1 | F78: 930 | G78: 480 | H78: 16x24 | I78: 0 | J78: CN tp HCM | K78: 12-2012 | L78: Fahasa | M78: BC tuần (18 đến 22/2): 14
A79: 76 | B79: Nguyễn Duy Trinh - Người cộng sản kiên cường, nhà ngoại giao tài năng (Hồi ký) | D79: Trợ giá 50% | E79: TB | F79: 500 | G79: 484 | H79: 16x24 | I79: 0 | J79: Đảng | K79: 1-2013 | L79: In và VHP
A80: 77 | B80: Đảng với vấn đề nông dân, nông nghiệp và nông thôn (1930-1975) | C80: PGS, TS. Vũ Quang Hiển (CB) | D80: TPH | E80: 1 | F80: 480 | G80: 440 | H80: 16x24 | I80: 98000 | J80: Đảng | K80: 2-2013 | L80: Phú Thịnh
A81: 78 | B81: Phong trào dân tộc dân chủ ở Nam Kỳ 1930-1945, nghiên cứu qua tài liệu lưu trữ | C81: TS. Phạm Thị Huệ | D81: TPH | E81: 1 | F81: 550 | G81: 400 | H81: 16x24 | I81: 95000 | J81: PL | K81: 1-2013 | L81: In sách VN
A82: 79 | B82: Hội đồng nhân dân huyện Thanh Trì - Những chặng đường phát triển (1961-2011) | C82: HĐND huyện Thanh Trì | D82: LKTG | E82: 1 | F82: 300 | G82: 320 | H82: 16x24 | I82: 0 | J82: Đảng | K82: 1-2013 | L82: Phú Thịnh
A83: 80 | B83: Giáo trình lý luận về Nhà nước và pháp luật (TB lần thứ nhất có sc, bs) | C83: Trường ĐH Luật Hà Nội, PGS, TS. Ng. Minh Đoan | D83: TPH | E83: TB | F83: 535 | G83: 516 | H83: 14,5x20,5 | I83: 81000 | J83: PL | K83: 1-2013 | L83: Tổng cục CNQP
A84: 81 | B84: Lịch sử công tác đảng, công tác chính trị Lực lượng vũ trang tỉnh Bạc Liêu (1945-1975) | C84: Đảng ủy- Bộ Chỉ huy quân sự tỉnh Bạc Liêu | D84: LKTG | E84: 1 | F84: 600 | G84: 336 | H84: 14,5x20,5 | I84: 0 | J84: CN Cần Thơ | K84: 12-2012 | L84: In Tổng hợp Cần Thơ
A85: 82 | B85: Làng khoa bảng Tả Thanh Oai | C85: Đảng ủy- HĐND- UBND- UB MTTQ xã Tả Thanh Oai huyện Thanh Trì, TP.HN | D85: LKTG | E85: 1 | F85: 1000 | G85: 192 | H85: 14,5x20,5 | I85: 0 | J85: Đảng | K85: 1-2013 | L85: Phú Thịnh
A86: 83 | B86: Văn bản hướng dẫn thi hành Luật phòng cháy và chữa cháy năm 2001 (ban hành từ tháng 5-2012 đến tháng 11-2012) | C86: QH | D86: TPH | E86: 1 | F86: 780 | G86: 104 | H86: 13x19 | I86: 17000 | J86: PL | K86: 1-2013 | L86: Nhà in ST
A87: 84 | B87: Biên niên lịch sử thị trấn Thanh Bình (1987-2010) | C87: BCH ĐB thị trấn Thanh Bình, huyện Thanh Bình, tỉnh Đồng Tháp | D87: QLP | E87: 1 | F87: 300 | G87: 120 | H87: 14,5x20,5 | I87: 0 | J87: CN Cần Thơ | K87: 1-2013 | L87: In Tổng hợp Cần Thơ
A88: 85 | B88: Sáng mãi xứ sở hiền tài | C88: Ng. Phan Thọ | D88: TPH | E88: 1 | F88: 480 | G88: 140 | H88: 14,5x20,5 | I88: 28000 | J88: GK | K88: 1-2013 | L88: Nhà in ST
A89: 86 | B89: Luật cạnh tranh | C89: QH | D89: TPH | E89: TB | F89: 1535 | G89: 80 | H89: 13x19 | I89: 12000 | J89: PL | K89: 1-2013 | L89: Nhà in ST
A90: 87 | B90: Luật đo lường năm 2011 và VBHDTH | C90: QH | D90: TPH | E90: 1 | F90: 950 | G90: 100 | H90: 13x19 | I90: 17000 | J90: PL | K90: 1-2013 | L90: Nhà in ST
A91: 88 | B91: Luật giám định tư pháp | C91: QH | D91: TPH | E91: TB | F91: 2035 | G91: 56 | H91: 13x19 | I91: 11000 | J91: PL | K91: 1-2013 | L91: Nhà in ST
A92: 89 | B92: Tài liệu học tập Nghị quyết Hội nghị lần thứ sáu Ban Chấp hành Trung ương Đảng Cộng sản Việt Nam khóa XI (Dùng cho cán bộ, đảng viên ở cơ sở) (Tái bản) | C92: Ban Tuyên giáo Trung ương | D92: TPH | E92: TB | F92: 15035 | G92: 108 | H92: 13x19 | I92: 13500 | J92: GK | K92: 2/2013 | L92: Tiến bộ | M92: BC tuần (25/2 đến 1/3): 16
A93: 90 | B93: Pháp lệnh khai thác và bảo vệ công trình thủy lợi năm 2001 và các nghị định hướng dẫn thi hành | C93: QH | D93: TPH | E93: 1 | F93: 470 | G93: 144 | H93: 13x19 | I93: 23000 | J93: PL | K93: 2/2013 | L93: Nhà in ST
A94: 91 | B94: Luật xây dựng năm 2003 được sđ, bs năm 2009 | C94: QH | D94: TPH | E94: TB | F94: 1035 | G94: 124 | H94: 13x19 | I94: 20000 | J94: PL | K94: 2/2013 | L94: Nhà in ST
A95: 92 | B95: Bác Hồ với những mùa xuân kháng chiến | C95: Ngô Quân Lập (Sưu tầm, biên soạn) | D95: LKTG+TPH | E95: 1 | F95: 1500 | G95: 82 | H95: 13x19 | I95: 15000 | J95: KĐLL | K95: 2/2013 | L95: In sách VN
A96: 93 | B96: Tội phạm, cấu thành tội phạm - Những vấn đề lý luận và thực tiễn (Sách chuyên khảo) | C96: Thiếu tướng, TS. Ng. Ngọc Thế | D96: TPH | E96: 1 | F96: 670 | G96: 256 | H96: 14,5x20,5 | I96: 44000 | J96: PL | K96: 2/2013 | L96: Học Liệu
A97: 94 | B97: Văn hóa kinh doanh ở Việt Nam hiện nay | C97: TS. Ng. T. Ngọc Anh | D97: TPH | E97: 1 | F97: 500 | G97: 244 | H97: 14,5x20,5 | I97: 42000 | J97: KĐLL | K97: 2/2013 | L97: Học Liệu
A98: 95 | B98: Sổ tay pháp luật dành cho cán bộ cơ sở (Tủ sách pháp luật phổ thông) | C98: PGS, TS. Ng.Ngọc Chí | D98: TPH | E98: 1 | F98: 600 | G98: 276 | H98: 12,5x20,5 | I98: 47000 | J98: PL | K98: 2/2013 | L98: Thuận Phát
A99: 96 | B99: Những nguyên lý cơ bản của chủ nghĩa M-L (Hỏi- đáp) | C99: PGS, TS. Ng. Văn Hòa (Chủ biên) | D99: QLP | E99: TB | F99: 3500 | G99: 304 | H99: 14,5x20,5 | I99: 56000 | J99: KĐLL | K99: 2/2013 | L99: Hưng Hà
A100: 97 | B100: Tài liệu nghiên cứu Nghị quyết Hội nghị lần thứ sáu Ban Chấp hành Trung ương Đảng Cộng sản Việt Nam khóa XI (Dùng cho cán bộ chủ chốt và báo cáo viên) | C100: Ban Tuyên giáo Trung ương | D100: TPH | E100: TB | F100: 15035 | G100: 332 | H100: 13x19 | I100: 35600 | J100: GK | K100: 2/2013 | L100: Tiến bộ
A101: 98 | B101: Luật khiếu nại năm 2011 và văn bản hướng dẫn thi hành | C101: QH | D101: TPH | E101: 1 | F101: 1560 | G101: 104 | H101: 13x19 | I101: 17000 | J101: PL | K101: 2/2013 | L101: Nhà in ST
...

Sheet 2014
B1: SÁCH XUẤT BẢN NĂM 2014
A3: TT | B3: Tên sách | C3: Tác giả | D3: Phương thức | F3: Số lượng in | G3: Số trang | H3: Khổ sách | I3: Giá bìa | J3: BBT | K3: QĐXB | L3: Nơi in | M3: Ghi chú
A4: 1 | B4: Tài liệu nghiên cứu Nghị quyết Hội nghị lần thứ tám Ban Chấp hành Trung ương Đảng Cộng sản Việt Nam khoá XI (Dùng cho cán bộ chủ chốt) | C4: Ban Tuyên giáo Trung ương | D4: TPH | E4: TB | F4: 5031 | G4: 108 | H4: 13x19 | I4: 11700 | J4: GK | K4: 1-2014 | L4: Tiến Bộ
A5: =A4+1 -> 2 | B5: Tài liệu hỏi - đáp Nghị quyết Hội nghị lần thứ tám Ban Chấp hành Trung ương Đảng Cộng sản Việt nam khoá XI (Dùng cho đoàn viên, hội viên các đoàn thể chính trị - xã hội và tuyên truyền rộng rãi trong nhân dân) | C5: Ban Tuyên giáo Trung ương | D5: TPH | E5: TB | F5: 5031 | G5: 36 | H5: 13x19 | I5: 4600 | J5: GK | K5: 1-2014 | L5: Tiến Bộ
A6: =A5+1 -> 3 | B6: Tài liệu học tập Nghị quyết Hội nghị lần thứ tám Ban Chấp hành Trung ương Đảng Cộng sản Việt Nam khoá XI (Dùng cho cán bộ, đảng viên ở cơ sở) | C6: Ban Tuyên giáo Trung ương | D6: TPH | E6: TB | F6: 30031 | G6: 44 | H6: 13x19 | I6: 5100 | J6: GK | K6: 1-2014 | L6: Tiến Bộ
A7: =A6+1 -> 4 | B7: Lịch sử Đảng bộ và nhân dân phường Bùi Thị Xuân (1930-2010) | C7: Đảng bộ quận Hai Bà Trưng - Ban Chấp hành Đảng bộ phường Bùi Thị Xuân | D7: LKTG | F7: 300 | G7: 208 | H7: 14,5x20,5 | I7: 0 | J7: Đ | K7: 1-2014 | L7: Phú Thịnh
A8: =A7+1 -> 5 | B8: Học tập và làm theo tư tưởng đạo đức Hồ Chí Minh qua tác phẩm Đạo đức cách mạng | C8: PGS.TS.Phạm Ngọc Anh (Chủ biên) | D8: QLP | F8: 500 | G8: 436 | H8: 14,5x20,5 | I8: 97000 | J8: KĐLL | K8: 1-2014 | L8: Phú Thịnh
A9: =A8+1 -> 6 | B9: Tài liệu tham khảo phục vụ nghiên cứu tổng kết 30 năm đổi mới | C9: Hội đồng Lý luận Trung ương | D9: TWĐH+TPH | F9: 1000 | G9: 676 | H9: 16x24 | I9: 0 | J9: KT | K9: 1-2014 | L9: Truyền thông VN | M9: BCT 20 đến 25-1-2014
A10: =A9+1 -> 7 | B10: Những giải pháp và điều kiện thực hiện phòng, chống suy thoái tư tưởng chính trị, đạo đức, lối sống trong cán bộ, đảng viên (Tái bản lần thứ hai) | C10: PGS.TS. Vũ Văn Phúc - PGS.TS. Ngô Văn Thạo (Đồng Chủ biên) | D10: TPH | E10: TB | F10: 2031 | G10: 372 | H10: 14,5x20,5 | I10: 60000 | J10: GK | K10: 1-2014 | L10: Sự thật
A11: =A10+1 -> 8 | B11: Đại hội XI của Đảng với nhiệm vụ xây dựng và bảo vệ Tổ quốc Việt Nam xã hội chủ nghĩa (Xuất bản lần thứ hai) | C11: Viện khoa học xã hội nhân văn quân sự | D11: TPH | E11: TB | F11: 2031 | G11: 376 | H11: 14,5x20,5 | I11: 61000 | J11: Đ | K11: 1-2014 | L11: Tiến Bộ
A12: =A11+1 -> 9 | B12: Một số vấn đề lý luận và thực tiễn ở Việt Nam thời kỳ mới (Sách tham khảo) | C12: PGS.TS. Đức Vượng | D12: TPH | F12: 690 | G12: 472 | H12: 14,5x20,5 | I12: 75000 | J12: GK | K12: 1-2014 | L12: Sự thật
A13: =A12+1 -> 10 | B13: Đảng lãnh đạo xây dựng và phát triển văn hoá trong thời kỳ đổi mới | C13: TS. Nguyễn Danh Tiên | D13: TPH | E13: TB | F13: 2031 | G13: 340 | H13: 14,5x20,5 | I13: 56000 | J13: GK | K13: 1-2014 | L13: Tiến Bộ
A14: =A13+1 -> 11 | B14: Tài năng và danh phận (Bút ký) | C14: Hà Minh Đức | D14: TWĐH+TPH | F14: 1000 | G14: 392 | H14: 14,5x20,5 | I14: 0 | J14: QT | K14: 1-2014 | L14: Tiến Bộ
A15: =A14+1 -> 12 | B15: Luật hợp tác xã | C15: QH | D15: TPH | E15: TB | F15: 1031 | G15: 80 | H15: 13x19 | I15: 13000 | J15: PL | K15: 1-2014 | L15: Sự thật
A16: =A15+1 -> 13 | B16: Một số vấn đề cơ bản của khoa học luận (Dành cho hệ cử nhân chính trị) | C16: Học viện Chính trị - Hành chính khu vực I - TS. Lê Văn Thái (Chủ biên) | D16: TPH | F16: 500 | G16: 156 | H16: 14,5x20,5 | I16: 29000 | J16: Đ | K16: 1-2014 | L16: Sự thật
A17: =A16+1 -> 14 | B17: Giáo trình những nguyên lý cơ bản của chủ nghĩa Mác - Lênin dành cho sinh viên đại học, cao đẳng khối không chuyên ngành Mác - Lênin, tư tưởng Hồ Chí Minh (Tái bản có sửa chữa) | C17: Bộ Giáo dục và Đào tạo | D17: TPH | E17: TB | F17: 10031 | G17: 492 | H17: 14,5x20,5 | I17: 36000 | J17: GK | K17: 1-2014 | L17: In & VHP
A18: =A17+1 -> 15 | B18: Võ Nguyên Giáp - Một cuộc đời (Sách tham khảo) | C18: Alain Ruscio | D18: TPH | E18: TB | F18: 2031 | G18: 132 | H18: 13x19 | I18: 21000 | J18: QT | K18: 1-2014 | L18: in Sách VN
A19: =A18+1 -> 16 | B19: Công tác tư tưởng và vấn đề đào tạo cán bộ làm công tác tư tưởng (Sách chuyên khảo) (Xuất bản lần thứ ba) | C19: PGS.TS.Trần Thị Anh Đào | D19: TPH | E19: TB | F19: 2031 | G19: 260 | H19: 14,5x20,5 | I19: 30000 | J19: Đ | K19: 1-2014 | L19: in Sách VN
A20: =A19+1 -> 17 | B20: Giữ gìn bản sắc dân tộc Việt Nam trong bối cảnh toàn cầu hoá hiện nay (Sách chuyên khảo) (Xuất bản lần thứ ba) | C20: TS. Phạm Thanh Hà | D20: TPH | E20: TB | F20: 2031 | G20: 200 | H20: 14,5x20,5 | I20: 39000 | J20: Đ | K20: 1-2014 | L20: in Sách VN
A21: =A20+1 -> 18 | B21: Hỏi - đáp về xây dựng nếp sống văn minh | C21: Bộ Văn hoá, thể thao và du lịch - Cục Văn hoá cơ sở | D21: TPH | E21: TB | F21: 2031 | G21: 200 | H21: 13x19 | I21: 25000 | J21: QT | K21: 1-2014 | L21: In & VHP
A22: =A21+1 -> 19 | B22: Hỏi - đáp về "diễn biến hoà bình" và "cách mạng màu" | C22: GS.TS.Phạm Ngọc Hiền (Chủ biên), TS. Kiều Tiến Hùng - ThS. Hồ Anh Tuấn | D22: TPH | E22: TB | F22: 2031 | G22: 252 | H22: 13x19 | I22: 36000 | J22: GK | K22: 1-2014 | L22: In & VHP
A23: =A22+1 -> 20 | B23: Bệnh quan liêu trong công tác cán bộ ở nước ta hiện nay - Thực trạng, nguyên nhân và giải pháp (Sách chuyên khảo) (Xuất bản lần thứ ba) | C23: PGS.TS.Trương Thị Thông - PGS.TS.Lê Kim Việt (Đồng Chủ biên) | D23: TPH | E23: TB | F23: 2031 | G23: 200 | H23: 12,5x20,5 | I23: 29000 | J23: Đ | K23: 1-2014 | L23: In & VHP
A24: =A23+1 -> 21 | B24: Luật giao thông đường thuỷ nội địa | C24: QH | D24: TPH | E24: TB | F24: 531 | G24: 96 | H24: 13x19 | I24: 15000 | J24: PL | K24: 1-2014 | L24: Sự thật
A25: =A24+1 -> 22 | B25: Tập bài giảng phân tích hiệu quả dự án đầu tư | C25: TS.Phạm Thị Thu Hà | D25: TPH | F25: 800 | G25: 332 | H25: 14,5x20,5 | I25: 55000 | J25: KT | K25: 1-2014 | L25: Sự thật
A26: =A25+1 -> 23 | B26: Điện Biên Phủ | C26: Đại tướng Võ Nguyên Giáp | D26: TPH | E26: TB | F26: 500 | G26: 552 | H26: 14,5x20,5 | I26: 86000 | J26: KĐLL | K26: 1-2014 | L26: Tiến Bộ
A27: =A26+1 -> 24 | B27: Lý luận và kinh nghiệm của Đảng Cộng sản Việt Nam về công tác dân vận | C27: Tập thể tác giả | D27: TWĐH+TPH | F27: 1000 | G27: 240 | H27: 16x24 | I27: 0 | J27: GK | K27: 1-2014 | L27: Tiến Bộ
A28: =A27+1 -> 25 | B28: Hồ Liên - Hoàng Bích Sơn - Nhà ngoại giao đất Việt | C28: Phạm Thị Xuân Khải - Hồ Thị Thu Hà (biên soạn) | D28: TWĐH+TPH | F28: 500 | G28: 344 | H28: 16x24 | I28: 0 | J28: QT | K28: 1-2014 | L28: in Sách VN | M28: BCT 27-1 đến 14-2-2014
A29: =A28+1 -> 26 | B29: Điều lệ Đảng cộng sản Việt Nam | C29: Đảng Cộng sản Việt Nam | D29: TPH | E29: TB | F29: 5031 | G29: 72 | H29: 10x14,5 | I29: 7000 | J29: Đảng | K29: 1-2014 | L29: Tiến Bộ
A30: =A29+1 -> 27 | B30: Luật quảng cáo năm 2012 và văn bản hướng dẫn thi hành | C30: QH | D30: TPH | F30: 800 | G30: 204 | H30: 13x19 | I30: 28000 | J30: PL | K30: 1-2014 | L30: Sự thật
A31: =A30+1 -> 28 | B31: Một số vấn đề tăng cường trách nhiệm công tố trong hoạt động điều tra, gắn công tố với hoạt động điều tra theo yêu cầu cải cách tư pháp | C31: TS. Nguyễn Hải Phong (Chủ biên) | D31: QLP | F31: 5000 | G31: 204 | H31: 14,5x20,5 | I31: 0 | J31: NCKH | K31: 1-2014 | L31: In Hà Nội
A32: =A31+1 -> 29 | B32: Hội người cao tuổi VN và công tác chăm sóc phát huy vai trò người cao tuổi (Hỏi và đáp) | C32: Hà Văn Thuật | D32: TPH | F32: 470 | G32: 304 | H32: 12,5x20,5 | I32: 51000 | J32: Đảng | K32: 1-2014 | L32: Sự thật
A33: =A32+1 -> 30 | B33: Tài liệu bồi dưỡng bí thư chi bộ và cấp ủy viên ở cơ sở | C33: BTGTW | D33: TPH | E33: TB | F33: 2531 | G33: 312 | H33: 13x19 | I33: 43000 | J33: GK | K33: 1-2014 | L33: Bình Định | M33: Sách In nối ở ST
A34: =A33+1 -> 31 | B34: Tài liệu học tập lý luận chính trị dành cho học viên lớp đối tượng kết nạp Đảng | C34: BTGTW | D34: TPH | E34: TB | F34: 7031 | G34: 224 | H34: 13x19 | I34: 27000 | J34: GK | K34: 1-2014 | L34: Bình Định | M34: Sách In nối ở ST
A35: =A34+1 -> 32 | B35: Tài liệu bồi dưỡng lý luận chính trị dành cho đảng viên mới | C35: BTGTW | D35: TPH | E35: TB | F35: 5031 | G35: 220 | H35: 13x19 | I35: 27000 | J35: GK | K35: 1-2014 | L35: Bình Định | M35: Sách In nối ở ST
A36: =A35+1 -> 33 | B36: Tín ngưỡng truyền thống Việt Nam (Hỏi - Đáp) | C36: TS. Đoàn Triệu Long | D36: TPH | F36: 550 | G36: 176 | H36: 14,5x20,5 | I36: 32000 | J36: Đảng | K36: 1-2014 | L36: Sự thật
A37: =A36+1 -> 34 | B37: Sổ tay về quản lý nhà nước và kỹ năng làm việc dành cho cán bộ, công chức xã, phường, thị trấn | C37: TS. Vũ Đăng Minh (Bộ Nội vụ) | D37: TPH | F37: 1220 | G37: 440 | H37: 14,5x20,5 | I37: 70000 | J37: Đảng | K37: 1-2014 | L37: Sự thật
A38: =A37+1 -> 35 | B38: Những khía cạnh Lịch sử - Văn hóa Việt Nam và Thế giới | C38: Trường Đại học khoa học Huế (Khoa lịch sử) | D38: TPH | F38: 2081 | G38: 364 | H38: 14,5x20,5 | I38: 59000 | J38: Đảng | K38: 1-2014 | L38: CTy In Truyền thông
A39: =A38+1 -> 36 | B39: Giá trị của đạo đức Nho giáo trong thời đại ngày nay | C39: Ban Bt sách kinh điển thánh hiền Trung Hoa (Tần Đại Đồng) | D39: TWĐH+TPH | F39: 1000 | G39: 412 | H39: 14,5x20,5 | I39: 0 | J39: Đảng | K39: 1-2014 | L39: Tiến Bộ
A40: =A39+1 -> 37 | B40: Lịch sử Đảng bộ xã Triệu Trạch (1930-2010) | C40: BCH Đảng bộ xã Triệu Trạch | D40: LKTG | F40: 1000 | G40: 328 | H40: 14,5x20,5 | I40: 0 | J40: GK | K40: 1-2014 | L40: Tiến Bộ
A41: =A40+1 -> 38 | B41: Từ điển tổ chức và công tác tổ chức | C41: Lê Quang Thưởng | D41: QLP | F41: 1000 | G41: 1176 | H41: 21x29,7 | I41: 600000 | J41: Lý luận | K41: 1-2014 | L41: CTy TNHH In Thuận Thiên Phú | M41: BCT 17-21-2-2014
A42: =A41+1 -> 39 | B42: Luật thuế giá trị gia tăng năm 2008 sửa đổi, bổ sung năm 2013 và VBHDTH | C42: QH | D42: TPH | F42: 800 | G42: 156 | H42: 13x19 | I42: 23000 | J42: PL | K42: 1-2014 | L42: Sự thật
A43: =A42+1 -> 40 | B43: Chu Văn An - Người thầy của muôn đời | C43: Huyện Thanh Trì - TPHN | D43: LKTG-TPH | F43: 1500 | G43: 228 | H43: 14,5x20,5 | I43: 46000 | J43: Đ | K43: 1-2014 | L43: Phú Thịnh
A44: =A43+1 -> 41 | B44: Theo dấu chân Bác Hồ | C44: Nguyễn Đức Quý | D44: TPH | F44: 500 | G44: 228 | H44: 12,5x20,5 | I44: 40000 | J44: Đ | K44: 1-2014 | L44: Sự thật
A45: =A44+1 -> 42 | B45: Luật thuế thu nhập doanh nghiệp năm 2008 sửa đổi, bổ sung năm 2013 và VBHDTH | C45: QH | D45: TPH | F45: 550 | G45: 196 | H45: 13x19 | I45: 28000 | J45: PL | K45: 1-2014 | L45: Sự thật
A46: =A45+1 -> 43 | B46: Quy định pháp luật về hợp đồng lao động | C46: QH | D46: TPH | F46: 660 | G46: 104 | H46: 13x19 | I46: 18000 | J46: PL | K46: 1-2014 | L46: Sự thật
A47: =A46+1 -> 44 | B47: Luật phòng, chống rửa tiền năm 2012 và VBHDTH | C47: QH, CP | D47: TPH | F47: 1000 | G47: 112 | H47: 13x19 | I47: 18000 | J47: PL | K47: 1-2014 | L47: Sự thật
A48: =A47+1 -> 45 | B48: Quy định pháp luật về cấp và thu hồi chứng chỉ hành nghề giấy phép hoạt động đình chỉ hoạt động chuyên môn đối với người hành nghề cơ sở khám, chữa bệnh | C48: QH | D48: TPH | F48: 600 | G48: 168 | H48: 13x19 | I48: 26000 | J48: PL | K48: 1-2014 | L48: Sự thật
A49: =A48+1 -> 46 | B49: Một số vấn đề về giải thích pháp luật chính thức ở VN hiện nay | C49: TS. Phạm Thị Duyên Thảo | D49: TPH | F49: 500 | G49: 236 | H49: 14,5x20,5 | I49: 41000 | J49: PL | K49: 1-2014 | L49: Sự thật
A50: =A49+1 -> 47 | B50: Dẫn luận nghiên cứu APEC | C50: GS. Mạc Đường | D50: TPH | F50: 800 | G50: 280 | H50: 14,5x20,5 | I50: 63000 | J50: HCM | K50: 1-2014 | L50: Khuyến học phía Nam
A51: =A50+1 -> 48 | B51: Thanh Thản một cuộc đời | C51: Võ Anh Tuấn | D51: TPH | F51: 450 | G51: 344 | H51: 14,5x20,5 | I51: 76000 | J51: HCM | K51: 1-2014 | L51: Fahasa
A52: =A51+1 -> 49 | B52: Lịch sử dđấu tranh cách mạng của đảng bộ và nhân dân xã Nhơn Đức (1930-2010) | C52: BCH Đảng bộ huyện Nhà Bè | D52: LKTG | F52: 330 | G52: 244 | H52: 14,5x20,5 | I52: 0 | J52: HCM | K52: 1-2014 | L52: Fahasa
A53: =A52+1 -> 50 | B53: C.Mác và Ph.Ăngghen Tuyển tập, tập VI ( Tiếng Lào ) | C53: HVCTQGHCM | D53: LKTG | F53: 500 | G53: 924 | H53: 15x22 | I53: 0 | J53: GK | K53: 1-2014 | L53: Tiến Bộ | M53: BCT 21-28-2-2014
A54: =A53+1 -> 51 | B54: Bàn về giải pháp phòng, chống tham nhũng ở Việt Nam hiện nay | C54: GS.TS Trương Giang Long | D54: TWĐH+TPH | F54: 1500 | G54: 588 | H54: 16x24 | I54: 0 | J54: HCM | K54: 1-2014 | L54: Fahasa
A55: =A54+1 -> 52 | B55: Những tấm gương bình dị mà cao quý | C55: BTGTW | D55: TWĐH+LKTG | F55: 1000 | G55: 296 | H55: 16x24 | I55: 0 | J55: GK | K55: 1-2014 | L55: Cty in sách VN
A56: =A55+1 -> 53 | B56: Đan Phượng tầm nhìn và phát triển | C56: Đảng bộ huyện Đan Phượng | D56: LKTG | F56: 530 | G56: 800 | H56: 19x27 | I56: 0 | J56: NCKH | K56: 1-2014 | L56: VHP | M56: BCT 3-3 đến 7-3-2014
A57: =A56+1 -> 54 | B57: Hiến pháp nước cộng hòa xã hội chủ nghĩa Việt Nam | C57: Qh | D57: TPH | E57: TB | F57: 5031 | G57: 72 | H57: 13x19 | I57: 14000 | J57: PL | K57: 1-2014 | L57: Tổng hợp Cần thơ
A58: =A57+1 -> 55 | B58: Luật khoa học và công nghệ | C58: QH | D58: TPH | E58: TB | F58: 1031 | G58: 96 | H58: 13x19 | I58: 15000 | J58: PL | K58: 1-2014 | L58: TP.HCM
A59: =A58+1 -> 56 | B59: Luật phòng, chống khủng bố | C59: QH | D59: TPH | E59: TB | F59: 1531 | G59: 44 | H59: 13x19 | I59: 10000 | J59: PL | K59: 1-2014 | L59: TP.HCM
A60: =A59+1 -> 57 | B60: Pháp luật Việt Nam về trách nhiệm bồi thường của nhà nước | C60: Đỗ Văn Đại - Nguyễn Trương Tín | D60: TPH | F60: 470 | G60: 492 | H60: 14,5x20,5 | I60: 82000 | J60: Đ | K60: 1-2014 | L60: Sự thật
A61: =A60+1 -> 58 | B61: Du lịch lễ hội vùng đất Tây Nam Bộ | C61: Đoàn Nô | D61: TPH | F61: 600 | G61: 180 | H61: 14,5x20,5 | I61: 80000 | J61: QT | K61: 1-2014 | L61: Tổng hợp Cần thơ
A62: =A61+1 -> 59 | B62: Lịch sử đảng bộ huyện Yên Sơn (1940-2010) | C62: BCH Đảng bộ huyện Yên Sơn | D62: LKTG | F62: 1000 | G62: 400 | H62: 14,5x20,5 | I62: 0 | J62: KĐLL | K62: 1-2014 | L62: TNHH In và DVTM Phú Thịnh
A63: =A62+1 -> 60 | B63: Lịch sử đảng bộ và nhân dân xã Đông Trung (1930-2010) | C63: BCH đảng bộ xã Đông Hưng | D63: LKTG | F63: 450 | G63: 416 | H63: 14,5x20,5 | I63: 0 | J63: KĐLL | K63: 1-2014 | L63: TNHH In và DVTM Phú Thịnh
A64: =A63+1 -> 61 | B64: Lịch sử đảng bộ huyện Đức Phổ (1975-2010) | C64: BCH đảng bộ huyện Đức Phổ | D64: LKTG | F64: 1030 | G64: 276 | H64: 15x22 | I64: 0 | J64: KT | K64: 1-2014 | L64: SX thương mại Ngọc Châu
A65: =A64+1 -> 62 | B65: Người của đất | C65: Nguyễn Ký Ức | D65: LKTG | F65: 430 | G65: 236 | H65: 14,5x20,5 | I65: 0 | J65: TPHCM | K65: 1-2014 | L65: Fahasa
A66: =A65+1 -> 63 | B66: Lịch sử đấu tranh cách mạng của đảng bộ và nhân dân Vinh Hà (1930-2010) | C66: Huyện ủy Phú Vang, BCHĐB xã Vinh Hà | D66: LKTG | F66: 260 | G66: 172 | H66: 14,5x20,5 | I66: 0 | J66: Đ | K66: 1-2014 | L66: Bao bì Huế
A67: =A66+1 -> 64 | B67: 100 nhà kinh tế nổi tiếng | C67: TS.TS. Nguyễn Công Nghiệp (CB) | D67: QLP | F67: 500 | G67: 642 | H67: 19x27 | I67: 0 | J67: KT | K67: 1-2014 | L67: Công đoàn VN | M67: BC tuần 18-8 đến 22-8
A68: =A67+1 -> 65 | B68: Luật thực hành tiết kiệm chống lãng phí năm 2013 và VBHDTH | C68: QH | D68: TPH | F68: 700 | G68: 116 | H68: 13x19 | I68: 19000 | J68: PL | K68: 1-2014 | L68: Sự thật | M68: 32
A69: =A68+1 -> 66 | B69: Phát triển văn hoá với tư cách nền tảng tinh thần của xã hội | C69: TS.Trần Thị Minh | D69: TPH | F69: 520 | G69: 232 | H69: 14,5x20,5 | I69: 40000 | J69: Đ | K69: 2-2014 | L69: in Sách VN
A70: =A69+1 -> 67 | B70: Quy định pháp luật về minh bạch tài sản, thu nhập | C70: QH | D70: TPH | F70: 450 | G70: 160 | H70: 13x19 | I70: 25000 | J70: PL | K70: 2-2014 | L70: Sự thật
A71: =A70+1 -> 68 | B71: Pháp lệnh quản lý, sử dụng vũ khí, vật liệu nổ và công cụ hỗ trợ năm 2011 sửa đổi, bổ sung năm 2013 | C71: QH | D71: TPH | F71: 1000 | G71: 92 | H71: 13x19 | I71: 17000 | J71: PL | K71: 2-2014 | L71: VHP
A72: =A71+1 -> 69 | B72: Hệ thống câu hỏi và bài tập tổ chức hạch toán kế toán | C72: TS. Trần Thị Cẩm Thanh, ThS. Lê Thị Hà | D72: TPH | F72: 3520 | G72: 80 | H72: 13x19 | I72: 14000 | J72: KT | K72: 2-2014 | L72: CTy cổ phần Ngọc Châu
A73: =A72+1 -> 70 | B73: Giáo trình tổ chức hạch toán kế toán | C73: TS. Trần Thị Cẩm Thanh | D73: TPH | F73: 3600 | G73: 140 | H73: 14,5x20,5 | I73: 22000 | J73: KT | K73: 2-2014 | L73: CTy cổ phần Ngọc Châu
A74: =A73+1 -> 71 | B74: Báo mạng điện tử những vấn đề cơ bản | C74: TS. Nguyễn Thị Trường Giang | D74: TPH | F74: 1340 | G74: 312 | H74: 14,5x20,5 | I74: 43000 | J74: KT | K74: 2-2014 | L74: Sự thật
A75: =A74+1 -> 72 | B75: Tìm hiểu pháp luật về bảo tồn di sản văn hóa | C75: Lê Văn Quý | D75: TPH | F75: 640 | G75: 164 | H75: 14,5x20,5 | I75: 30000 | J75: PL | K75: 2-2014 | L75: Học Liệu
A76: =A75+1 -> 73 | B76: Giáo trình lịch sử nhà nước và pháp luật thế giới (Xuất bản lần thứ hai có sửa chữa, bổ sung) | C76: TS. Nguyễn Minh Tuấn | D76: TPH | E76: TB | F76: 800 | G76: 508 | H76: 14,5x20,5 | I76: 80000 | J76: KT | K76: 2-2014 | L76: TNHH In và DVTM Phú Thịnh
A77: =A76+1 -> 74 | B77: V.I.Lênin Tuyển tập, tập III ( Tiếng Lào ) | C77: HVCTQGHCM | D77: LKTG | F77: 500 | G77: 896 | H77: 15x22 | I77: 0 | J77: GK | K77: 2-2014
A78: =A77+1 -> 75 | B78: Khám phá lịch sử Việt Nam | C78: PGS.TS. NGƯT. Phạm Xanh | D78: TPH | F78: 700 | G78: 444 | H78: 16x24 | I78: 93000 | J78: Đ | K78: 2-2014 | L78: VHP
A79: =A78+1 -> 76 | B79: Luật điện lực năm 2004 sửa đổi, bổ sung năm 2012 và VBHDTH | C79: QH | D79: TPH | F79: 640 | G79: 208 | H79: 13x19 | I79: 29000 | J79: PL | K79: 2-2014 | L79: Sự thật
A80: =A79+1 -> 77 | B80: Luật công đoàn năm 2012 và văn bản hướng dẫn thi hành | C80: QH | D80: TPH | F80: 1000 | G80: 80 | H80: 13x19 | I80: 15000 | J80: PL | K80: 2-2014 | L80: Sự thật
A81: =A80+1 -> 78 | B81: Bộ luật hình sự năm 1999 được sửa đổi, bổ sung năm 2009 | C81: QH | D81: TPH | E81: TB | F81: 1031 | G81: 320 | H81: 13x19 | I81: 37000 | J81: PL | K81: 2-2014 | L81: Cần Thơ | M81: Sách In nối ở ST
A82: =A81+1 -> 79 | B82: Nghị định số 115/2013/NĐ-CP về quản lý, bảo quản tang vật phương tiện vi phạm hành chính bị tạm giữ, tịch thu theo thủ tục hành chính và VBHDTH | C82: QH | D82: TPH | F82: 580 | G82: 48 | H82: 13x19 | I82: 12000 | J82: PL | K82: 2-2014 | L82: Sự thật
A83: =A82+1 -> 80 | B83: Luật phòng cháy và chữa cháy năm 2001 sửa đổi, bổ sung năm 2013 | C83: QH | D83: TPH | E83: TB | F83: 2031 | G83: 120 | H83: 13x19 | I83: 18000 | J83: PL | K83: 2-2014 | L83: Tổng hợp Cần thơ
A84: =A83+1 -> 81 | B84: Luật hòa giải ở cơ sở | C84: Qh | D84: TPH | E84: TB | F84: 1031 | G84: 28 | H84: 13x19 | I84: 8000 | J84: PL | K84: 2-2014 | L84: Tổng hợp Cần thơ
A85: =A84+1 -> 82 | B85: Luật việc làm | C85: QH | D85: TPH | E85: TB | F85: 3031 | G85: 48 | H85: 13x19 | I85: 10000 | J85: PL | K85: 2-2014 | L85: Tổng hợp Cần thơ
A86: =A85+1 -> 83 | B86: Luật tiếp công dân | C86: QH | D86: TPH | E86: TB | F86: 3031 | G86: 52 | H86: 13x19 | I86: 11000 | J86: PL | K86: 2-2014 | L86: Tổng hợp Cần thơ
A87: =A86+1 -> 84 | B87: Luật thực hành tiết kiệm chống lãng phí | C87: QH | D87: TPH | E87: TB | F87: 5031 | G87: 80 | H87: 13x19 | I87: 13000 | J87: PL | K87: 2-2014 | L87: Tổng hợp Cần thơ
A88: =A87+1 -> 85 | B88: Luật đấu thầu | C88: QH | D88: TPH | E88: TB | F88: 2031 | G88: 124 | H88: 13x19 | I88: 18000 | J88: PL | K88: 2-2014 | L88: Tổng hợp Cần thơ
A89: =A88+1 -> 86 | B89: Chương trình sơ cấp lý luận chính trị (tài liệu học tập) | C89: Ban Tuyên giáo Trung ương | D89: TPH | E89: TB | F89: 1031 | G89: 368 | H89: 14,5x20,5 | I89: 50000 | J89: GK | K89: 2-2014 | L89: Tổng hợp Cần thơ
A90: =A89+1 -> 87 | B90: Giáo trình tư tưởng Hồ Chí Minh | C90: Hội đồng Trung ương, bộ môn khoa học Mác-Lênin tư tưởng HCM | D90: TPH | E90: TB | F90: 731 | G90: 500 | H90: 14,5x20,5 | I90: 79000 | J90: GK | K90: 2-2014 | L90: In Bình Định
A91: =A90+1 -> 88 | B91: Lịch sử kho xăng dầu VK102 (1974-2014) | C91: Cục hậu cần quân khu 7 | D91: LKTG | F91: 430 | G91: 204 | H91: 14,5x20,5 | I91: 0 | J91: TPHCM | K91: 2-2014 | L91: Khuyến học phía Nam
A92: =A91+1 -> 89 | B92: Nhân cách sử học | C92: Trần Văn Thọ, Nguyễn Quang Ngọc, Philiperapin | D92: QLP | F92: 500 | G92: 832 | H92: 16x24 | I92: 0 | J92: KĐLL | K92: 2-2014 | L92: In và dịch vụ Phú Thịnh | M92: BCT 10-3 đến 14-3-2014
A93: =A92+1 -> 90 | B93: Học tập và làm theo tư tưởng đạo đức Hồ Chí Minh về nêu cao tinh thần trách nhiệm, chống chủ nghĩa cá nhân, nói đi đôi với làm (tài liệu sinh hoạt chi bộ, đoàn thể và tại các cơ quan, đơn vị năm 2014) | C93: BTGTW | D93: TPH | E93: TB | F93: 20031 | G93: 120 | H93: 10x14,5 | I93: 13500 | J93: GK | K93: 2-2014 | L93: Cần Thơ | M93: Sách In nối ở ST
A94: =A93+1 -> 91 | B94: Luật Đất đai | C94: QH | D94: TPH | E94: TB | F94: 5031 | G94: 236 | H94: 14,5x20,5 | I94: 36000 | J94: Pl | K94: 2-2014 | L94: Cần Thơ
A95: =A94+1 -> 92 | B95: "Xã trưởng chơi ngông" | C95: Vũ Lân | D95: TPH | F95: 500 | G95: 256 | H95: 12,5x20,5 | I95: 44000 | J95: Đ | K95: 2-2014 | L95: TTNC và SX Học Liệu
A96: =A95+1 -> 93 | B96: Luật tài nguyên nước năm 2012 và VBHDTH | C96: QH | D96: TPH | F96: 520 | G96: 144 | H96: 13x19 | I96: 22000 | J96: PL | K96: 2-2014 | L96: Sự thật
A97: =A96+1 -> 94 | B97: Pháp lệnh sửa đổi, bổ sung một số điều của Pháp lệnh quản lý sử dụng vũ khí, vật liệu nổ và công cụ hỗ trợ | C97: QH | D97: TPH | F97: 1550 | G97: 56 | H97: 13x19 | I97: 13000 | J97: Pl | K97: 2-2014 | L97: Sự thật
A98: =A97+1 -> 95 | B98: Luật luật sư năm 2006 sửa đổi, bổ sung năm 2012 và VBHDTH | C98: QH | D98: TPH | F98: 700 | G98: 260 | H98: 13x19 | I98: 35000 | J98: PL | K98: 2-2014 | L98: Sự thật
A99: =A98+1 -> 96 | B99: Quy định pháp luật đối với lao động nữ | C99: QH | D99: TPH | F99: 570 | G99: 56 | H99: 13x19 | I99: 13000 | J99: PL | K99: 2-2014 | L99: Sự thật
A100: =A99+1 -> 97 | B100: Bộ luật tố tụng hình sự của nước CHXHCNVN | C100: QH | D100: TPH | E100: TB | F100: 5031 | G100: 256 | H100: 13x19 | I100: 40000 | J100: PL | K100: 2-2014 | L100: Sự thật | M100: Sách In nối 3-2014
